Workbook

Sheet Premissas
B2: MODELO INCENTIVO PRODUTIVIDADE — JULHO E AGOSTO | GPA | MENSAL + DIÁRIO
B4: PARÂMETROS EDITÁVEIS
B6: Faixa | C6: Fator mín | D6: Fator máx | E6: Valor MENSAL | F6: Valor DIÁRIO
B7: Não atingiu | C7: 0 | D7: 0.9999 | E7: 0 | F7: =IF(E7=0,0,E7/$C$16) -> 0
B8: 1,00 – 1,19 | C8: 1 | D8: 1.1999 | E8: 100 | F8: =IF(E8=0,0,E8/$C$16) -> 3.8461538
B9: 1,20 – 1,39 | C9: 1.2 | D9: 1.3999 | E9: 200 | F9: =IF(E9=0,0,E9/$C$16) -> 7.6923077
B10: 1,40 – 1,59 | C10: 1.4 | D10: 1.5999 | E10: 350 | F10: =IF(E10=0,0,E10/$C$16) -> 13.461538
B11: 1,60 – 1,99 | C11: 1.6 | D11: 1.8 | E11: 500 | F11: =IF(E11=0,0,E11/$C$16) -> 19.230769
B12: ≥ 2,00 (teto) | C12: 1.9 | D12: 2 | E12: 750 | F12: =IF(E12=0,0,E12/$C$16) -> 28.846154
B15: Horas Efetivas | C15: 5.5
B16: Dias úteis | C16: 26
B17: Teto mensal HC | C17: 750
B19: METAS CD1942
B20: Atividade | C20: Meta
B21: CARREGAMENTO | C21: 22
B22: RECEBIMENTO | C22: 17
B23: PUXADA RECEB | C23: 16
B24: ATIVIDADE OP. EMP. | C24: 20
B27: REGRAS
B28: 1. Empresa: se EMPRESA preenchida usa o valor; se em branco: =SE(ESQUERDA(USUÁRIO;1)="T";"TERCEIRA";"GPA").
B29: 2. Elegível: EMPRESA_AJUSTADA = GPA. Exclui TERCEIRA/TERCEIRO e SEPARAÇÃO.
B30: 3. Fator = PRODUTIVIDADE/META. Consolidação = melhor fator do HC no MÊS.
B31: 4. Pagamento MENSAL pela faixa. Valor DIÁRIO = mensal ÷ dias úteis (B13).
B32: 5. Meta em branco/zero → meta padrão CD1942. Teto = B14.
B33: 6. Simulação JULHO e AGOSTO. Base original completa na aba Base.
B34: 7. Amarelo + azul = editável. Demais células = fórmulas.
B37: CONTROLE
B38: HCs Jul | C38: =COUNTIFS(Consolidado_HC!A:A,7) -> 788
B39: Custo Jul | C39: =SUMIF(Consolidado_HC!A:A,7,Consolidado_HC!L:L) -> 214000
B40: HCs Ago | C40: =COUNTIFS(Consolidado_HC!A:A,8) -> 805
B41: Custo Ago | C41: =SUMIF(Consolidado_HC!A:A,8,Consolidado_HC!L:L) -> 204500

Sheet Simulação
A1: Faixa (Carregamento 409 FLV = 24 ) | B1: Fator mín | C1: Fator máx | D1: Alcance Qtd | E1: Qtd TT Acu. | F1: Aumento Faixa | H1: CD | I1: Indicador | J1: Categoria | K1: Meta | L1: Média Geral | M1: Cód. Unidade de Medida
A2: Alcance dia | B2: 0 | C2: 0.9999 | D2: =24*B9 -> 132 | E2: 0 | F2: 0 | H2: 409 | I2: ATIVIDADE OP. EMP. | J2: CARNES | K2: 26.991741 | L2: =AVERAGE(K2:K4) -> 25.96294 | M2: 2
A3: 1.19 | B3: 1 | C3: 1.1999 | D3: =D2+E3 -> 157.08 | E3: =D2*19% -> 25.08 | F3: =ABS(D2-D3) -> 25.08 | H3: 409 | I3: ATIVIDADE OP. EMP. | J3: F.L.V | K3: 26.171763 | M3: 2
A4: 1.39 | B4: 1.2 | C4: 1.3999 | D4: =D2+E4 -> 183.48 | E4: =D2*39% -> 51.48 | F4: =ABS(D3-D4) -> 26.4 | H4: 409 | I4: ATIVIDADE OP. EMP. | J4: MERCEARIA | K4: 24.725317 | M4: 2
A5: 1.59 | B5: 1.4 | C5: 1.5999 | D5: =D2+E5 -> 209.88 | E5: =D2*59% -> 77.88 | F5: =ABS(D4-D5) -> 26.4 | H5: 409 | I5: CARREGAMENTO | J5: CARNES | K5: 15.819599 | L5: =AVERAGE(K5:K7) -> 21.764179 | M5: 1
A6: 1.79 | B6: 1.6 | C6: 1.8 | D6: =D2+E6 -> 236.28 | E6: =D2*79% -> 104.28 | F6: =ABS(D5-D6) -> 26.4 | H6: 409 | I6: CARREGAMENTO | J6: F.L.V | K6: 24.390974 | M6: 1
A7: ≥ 2,00 (teto) | B7: 1.9 | C7: 2 | D7: =D2+E7 -> 264 | E7: =D2*100% -> 132 | F7: =ABS(D6-D7) -> 27.72 | H7: 409 | I7: CARREGAMENTO | J7: MERCEARIA | K7: 25.081963 | M7: 1
H8: 409 | I8: PUXADA RECEB | J8: CARNES | K8: 20.014969 | L8: =AVERAGE(K8:K10) -> 21.914432 | M8: 34
A9: Média Hora | B9: 5.5 | H9: 409 | I9: PUXADA RECEB | J9: F.L.V | K9: 23.865604 | M9: 34
A10: Faixa (Carregamento 409 FLV = 24 ) | B10: Fator máx | C10: Valor (Olpn/ PLT ID) | D10: Valor DIÁRIO | E10: Valor Mensal | H10: 409 | I10: PUXADA RECEB | J10: MERCEARIA | K10: 21.862723 | M10: 34
A11: Alcance dia | B11: 0.9999 | C11: 0 | D11: =IF(C11=0,0,C11/$B$16) -> 0 | E11: =D11*26 -> 0 | H11: 409 | I11: RECEBIMENTO | J11: CARNES | K11: 16.771957 | L11: =AVERAGE(K11:K13) -> 23.031803 | M11: 4
A12: 1.19 | B12: 1.1999 | C12: 0.22 | D12: =C12*F3 -> 5.5176 | E12: =D12*26 -> 143.4576 | G12: =E12/25 -> 5.738304 | H12: 409 | I12: RECEBIMENTO | J12: F.L.V | K12: 20.718359 | M12: 4
A13: 1.39 | B13: 1.3999 | C13: 0.22 | D13: =C13*F4 -> 5.808 | E13: =D13*26 -> 151.008 | H13: 409 | I13: RECEBIMENTO | J13: MERCEARIA | K13: 31.605093 | M13: 4
A14: 1.59 | B14: 1.5999 | C14: 0.22 | D14: =C14*F5 -> 5.808 | E14: =D14*26 -> 151.008
A15: 1.79 | B15: 1.8 | C15: 0.22 | D15: =C15*F6 -> 5.808 | E15: =D15*26 -> 151.008 | H15: CD | I15: Função | J15: Cód. Unidade de Medida
A16: ≥ 2,00 (teto) | B16: 2 | C16: 0.22 | D16: =C16*F7 -> 6.0984 | E16: =D16*26 -> 158.5584 | H16: 409 | I16: Carregamento | J16: 1
A17: TT | D17: =SUM(D11:D16) -> 29.04 | E17: =SUM(E11:E16) -> 755.04 | H17: 409 | I17: Carregamento+Empilhadeira | J17: 12
H18: 409 | I18: Carregamento+Empilhadeira+Puxada | J18: 123
A19: REGRAS | H19: 409 | I19: Carregamento+Empilhadeira+Puxada+Recebimento | J19: 1234
A20: 1. Utilizar metricas de valores por superação de meta | H20: 409 | I20: Carregamento+Puxada | J20: 13
A21: 2. Para atividades com sinergia trazer média | H21: 409 | I21: Carregamento+Recebimento | J21: 14
H22: 409 | I22: Empilhadeira | J22: 2
H23: 409 | I23: Empilhadeira+Puxada | J23: 23
H24: 409 | I24: Empilhadeira+Puxada+Recebimento | J24: 234
H25: 409 | I25: Empilhadeira+Recebimento | J25: 24
H26: 409 | I26: Puxada | J26: 3
H27: 409 | I27: Puxada+Recebimento | J27: 34
H28: 409 | I28: Recebimento | J28: 4

Sheet AllIn_Apoio
B1: SIMULAÇÃO ALL-IN — CAMISA 10 / APOIO / INVENTÁRIO / ROUPARIA
B3: PREMISSAS (editáveis — amarelo)
B5: Mês referência | C5: 8
B6: Dias úteis (ganho diário) | C6: =Premissas!C16 -> 26
B7: Teto mensal por HC (R$) | C7: =Premissas!C17 -> 750
B9: FAIXAS (mesmas do operacional — referenciam Premissas)
B10: Faixa | C10: Fator mín | D10: Fator máx | E10: Valor MENSAL | F10: Valor DIÁRIO
B11: =Premissas!B7 -> Não atingiu | C11: =Premissas!C7 -> 0 | D11: =Premissas!D7 -> 0.9999 | E11: =Premissas!E7 -> 0 | F11: =Premissas!F7 -> 0
B12: =Premissas!B8 -> 1,00 – 1,19 | C12: =Premissas!C8 -> 1 | D12: =Premissas!D8 -> 1.1999 | E12: =Premissas!E8 -> 100 | F12: =Premissas!F8 -> 3.8461538
B13: =Premissas!B9 -> 1,20 – 1,39 | C13: =Premissas!C9 -> 1.2 | D13: =Premissas!D9 -> 1.3999 | E13: =Premissas!E9 -> 200 | F13: =Premissas!F9 -> 7.6923077
B14: =Premissas!B10 -> 1,40 – 1,59 | C14: =Premissas!C10 -> 1.4 | D14: =Premissas!D10 -> 1.5999 | E14: =Premissas!E10 -> 350 | F14: =Premissas!F10 -> 13.461538
B15: =Premissas!B11 -> 1,60 – 1,99 | C15: =Premissas!C11 -> 1.6 | D15: =Premissas!D11 -> 1.8 | E15: =Premissas!E11 -> 500 | F15: =Premissas!F11 -> 19.230769
B16: =Premissas!B12 -> ≥ 2,00 (teto) | C16: =Premissas!C12 -> 1.9 | D16: =Premissas!D12 -> 2 | E16: =Premissas!E12 -> 750 | F16: =Premissas!F12 -> 28.846154
B18: INPUT POR CD — ALL-IN (editável)
B19: Preencha Meta, Realizado e Qtd de HCs Camisa 10/Apoio. Fator, faixa e valores calculam sozinhos.
B20: CD | C20: META_ALLIN | D20: REALIZADO_ALLIN | E20: FATOR | F20: FAIXA | G20: VALOR_MENSAL_HC | H20: VALOR_DIARIO_HC | I20: QTD_HCs_APOIO | J20: CUSTO_MENSAL_CD | K20: CUSTO_DIARIO_CD
B21: 1942 | C21: 470 | D21: 500 | E21: =IF(OR(C21="",C21=0,D21=""),"",D21/C21) -> 1.0638298 | F21: =IF(E21="","",IF(E21<Premissas!$C$8,"< 1,00",IF(E21<Premissas!$C$9,"1,00 – 1,19",IF(E21<Premissas!$C$10,"1,20 – 1,39",IF(E21<Premissas!$C$11,"1,40 – 1,59",IF(E21<Premissas!$C$12,"1,60 – 1,99","≥ 2,00")))))) -> 1,00 – 1,19 | G21: =IF(E21="","",MIN(Premissas!$C$17,IF(E21<Premissas!$C$8,Premissas!$E$7,IF(E21<Premissas!$C$9,Premissas!$E$8,IF(E21<Premissas!$C$10,Premissas!$E$9,IF(E21<Premissas!$C$11,Premissas!$E$10,IF(E21<Premissas!$C$12,Premissas!$E$11,Premissas!$E$12))))))) -> 100 | H21: =IF(OR(G21="",G21=0),0,G21/$C$6) -> 3.8461538 | I21: 5 | J21: =IF(OR(G21="",I21=""),0,G21*I21) -> 500 | K21: =IF(OR(J21="",J21=0),0,J21/$C$6) -> 19.230769
B22: 409 | E22: =IF(OR(C22="",C22=0,D22=""),"",D22/C22) | F22: =IF(E22="","",IF(E22<Premissas!$C$8,"< 1,00",IF(E22<Premissas!$C$9,"1,00 – 1,19",IF(E22<Premissas!$C$10,"1,20 – 1,39",IF(E22<Premissas!$C$11,"1,40 – 1,59",IF(E22<Premissas!$C$12,"1,60 – 1,99","≥ 2,00")))))) | G22: =IF(E22="","",MIN(Premissas!$C$17,IF(E22<Premissas!$C$8,Premissas!$E$7,IF(E22<Premissas!$C$9,Premissas!$E$8,IF(E22<Premissas!$C$10,Premissas!$E$9,IF(E22<Premissas!$C$11,Premissas!$E$10,IF(E22<Premissas!$C$12,Premissas!$E$11,Premissas!$E$12))))))) | H22: =IF(OR(G22="",G22=0),0,G22/$C$6) -> 0 | J22: =IF(OR(G22="",I22=""),0,G22*I22) -> 0 | K22: =IF(OR(J22="",J22=0),0,J22/$C$6) -> 0
B23: 930 | E23: =IF(OR(C23="",C23=0,D23=""),"",D23/C23) | F23: =IF(E23="","",IF(E23<Premissas!$C$8,"< 1,00",IF(E23<Premissas!$C$9,"1,00 – 1,19",IF(E23<Premissas!$C$10,"1,20 – 1,39",IF(E23<Premissas!$C$11,"1,40 – 1,59",IF(E23<Premissas!$C$12,"1,60 – 1,99","≥ 2,00")))))) | G23: =IF(E23="","",MIN(Premissas!$C$17,IF(E23<Premissas!$C$8,Premissas!$E$7,IF(E23<Premissas!$C$9,Premissas!$E$8,IF(E23<Premissas!$C$10,Premissas!$E$9,IF(E23<Premissas!$C$11,Premissas!$E$10,IF(E23<Premissas!$C$12,Premissas!$E$11,Premissas!$E$12))))))) | H23: =IF(OR(G23="",G23=0),0,G23/$C$6) -> 0 | J23: =IF(OR(G23="",I23=""),0,G23*I23) -> 0 | K23: =IF(OR(J23="",J23=0),0,J23/$C$6) -> 0
B24: 1953 | E24: =IF(OR(C24="",C24=0,D24=""),"",D24/C24) | F24: =IF(E24="","",IF(E24<Premissas!$C$8,"< 1,00",IF(E24<Premissas!$C$9,"1,00 – 1,19",IF(E24<Premissas!$C$10,"1,20 – 1,39",IF(E24<Premissas!$C$11,"1,40 – 1,59",IF(E24<Premissas!$C$12,"1,60 – 1,99","≥ 2,00")))))) | G24: =IF(E24="","",MIN(Premissas!$C$17,IF(E24<Premissas!$C$8,Premissas!$E$7,IF(E24<Premissas!$C$9,Premissas!$E$8,IF(E24<Premissas!$C$10,Premissas!$E$9,IF(E24<Premissas!$C$11,Premissas!$E$10,IF(E24<Premissas!$C$12,Premissas!$E$11,Premissas!$E$12))))))) | H24: =IF(OR(G24="",G24=0),0,G24/$C$6) -> 0 | J24: =IF(OR(G24="",I24=""),0,G24*I24) -> 0 | K24: =IF(OR(J24="",J24=0),0,J24/$C$6) -> 0
B25: 1965 | E25: =IF(OR(C25="",C25=0,D25=""),"",D25/C25) | F25: =IF(E25="","",IF(E25<Premissas!$C$8,"< 1,00",IF(E25<Premissas!$C$9,"1,00 – 1,19",IF(E25<Premissas!$C$10,"1,20 – 1,39",IF(E25<Premissas!$C$11,"1,40 – 1,59",IF(E25<Premissas!$C$12,"1,60 – 1,99","≥ 2,00")))))) | G25: =IF(E25="","",MIN(Premissas!$C$17,IF(E25<Premissas!$C$8,Premissas!$E$7,IF(E25<Premissas!$C$9,Premissas!$E$8,IF(E25<Premissas!$C$10,Premissas!$E$9,IF(E25<Premissas!$C$11,Premissas!$E$10,IF(E25<Premissas!$C$12,Premissas!$E$11,Premissas!$E$12))))))) | H25: =IF(OR(G25="",G25=0),0,G25/$C$6) -> 0 | J25: =IF(OR(G25="",I25=""),0,G25*I25) -> 0 | K25: =IF(OR(J25="",J25=0),0,J25/$C$6) -> 0
B26: 1974 | E26: =IF(OR(C26="",C26=0,D26=""),"",D26/C26) | F26: =IF(E26="","",IF(E26<Premissas!$C$8,"< 1,00",IF(E26<Premissas!$C$9,"1,00 – 1,19",IF(E26<Premissas!$C$10,"1,20 – 1,39",IF(E26<Premissas!$C$11,"1,40 – 1,59",IF(E26<Premissas!$C$12,"1,60 – 1,99","≥ 2,00")))))) | G26: =IF(E26="","",MIN(Premissas!$C$17,IF(E26<Premissas!$C$8,Premissas!$E$7,IF(E26<Premissas!$C$9,Premissas!$E$8,IF(E26<Premissas!$C$10,Premissas!$E$9,IF(E26<Premissas!$C$11,Premissas!$E$10,IF(E26<Premissas!$C$12,Premissas!$E$11,Premissas!$E$12))))))) | H26: =IF(OR(G26="",G26=0),0,G26/$C$6) -> 0 | J26: =IF(OR(G26="",I26=""),0,G26*I26) -> 0 | K26: =IF(OR(J26="",J26=0),0,J26/$C$6) -> 0
B27: 1979 | E27: =IF(OR(C27="",C27=0,D27=""),"",D27/C27) | F27: =IF(E27="","",IF(E27<Premissas!$C$8,"< 1,00",IF(E27<Premissas!$C$9,"1,00 – 1,19",IF(E27<Premissas!$C$10,"1,20 – 1,39",IF(E27<Premissas!$C$11,"1,40 – 1,59",IF(E27<Premissas!$C$12,"1,60 – 1,99","≥ 2,00")))))) | G27: =IF(E27="","",MIN(Premissas!$C$17,IF(E27<Premissas!$C$8,Premissas!$E$7,IF(E27<Premissas!$C$9,Premissas!$E$8,IF(E27<Premissas!$C$10,Premissas!$E$9,IF(E27<Premissas!$C$11,Premissas!$E$10,IF(E27<Premissas!$C$12,Premissas!$E$11,Premissas!$E$12))))))) | H27: =IF(OR(G27="",G27=0),0,G27/$C$6) -> 0 | J27: =IF(OR(G27="",I27=""),0,G27*I27) -> 0 | K27: =IF(OR(J27="",J27=0),0,J27/$C$6) -> 0
B28: 7801 | E28: =IF(OR(C28="",C28=0,D28=""),"",D28/C28) | F28: =IF(E28="","",IF(E28<Premissas!$C$8,"< 1,00",IF(E28<Premissas!$C$9,"1,00 – 1,19",IF(E28<Premissas!$C$10,"1,20 – 1,39",IF(E28<Premissas!$C$11,"1,40 – 1,59",IF(E28<Premissas!$C$12,"1,60 – 1,99","≥ 2,00")))))) | G28: =IF(E28="","",MIN(Premissas!$C$17,IF(E28<Premissas!$C$8,Premissas!$E$7,IF(E28<Premissas!$C$9,Premissas!$E$8,IF(E28<Premissas!$C$10,Premissas!$E$9,IF(E28<Premissas!$C$11,Premissas!$E$10,IF(E28<Premissas!$C$12,Premissas!$E$11,Premissas!$E$12))))))) | H28: =IF(OR(G28="",G28=0),0,G28/$C$6) -> 0 | J28: =IF(OR(G28="",I28=""),0,G28*I28) -> 0 | K28: =IF(OR(J28="",J28=0),0,J28/$C$6) -> 0
B29: TOTAL | I29: =SUM(I21:I28) -> 5 | J29: =SUM(J21:J28) -> 500 | K29: =SUM(K21:K28) -> 19.230769
B31: REGRAS
B32: 1. Indicador: FATOR = REALIZADO_ALLIN ÷ META_ALLIN (mesmo racional do operacional).
B33: 2. Todos os HCs Camisa 10/Apoio do CD recebem o mesmo valor (indicador coletivo).
B34: 3. Faixas e teto idênticos ao modelo operacional (aba Premissas).
B35: 4. Células amarelas = input. Demais = fórmulas.
B36: 5. Simulação CD1942: meta 470 | realizado 500 | fator 1,06 → faixa R$ 100 (exemplo com 5 HCs).
B37: 6. Preencha meta/realizado/qtd dos demais CDs para expandir a simulação de agosto.
B40: Projeção all in — o que acontece se o realizado mudar?
B41: Realizado simulado (editável) | C41: 500
B42: Meta (fix. CD1942) | C42: =C21 -> 470
B43: Fator simulado | C43: =IF(C42=0,"",C41/C42) -> 1.0638298
B44: Valor mensal/HC | C44: =IF(C43="","",MIN(Premissas!$C$17,IF(C43<Premissas!$C$8,Premissas!$E$7,IF(C43<Premissas!$C$9,Premissas!$E$8,IF(C43<Premissas!$C$10,Premissas!$E$9,IF(C43<Premissas!$C$11,Premissas!$E$10,IF(C43<Premissas!$C$12,Premissas!$E$11,Premissas!$E$12))))))) -> 100
B45: Valor diário/HC | C45: =IF(OR(C44="",C44=0),0,C44/$C$6) -> 3.8461538

Sheet Detalhe_Registro
A1: MES | B1: CD | C1: ATIVIDADE | D1: USUARIO | E1: COLABORADOR | F1: QUANTIDADE | G1: HORAS | H1: PRODUTIVIDADE | I1: META_ORIGINAL | J1: META_USADA | K1: META_PREENCHIDA | L1: EMPRESA_AJUSTADA | M1: FATOR | N1: VALOR_MENSAL | O1: VALOR_DIARIO
A2: 7 | B2: 409 | C2: ATIVIDADE OP. EMP. | D2: 182403 | E2: Reginaldo Alves Araujo | F2: 2377 | G2: 66.81 | H2: 36 | I2: 25 | J2: 25 | K2: NÃO | L2: GPA | M2: =IF(OR(J2="",J2<=0),"",H2/J2) -> 1.44 | N2: =IF(M2="","",IF(M2<Premissas!$C$8,Premissas!$E$7,IF(M2<Premissas!$C$9,Premissas!$E$8,IF(M2<Premissas!$C$10,Premissas!$E$9,IF(M2<Premissas!$C$11,Premissas!$E$10,IF(M2<Premissas!$C$12,Premissas!$E$11,Premissas!$E$12)))))) -> 350 | O2: =IF(OR(N2="",N2=0),0,N2/Premissas!$C$16) -> 13.461538
A3: 7 | B3: 409 | C3: RECEBIMENTO | D3: 250187 | E3: Marcio Da Silva Rodrigues | F3: 1518 | G3: 30.47 | H3: 50 | I3: 25 | J3: 25 | K3: NÃO | L3: GPA | M3: =IF(OR(J3="",J3<=0),"",H3/J3) -> 2 | N3: =IF(M3="","",IF(M3<Premissas!$C$8,Premissas!$E$7,IF(M3<Premissas!$C$9,Premissas!$E$8,IF(M3<Premissas!$C$10,Premissas!$E$9,IF(M3<Premissas!$C$11,Premissas!$E$10,IF(M3<Premissas!$C$12,Premissas!$E$11,Premissas!$E$12)))))) -> 750 | O3: =IF(OR(N3="",N3=0),0,N3/Premissas!$C$16) -> 28.846154
A4: 7 | B4: 409 | C4: CARREGAMENTO | D4: 250896 | E4: Hugo Clementino Nunes | F4: 272 | G4: 4.08 | H4: 67 | I4: 24 | J4: 24 | K4: NÃO | L4: GPA | M4: =IF(OR(J4="",J4<=0),"",H4/J4) -> 2.7916667 | N4: =IF(M4="","",IF(M4<Premissas!$C$8,Premissas!$E$7,IF(M4<Premissas!$C$9,Premissas!$E$8,IF(M4<Premissas!$C$10,Premissas!$E$9,IF(M4<Premissas!$C$11,Premissas!$E$10,IF(M4<Premissas!$C$12,Premissas!$E$11,Premissas!$E$12)))))) -> 750 | O4: =IF(OR(N4="",N4=0),0,N4/Premissas!$C$16) -> 28.846154
A5: 7 | B5: 409 | C5: PUXADA RECEB | D5: 250896 | E5: Hugo Clementino Nunes | F5: 318 | G5: 9.38 | H5: 34 | I5: 22 | J5: 22 | K5: NÃO | L5: GPA | M5: =IF(OR(J5="",J5<=0),"",H5/J5) -> 1.5454545 | N5: =IF(M5="","",IF(M5<Premissas!$C$8,Premissas!$E$7,IF(M5<Premissas!$C$9,Premissas!$E$8,IF(M5<Premissas!$C$10,Premissas!$E$9,IF(M5<Premissas!$C$11,Premissas!$E$10,IF(M5<Premissas!$C$12,Premissas!$E$11,Premissas!$E$12)))))) -> 350 | O5: =IF(OR(N5="",N5=0),0,N5/Premissas!$C$16) -> 13.461538
A6: 7 | B6: 409 | C6: RECEBIMENTO | D6: 250896 | E6: Hugo Clementino Nunes | F6: 187 | G6: 7.68 | H6: 24 | I6: 25 | J6: 25 | K6: NÃO | L6: GPA | M6: =IF(OR(J6="",J6<=0),"",H6/J6) -> 0.96 | N6: =IF(M6="","",IF(M6<Premissas!$C$8,Premissas!$E$7,IF(M6<Premissas!$C$9,Premissas!$E$8,IF(M6<Premissas!$C$10,Premissas!$E$9,IF(M6<Premissas!$C$11,Premissas!$E$10,IF(M6<Premissas!$C$12,Premissas!$E$11,Premissas!$E$12)))))) -> 0 | O6: =IF(OR(N6="",N6=0),0,N6/Premissas!$C$16) -> 0
A7: 7 | B7: 409 | C7: PUXADA RECEB | D7: 251239 | E7: Mauricio Rodrigues | F7: 124 | G7: 7.08 | H7: 18 | I7: 22 | J7: 22 | K7: NÃO | L7: GPA | M7: =IF(OR(J7="",J7<=0),"",H7/J7) -> 0.81818182 | N7: =IF(M7="","",IF(M7<Premissas!$C$8,Premissas!$E$7,IF(M7<Premissas!$C$9,Premissas!$E$8,IF(M7<Premissas!$C$10,Premissas!$E$9,IF(M7<Premissas!$C$11,Premissas!$E$10,IF(M7<Premissas!$C$12,Premissas!$E$11,Premissas!$E$12)))))) -> 0 | O7: =IF(OR(N7="",N7=0),0,N7/Premissas!$C$16) -> 0
A8: 7 | B8: 409 | C8: PUXADA RECEB | D8: 251240 | E8: Gildo Antonio Barbosa | F8: 38 | G8: 1.3 | H8: 29 | I8: 22 | J8: 22 | K8: NÃO | L8: GPA | M8: =IF(OR(J8="",J8<=0),"",H8/J8) -> 1.3181818 | N8: =IF(M8="","",IF(M8<Premissas!$C$8,Premissas!$E$7,IF(M8<Premissas!$C$9,Premissas!$E$8,IF(M8<Premissas!$C$10,Premissas!$E$9,IF(M8<Premissas!$C$11,Premissas!$E$10,IF(M8<Premissas!$C$12,Premissas!$E$11,Premissas!$E$12)))))) -> 200 | O8: =IF(OR(N8="",N8=0),0,N8/Premissas!$C$16) -> 7.6923077
A9: 7 | B9: 409 | C9: RECEBIMENTO | D9: 251240 | E9: Gildo Antonio Barbosa | F9: 3278 | G9: 39.72 | H9: 83 | I9: 25 | J9: 25 | K9: NÃO | L9: GPA | M9: =IF(OR(J9="",J9<=0),"",H9/J9) -> 3.32 | N9: =IF(M9="","",IF(M9<Premissas!$C$8,Premissas!$E$7,IF(M9<Premissas!$C$9,Premissas!$E$8,IF(M9<Premissas!$C$10,Premissas!$E$9,IF(M9<Premissas!$C$11,Premissas!$E$10,IF(M9<Premissas!$C$12,Premissas!$E$11,Premissas!$E$12)))))) -> 750 | O9: =IF(OR(N9="",N9=0),0,N9/Premissas!$C$16) -> 28.846154
A10: 7 | B10: 409 | C10: CARREGAMENTO | D10: 255199 | E10: Gilberton Santana De Moura | F10: 344 | G10: 7.68 | H10: 45 | I10: 24 | J10: 24 | K10: NÃO | L10: GPA | M10: =IF(OR(J10="",J10<=0),"",H10/J10) -> 1.875 | N10: =IF(M10="","",IF(M10<Premissas!$C$8,Premissas!$E$7,IF(M10<Premissas!$C$9,Premissas!$E$8,IF(M10<Premissas!$C$10,Premissas!$E$9,IF(M10<Premissas!$C$11,Premissas!$E$10,IF(M10<Premissas!$C$12,Premissas!$E$11,Premissas!$E$12)))))) -> 500 | O10: =IF(OR(N10="",N10=0),0,N10/Premissas!$C$16) -> 19.230769
A11: 7 | B11: 409 | C11: ATIVIDADE OP. EMP. | D11: 264318 | E11: Flavio Soares Da Silva | F11: 2828 | G11: 66.5 | H11: 43 | I11: 25 | J11: 25 | K11: NÃO | L11: GPA | M11: =IF(OR(J11="",J11<=0),"",H11/J11) -> 1.72 | N11: =IF(M11="","",IF(M11<Premissas!$C$8,Premissas!$E$7,IF(M11<Premissas!$C$9,Premissas!$E$8,IF(M11<Premissas!$C$10,Premissas!$E$9,IF(M11<Premissas!$C$11,Premissas!$E$10,IF(M11<Premissas!$C$12,Premissas!$E$11,Premissas!$E$12)))))) -> 500 | O11: =IF(OR(N11="",N11=0),0,N11/Premissas!$C$16) -> 19.230769
A12: 7 | B12: 409 | C12: ATIVIDADE OP. EMP. | D12: 264446 | E12: HUMBERTO DE ANDRADE SILVA | F12: 1857 | G12: 46.24 | H12: 40 | I12: 25 | J12: 25 | K12: NÃO | L12: GPA | M12: =IF(OR(J12="",J12<=0),"",H12/J12) -> 1.6 | N12: =IF(M12="","",IF(M12<Premissas!$C$8,Premissas!$E$7,IF(M12<Premissas!$C$9,Premissas!$E$8,IF(M12<Premissas!$C$10,Premissas!$E$9,IF(M12<Premissas!$C$11,Premissas!$E$10,IF(M12<Premissas!$C$12,Premissas!$E$11,Premissas!$E$12)))))) -> 500 | O12: =IF(OR(N12="",N12=0),0,N12/Premissas!$C$16) -> 19.230769
A13: 7 | B13: 409 | C13: ATIVIDADE OP. EMP. | D13: 265139 | E13: Ronieles Junior Vasconcelos | F13: 1507 | G13: 52.63 | H13: 29 | I13: 25 | J13: 25 | K13: NÃO | L13: GPA | M13: =IF(OR(J13="",J13<=0),"",H13/J13) -> 1.16 | N13: =IF(M13="","",IF(M13<Premissas!$C$8,Premissas!$E$7,IF(M13<Premissas!$C$9,Premissas!$E$8,IF(M13<Premissas!$C$10,Premissas!$E$9,IF(M13<Premissas!$C$11,Premissas!$E$10,IF(M13<Premissas!$C$12,Premissas!$E$11,Premissas!$E$12)))))) -> 100 | O13: =IF(OR(N13="",N13=0),0,N13/Premissas!$C$16) -> 3.8461538
... A362: 7 | B362: 1974 | C362: ATIVIDADE OP. EMP. | D362: 143573 | E362: ALEXANDRE GLEYSON GOMES TEIXEIRA | F362: 51 | G362: 1.31 | H362: 39 | I362: 9 | J362: 9 | K362: NÃO | L362: GPA | M362: =IF(OR(J362="",J362<=0),"",H362/J362) -> 4.3333333 | N362: =IF(M362="","",IF(M362<Premissas!$C$8,Premissas!$E$7,IF(M362<Premissas!$C$9,Premissas!$E$8,IF(M362<Premissas!$C$10,Premissas!$E$9,IF(M362<Premissas!$C$11,Premissas!$E$10,IF(M362<Premissas!$C$12,Premissas!$E$11,Premissas!$E$12)))))) -> 750 | O362: =IF(OR(N362="",N362=0),0,N362/Premissas!$C$16) -> 28.846154
A363: 7 | B363: 1974 | C363: CARREGAMENTO | D363: 149952 | E363: RONALD NUNES DOS SANTOS | F363: 23 | G363: 1.21 | H363: 19 | J363: 22 | K363: SIM | L363: GPA | M363: =IF(OR(J363="",J363<=0),"",H363/J363) -> 0.86363636 | N363: =IF(M363="","",IF(M363<Premissas!$C$8,Premissas!$E$7,IF(M363<Premissas!$C$9,Premissas!$E$8,IF(M363<Premissas!$C$10,Premissas!$E$9,IF(M363<Premissas!$C$11,Premissas!$E$10,IF(M363<Premissas!$C$12,Premissas!$E$11,Premissas!$E$12)))))) -> 0 | O363: =IF(OR(N363="",N363=0),0,N363/Premissas!$C$16) -> 0
A364: 7 | B364: 1974 | C364: PUXADA RECEB | D364: 149952 | E364: RONALD NUNES DOS SANTOS | F364: 95 | G364: 2.7 | H364: 35 | J364: 16 | K364: SIM | L364: GPA | M364: =IF(OR(J364="",J364<=0),"",H364/J364) -> 2.1875 | N364: =IF(M364="","",IF(M364<Premissas!$C$8,Premissas!$E$7,IF(M364<Premissas!$C$9,Premissas!$E$8,IF(M364<Premissas!$C$10,Premissas!$E$9,IF(M364<Premissas!$C$11,Premissas!$E$10,IF(M364<Premissas!$C$12,Premissas!$E$11,Premissas!$E$12)))))) -> 750 | O364: =IF(OR(N364="",N364=0),0,N364/Premissas!$C$16) -> 28.846154
A365: 7 | B365: 1974 | C365: RECEBIMENTO | D365: 149952 | E365: RONALD NUNES DOS SANTOS | F365: 357 | G365: 6.48 | H365: 55 | I365: 41 | J365: 41 | K365: NÃO | L365: GPA | M365: =IF(OR(J365="",J365<=0),"",H365/J365) -> 1.3414634 | N365: =IF(M365="","",IF(M365<Premissas!$C$8,Premissas!$E$7,IF(M365<Premissas!$C$9,Premissas!$E$8,IF(M365<Premissas!$C$10,Premissas!$E$9,IF(M365<Premissas!$C$11,Premissas!$E$10,IF(M365<Premissas!$C$12,Premissas!$E$11,Premissas!$E$12)))))) -> 200 | O365: =IF(OR(N365="",N365=0),0,N365/Premissas!$C$16) -> 7.6923077
A366: 7 | B366: 1974 | C366: ATIVIDADE OP. EMP. | D366: 157110 | E366: FRANCISCO JEAN MOURA | F366: 2623 | G366: 101.11 | H366: 26 | I366: 9 | J366: 9 | K366: NÃO | L366: GPA | M366: =IF(OR(J366="",J366<=0),"",H366/J366) -> 2.8888889 | N366: =IF(M366="","",IF(M366<Premissas!$C$8,Premissas!$E$7,IF(M366<Premissas!$C$9,Premissas!$E$8,IF(M366<Premissas!$C$10,Premissas!$E$9,IF(M366<Premissas!$C$11,Premissas!$E$10,IF(M366<Premissas!$C$12,Premissas!$E$11,Premissas!$E$12)))))) -> 750 | O366: =IF(OR(N366="",N366=0),0,N366/Premissas!$C$16) -> 28.846154
A367: 7 | B367: 1974 | C367: ATIVIDADE OP. EMP. | D367: 157789 | E367: FRANCISCO DAS CHAGAS ALVES RODRIGUES | F367: 1783 | G367: 51.71 | H367: 34 | I367: 9 | J367: 9 | K367: NÃO | L367: GPA | M367: =IF(OR(J367="",J367<=0),"",H367/J367) -> 3.7777778 | N367: =IF(M367="","",IF(M367<Premissas!$C$8,Premissas!$E$7,IF(M367<Premissas!$C$9,Premissas!$E$8,IF(M367<Premissas!$C$10,Premissas!$E$9,IF(M367<Premissas!$C$11,Premissas!$E$10,IF(M367<Premissas!$C$12,Premissas!$E$11,Premissas!$E$12)))))) -> 750 | O367: =IF(OR(N367="",N367=0),0,N367/Premissas!$C$16) -> 28.846154
A368: 7 | B368: 1974 | C368: ATIVIDADE OP. EMP. | D368: 286911 | E368: ANTONIO CARLOS DOS SANTOS SOUZA | F368: 2222 | G368: 65.97 | H368: 34 | I368: 9 | J368: 9 | K368: NÃO | L368: GPA | M368: =IF(OR(J368="",J368<=0),"",H368/J368) -> 3.7777778 | N368: =IF(M368="","",IF(M368<Premissas!$C$8,Premissas!$E$7,IF(M368<Premissas!$C$9,Premissas!$E$8,IF(M368<Premissas!$C$10,Premissas!$E$9,IF(M368<Premissas!$C$11,Premissas!$E$10,IF(M368<Premissas!$C$12,Premissas!$E$11,Premissas!$E$12)))))) -> 750 | O368: =IF(OR(N368="",N368=0),0,N368/Premissas!$C$16) -> 28.846154
A369: 7 | B369: 1974 | C369: RECEBIMENTO | D369: 2984822 | E369: SAMIA SOUZA NOGUEIRA | F369: 2 | G369: 0.02 | H369: 100 | I369: 41 | J369: 41 | K369: NÃO | L369: GPA | M369: =IF(OR(J369="",J369<=0),"",H369/J369) -> 2.4390244 | N369: =IF(M369="","",IF(M369<Premissas!$C$8,Premissas!$E$7,IF(M369<Premissas!$C$9,Premissas!$E$8,IF(M369<Premissas!$C$10,Premissas!$E$9,IF(M369<Premissas!$C$11,Premissas!$E$10,IF(M369<Premissas!$C$12,Premissas!$E$11,Premissas!$E$12)))))) -> 750 | O369: =IF(OR(N369="",N369=0),0,N369/Premissas!$C$16) -> 28.846154
A370: 7 | B370: 1974 | C370: ATIVIDADE OP. EMP. | D370: 316536 | E370: JOSE HORMANDO SOARES DOS SANTOS | F370: 2224 | G370: 68.12 | H370: 33 | I370: 9 | J370: 9 | K370: NÃO | L370: GPA | M370: =IF(OR(J370="",J370<=0),"",H370/J370) -> 3.6666667 | N370: =IF(M370="","",IF(M370<Premissas!$C$8,Premissas!$E$7,IF(M370<Premissas!$C$9,Premissas!$E$8,IF(M370<Premissas!$C$10,Premissas!$E$9,IF(M370<Premissas!$C$11,Premissas!$E$10,IF(M370<Premissas!$C$12,Premissas!$E$11,Premissas!$E$12)))))) -> 750 | O370: =IF(OR(N370="",N370=0),0,N370/Premissas!$C$16) -> 28.846154
A371: 7 | B371: 1974 | C371: CARREGAMENTO | D371: 365615 | E371: FIRMINO NETO DE SOUSA SILVA | F371: 159 | G371: 7.05 | H371: 23 | J371: 22 | K371: SIM | L371: GPA | M371: =IF(OR(J371="",J371<=0),"",H371/J371) -> 1.0454545 | N371: =IF(M371="","",IF(M371<Premissas!$C$8,Premissas!$E$7,IF(M371<Premissas!$C$9,Premissas!$E$8,IF(M371<Premissas!$C$10,Premissas!$E$9,IF(M371<Premissas!$C$11,Premissas!$E$10,IF(M371<Premissas!$C$12,Premissas!$E$11,Premissas!$E$12)))))) -> 100 | O371: =IF(OR(N371="",N371=0),0,N371/Premissas!$C$16) -> 3.8461538
A372: 7 | B372: 1974 | C372: PUXADA RECEB | D372: 365615 | E372: FIRMINO NETO DE SOUSA SILVA | F372: 49 | G372: 3.68 | H372: 13 | J372: 16 | K372: SIM | L372: GPA | M372: =IF(OR(J372="",J372<=0),"",H372/J372) -> 0.8125 | N372: =IF(M372="","",IF(M372<Premissas!$C$8,Premissas!$E$7,IF(M372<Premissas!$C$9,Premissas!$E$8,IF(M372<Premissas!$C$10,Premissas!$E$9,IF(M372<Premissas!$C$11,Premissas!$E$10,IF(M372<Premissas!$C$12,Premissas!$E$11,Premissas!$E$12)))))) -> 0 | O372: =IF(OR(N372="",N372=0),0,N372/Premissas!$C$16) -> 0
A373: 7 | B373: 1974 | C373: RECEBIMENTO | D373: 365615 | E373: FIRMINO NETO DE SOUSA SILVA | F373: 2251 | G373: 33.25 | H373: 68 | I373: 41 | J373: 41 | K373: NÃO | L373: GPA | M373: =IF(OR(J373="",J373<=0),"",H373/J373) -> 1.6585366 | N373: =IF(M373="","",IF(M373<Premissas!$C$8,Premissas!$E$7,IF(M373<Premissas!$C$9,Premissas!$E$8,IF(M373<Premissas!$C$10,Premissas!$E$9,IF(M373<Premissas!$C$11,Premissas!$E$10,IF(M373<Premissas!$C$12,Premissas!$E$11,Premissas!$E$12)))))) -> 500 | O373: =IF(OR(N373="",N373=0),0,N373/Premissas!$C$16) -> 19.230769
A374: 7 | B374: 1974 | C374: ATIVIDADE OP. EMP. | D374: 5425590 | E374: Thiago Igor Soares Vieira | F374: 602 | G374: 21.59 | H374: 28 | I374: 9 | J374: 9 | K374: NÃO | L374: GPA | M374: =IF(OR(J374="",J374<=0),"",H374/J374) -> 3.1111111 | N374: =IF(M374="","",IF(M374<Premissas!$C$8,Premissas!$E$7,IF(M374<Premissas!$C$9,Premissas!$E$8,IF(M374<Premissas!$C$10,Premissas!$E$9,IF(M374<Premissas!$C$11,Premissas!$E$10,IF(M374<Premissas!$C$12,Premissas!$E$11,Premissas!$E$12)))))) -> 750 | O374: =IF(OR(N374="",N374=0),0,N374/Premissas!$C$16) -> 28.846154
A375: 7 | B375: 1974 | C375: CARREGAMENTO | D375: 5426251 | E375: Alisson Vitor Vieira Diniz | F375: 441 | G375: 8.54 | H375: 52 | J375: 22 | K375: SIM | L375: GPA | M375: =IF(OR(J375="",J375<=0),"",H375/J375) -> 2.3636364 | N375: =IF(M375="","",IF(M375<Premissas!$C$8,Premissas!$E$7,IF(M375<Premissas!$C$9,Premissas!$E$8,IF(M375<Premissas!$C$10,Premissas!$E$9,IF(M375<Premissas!$C$11,Premissas!$E$10,IF(M375<Premissas!$C$12,Premissas!$E$11,Premissas!$E$12)))))) -> 750 | O375: =IF(OR(N375="",N375=0),0,N375/Premissas!$C$16) -> 28.846154
A376: 7 | B376: 1974 | C376: PUXADA RECEB | D376: 5426251 | E376: Alisson Vitor Vieira Diniz | F376: 159 | G376: 7.56 | H376: 21 | J376: 16 | K376: SIM | L376: GPA | M376: =IF(OR(J376="",J376<=0),"",H376/J376) -> 1.3125 | N376: =IF(M376="","",IF(M376<Premissas!$C$8,Premissas!$E$7,IF(M376<Premissas!$C$9,Premissas!$E$8,IF(M376<Premissas!$C$10,Premissas!$E$9,IF(M376<Premissas!$C$11,Premissas!$E$10,IF(M376<Premissas!$C$12,Premissas!$E$11,Premissas!$E$12)))))) -> 200 | O376: =IF(OR(N376="",N376=0),0,N376/Premissas!$C$16) -> 7.6923077
A377: 7 | B377: 1974 | C377: RECEBIMENTO | D377: 5426251 | E377: Alisson Vitor Vieira Diniz | F377: 963 | G377: 27.36 | H377: 35 | I377: 41 | J377: 41 | K377: NÃO | L377: GPA | M377: =IF(OR(J377="",J377<=0),"",H377/J377) -> 0.85365854 | N377: =IF(M377="","",IF(M377<Premissas!$C$8,Premissas!$E$7,IF(M377<Premissas!$C$9,Premissas!$E$8,IF(M377<Premissas!$C$10,Premissas!$E$9,IF(M377<Premissas!$C$11,Premissas!$E$10,IF(M377<Premissas!$C$12,Premissas!$E$11,Premissas!$E$12)))))) -> 0 | O377: =IF(OR(N377="",N377=0),0,N377/Premissas!$C$16) -> 0
A378: 7 | B378: 1974 | C378: CARREGAMENTO | D378: 5440050 | E378: Daniel Diogo Moraes | F378: 1551 | G378: 19.29 | H378: 80 | J378: 22 | K378: SIM | L378: GPA | M378: =IF(OR(J378="",J378<=0),"",H378/J378) -> 3.6363636 | N378: =IF(M378="","",IF(M378<Premissas!$C$8,Premissas!$E$7,IF(M378<Premissas!$C$9,Premissas!$E$8,IF(M378<Premissas!$C$10,Premissas!$E$9,IF(M378<Premissas!$C$11,Premissas!$E$10,IF(M378<Premissas!$C$12,Premissas!$E$11,Premissas!$E$12)))))) -> 750 | O378: =IF(OR(N378="",N378=0),0,N378/Premissas!$C$16) -> 28.846154
A379: 7 | B379: 1974 | C379: PUXADA RECEB | D379: 5440050 | E379: Daniel Diogo Moraes | F379: 33 | G379: 1.05 | H379: 31 | J379: 16 | K379: SIM | L379: GPA | M379: =IF(OR(J379="",J379<=0),"",H379/J379) -> 1.9375 | N379: =IF(M379="","",IF(M379<Premissas!$C$8,Premissas!$E$7,IF(M379<Premissas!$C$9,Premissas!$E$8,IF(M379<Premissas!$C$10,Premissas!$E$9,IF(M379<Premissas!$C$11,Premissas!$E$10,IF(M379<Premissas!$C$12,Premissas!$E$11,Premissas!$E$12)))))) -> 750 | O379: =IF(OR(N379="",N379=0),0,N379/Premissas!$C$16) -> 28.846154
A380: 7 | B380: 1974 | C380: RECEBIMENTO | D380: 5440050 | E380: Daniel Diogo Moraes | F380: 140 | G380: 1.44 | H380: 97 | I380: 41 | J380: 41 | K380: NÃO | L380: GPA | M380: =IF(OR(J380="",J380<=0),"",H380/J380) -> 2.3658537 | N380: =IF(M380="","",IF(M380<Premissas!$C$8,Premissas!$E$7,IF(M380<Premissas!$C$9,Premissas!$E$8,IF(M380<Premissas!$C$10,Premissas!$E$9,IF(M380<Premissas!$C$11,Premissas!$E$10,IF(M380<Premissas!$C$12,Premissas!$E$11,Premissas!$E$12)))))) -> 750 | O380: =IF(OR(N380="",N380=0),0,N380/Premissas!$C$16) -> 28.846154
A381: 7 | B381: 1974 | C381: PUXADA RECEB | D381: 5440114 | E381: Antonio Lucas De Oliveira Matos | F381: 90 | G381: 3.08 | H381: 29 | J381: 16 | K381: SIM | L381: GPA | M381: =IF(OR(J381="",J381<=0),"",H381/J381) -> 1.8125 | N381: =IF(M381="","",IF(M381<Premissas!$C$8,Premissas!$E$7,IF(M381<Premissas!$C$9,Premissas!$E$8,IF(M381<Premissas!$C$10,Premissas!$E$9,IF(M381<Premissas!$C$11,Premissas!$E$10,IF(M381<Premissas!$C$12,Premissas!$E$11,Premissas!$E$12)))))) -> 500 | O381: =IF(OR(N381="",N381=0),0,N381/Premissas!$C$16) -> 19.230769
A382: 7 | B382: 1974 | C382: CARREGAMENTO | D382: 5441927 | E382: Cicero Manoel Da Silva | F382: 405 | G382: 2.44 | H382: 166 | J382: 22 | K382: SIM | L382: GPA | M382: =IF(OR(J382="",J382<=0),"",H382/J382) -> 7.5454545 | N382: =IF(M382="","",IF(M382<Premissas!$C$8,Premissas!$E$7,IF(M382<Premissas!$C$9,Premissas!$E$8,IF(M382<Premissas!$C$10,Premissas!$E$9,IF(M382<Premissas!$C$11,Premissas!$E$10,IF(M382<Premissas!$C$12,Premissas!$E$11,Premissas!$E$12)))))) -> 750 | O382: =IF(OR(N382="",N382=0),0,N382/Premissas!$C$16) -> 28.846154
A383: 7 | B383: 1974 | C383: PUXADA RECEB | D383: 5441927 | E383: Cicero Manoel Da Silva | F383: 286 | G383: 8.33 | H383: 34 | J383: 16 | K383: SIM | L383: GPA | M383: =IF(OR(J383="",J383<=0),"",H383/J383) -> 2.125 | N383: =IF(M383="","",IF(M383<Premissas!$C$8,Premissas!$E$7,IF(M383<Premissas!$C$9,Premissas!$E$8,IF(M383<Premissas!$C$10,Premissas!$E$9,IF(M383<Premissas!$C$11,Premissas!$E$10,IF(M383<Premissas!$C$12,Premissas!$E$11,Premissas!$E$12)))))) -> 750 | O383: =IF(OR(N383="",N383=0),0,N383/Premissas!$C$16) -> 28.846154
A384: 7 | B384: 1974 | C384: RECEBIMENTO | D384: 5441927 | E384: Cicero Manoel Da Silva | F384: 1596 | G384: 31.71 | H384: 50 | I384: 41 | J384: 41 | K384: NÃO | L384: GPA | M384: =IF(OR(J384="",J384<=0),"",H384/J384) -> 1.2195122 | N384: =IF(M384="","",IF(M384<Premissas!$C$8,Premissas!$E$7,IF(M384<Premissas!$C$9,Premissas!$E$8,IF(M384<Premissas!$C$10,Premissas!$E$9,IF(M384<Premissas!$C$11,Premissas!$E$10,IF(M384<Premissas!$C$12,Premissas!$E$11,Premissas!$E$12)))))) -> 200 | O384: =IF(OR(N384="",N384=0),0,N384/Premissas!$C$16) -> 7.6923077
A385: 7 | B385: 1974 | C385: ATIVIDADE OP. EMP. | D385: 5443148 | E385: Danilson Paulino De Sousa | F385: 1938 | G385: 74.34 | H385: 26 | I385: 9 | J385: 9 | K385: NÃO | L385: GPA | M385: =IF(OR(J385="",J385<=0),"",H385/J385) -> 2.8888889 | N385: =IF(M385="","",IF(M385<Premissas!$C$8,Premissas!$E$7,IF(M385<Premissas!$C$9,Premissas!$E$8,IF(M385<Premissas!$C$10,Premissas!$E$9,IF(M385<Premissas!$C$11,Premissas!$E$10,IF(M385<Premissas!$C$12,Premissas!$E$11,Premissas!$E$12)))))) -> 750 | O385: =IF(OR(N385="",N385=0),0,N385/Premissas!$C$16) -> 28.846154
A386: 7 | B386: 1974 | C386: PUXADA RECEB | D386: 5443571 | E386: Isaac Marques Do Nascimento | F386: 67 | G386: 2.31 | H386: 29 | J386: 16 | K386: SIM | L386: GPA | M386: =IF(OR(J386="",J386<=0),"",H386/J386) -> 1.8125 | N386: =IF(M386="","",IF(M386<Premissas!$C$8,Premissas!$E$7,IF(M386<Premissas!$C$9,Premissas!$E$8,IF(M386<Premissas!$C$10,Premissas!$E$9,IF(M386<Premissas!$C$11,Premissas!$E$10,IF(M386<Premissas!$C$12,Premissas!$E$11,Premissas!$E$12)))))) -> 500 | O386: =IF(OR(N386="",N386=0),0,N386/Premissas!$C$16) -> 19.230769
A387: 7 | B387: 1974 | C387: PUXADA RECEB | D387: 5451671 | E387: Fabio Mota De Sousa | F387: 801 | G387: 35.48 | H387: 23 | J387: 16 | K387: SIM | L387: GPA | M387: =IF(OR(J387="",J387<=0),"",H387/J387) -> 1.4375 | N387: =IF(M387="","",IF(M387<Premissas!$C$8,Premissas!$E$7,IF(M387<Premissas!$C$9,Premissas!$E$8,IF(M387<Premissas!$C$10,Premissas!$E$9,IF(M387<Premissas!$C$11,Premissas!$E$10,IF(M387<Premissas!$C$12,Premissas!$E$11,Premissas!$E$12)))))) -> 350 | O387: =IF(OR(N387="",N387=0),0,N387/Premissas!$C$16) -> 13.461538
A388: 7 | B388: 1974 | C388: CARREGAMENTO | D388: 5464170 | E388: Cicero Ricardo Da Silva | F388: 45 | G388: 1.22 | H388: 37 | J388: 22 | K388: SIM | L388: GPA | M388: =IF(OR(J388="",J388<=0),"",H388/J388) -> 1.6818182 | N388: =IF(M388="","",IF(M388<Premissas!$C$8,Premissas!$E$7,IF(M388<Premissas!$C$9,Premissas!$E$8,IF(M388<Premissas!$C$10,Premissas!$E$9,IF(M388<Premissas!$C$11,Premissas!$E$10,IF(M388<Premissas!$C$12,Premissas!$E$11,Premissas!$E$12)))))) -> 500 | O388: =IF(OR(N388="",N388=0),0,N388/Premissas!$C$16) -> 19.230769
A389: 7 | B389: 1974 | C389: PUXADA RECEB | D389: 5464170 | E389: Cicero Ricardo Da Silva | F389: 194 | G389: 4.64 | H389: 42 | J389: 16 | K389: SIM | L389: GPA | M389: =IF(OR(J389="",J389<=0),"",H389/J389) -> 2.625 | N389: =IF(M389="","",IF(M389<Premissas!$C$8,Premissas!$E$7,IF(M389<Premissas!$C$9,Premissas!$E$8,IF(M389<Premissas!$C$10,Premissas!$E$9,IF(M389<Premissas!$C$11,Premissas!$E$10,IF(M389<Premissas!$C$12,Premissas!$E$11,Premissas!$E$12)))))) -> 750 | O389: =IF(OR(N389="",N389=0),0,N389/Premissas!$C$16) -> 28.846154
A390: 7 | B390: 1974 | C390: RECEBIMENTO | D390: 5464170 | E390: Cicero Ricardo Da Silva | F390: 4400 | G390: 61.73 | H390: 71 | I390: 41 | J390: 41 | K390: NÃO | L390: GPA | M390: =IF(OR(J390="",J390<=0),"",H390/J390) -> 1.7317073 | N390: =IF(M390="","",IF(M390<Premissas!$C$8,Premissas!$E$7,IF(M390<Premissas!$C$9,Premissas!$E$8,IF(M390<Premissas!$C$10,Premissas!$E$9,IF(M390<Premissas!$C$11,Premissas!$E$10,IF(M390<Premissas!$C$12,Premissas!$E$11,Premissas!$E$12)))))) -> 500 | O390: =IF(OR(N390="",N390=0),0,N390/Premissas!$C$16) -> 19.230769
A391: 7 | B391: 1974 | C391: CARREGAMENTO | D391: 5499585 | E391: Alexandre Victor Da Silva Moura | F391: 39 | G391: 1.02 | H391: 38 | J391: 22 | K391: SIM | L391: GPA | M391: =IF(OR(J391="",J391<=0),"",H391/J391) -> 1.7272727 | N391: =IF(M391="","",IF(M391<Premissas!$C$8,Premissas!$E$7,IF(M391<Premissas!$C$9,Premissas!$E$8,IF(M391<Premissas!$C$10,Premissas!$E$9,IF(M391<Premissas!$C$11,Premissas!$E$10,IF(M391<Premissas!$C$12,Premissas!$E$11,Premissas!$E$12)))))) -> 500 | O391: =IF(OR(N391="",N391=0),0,N391/Premissas!$C$16) -> 19.230769
A392: 7 | B392: 1974 | C392: PUXADA RECEB | D392: 5499585 | E392: Alexandre Victor Da Silva Moura | F392: 1133 | G392: 20.32 | H392: 56 | J392: 16 | K392: SIM | L392: GPA | M392: =IF(OR(J392="",J392<=0),"",H392/J392) -> 3.5 | N392: =IF(M392="","",IF(M392<Premissas!$C$8,Premissas!$E$7,IF(M392<Premissas!$C$9,Premissas!$E$8,IF(M392<Premissas!$C$10,Premissas!$E$9,IF(M392<Premissas!$C$11,Premissas!$E$10,IF(M392<Premissas!$C$12,Premissas!$E$11,Premissas!$E$12)))))) -> 750 | O392: =IF(OR(N392="",N392=0),0,N392/Premissas!$C$16) -> 28.846154
A393: 7 | B393: 1974 | C393: RECEBIMENTO | D393: 5499585 | E393: Alexandre Victor Da Silva Moura | F393: 833 | G393: 5 | H393: 167 | I393: 41 | J393: 41 | K393: NÃO | L393: GPA | M393: =IF(OR(J393="",J393<=0),"",H393/J393) -> 4.0731707 | N393: =IF(M393="","",IF(M393<Premissas!$C$8,Premissas!$E$7,IF(M393<Premissas!$C$9,Premissas!$E$8,IF(M393<Premissas!$C$10,Premissas!$E$9,IF(M393<Premissas!$C$11,Premissas!$E$10,IF(M393<Premissas!$C$12,Premissas!$E$11,Premissas!$E$12)))))) -> 750 | O393: =IF(OR(N393="",N393=0),0,N393/Premissas!$C$16) -> 28.846154
A394: 7 | B394: 1974 | C394: PUXADA RECEB | D394: 5570735 | E394: Alef Bruno Rodrigues Marques | F394: 13 | G394: 0.34 | H394: 38 | J394: 16 | K394: SIM | L394: GPA | M394: =IF(OR(J394="",J394<=0),"",H394/J394) -> 2.375 | N394: =IF(M394="","",IF(M394<Premissas!$C$8,Premissas!$E$7,IF(M394<Premissas!$C$9,Premissas!$E$8,IF(M394<Premissas!$C$10,Premissas!$E$9,IF(M394<Premissas!$C$11,Premissas!$E$10,IF(M394<Premissas!$C$12,Premissas!$E$11,Premissas!$E$12)))))) -> 750 | O394: =IF(OR(N394="",N394=0),0,N394/Premissas!$C$16) -> 28.846154
A395: 7 | B395: 1974 | C395: PUXADA RECEB | D395: 5579147 | E395: JOSE EDSON DA SILVA DO NASCIMENTO | F395: 8 | G395: 0.49 | H395: 16 | J395: 16 | K395: SIM | L395: GPA | M395: =IF(OR(J395="",J395<=0),"",H395/J395) -> 1 | N395: =IF(M395="","",IF(M395<Premissas!$C$8,Premissas!$E$7,IF(M395<Premissas!$C$9,Premissas!$E$8,IF(M395<Premissas!$C$10,Premissas!$E$9,IF(M395<Premissas!$C$11,Premissas!$E$10,IF(M395<Premissas!$C$12,Premissas!$E$11,Premissas!$E$12)))))) -> 100 | O395: =IF(OR(N395="",N395=0),0,N395/Premissas!$C$16) -> 3.8461538
A396: 7 | B396: 1974 | C396: PUXADA RECEB | D396: 5588219 | E396: Denzel Wellington Do Nascimento Marques | F396: 10 | G396: 1.03 | H396: 10 | J396: 16 | K396: SIM | L396: GPA | M396: =IF(OR(J396="",J396<=0),"",H396/J396) -> 0.625 | N396: =IF(M396="","",IF(M396<Premissas!$C$8,Premissas!$E$7,IF(M396<Premissas!$C$9,Premissas!$E$8,IF(M396<Premissas!$C$10,Premissas!$E$9,IF(M396<Premissas!$C$11,Premissas!$E$10,IF(M396<Premissas!$C$12,Premissas!$E$11,Premissas!$E$12)))))) -> 0 | O396: =IF(OR(N396="",N396=0),0,N396/Premissas!$C$16) -> 0
A397: 7 | B397: 1974 | C397: PUXADA RECEB | D397: 5595274 | E397: Edmilson Gabriel Do Nascimento Filho | F397: 430 | G397: 15.3 | H397: 28 | J397: 16 | K397: SIM | L397: GPA | M397: =IF(OR(J397="",J397<=0),"",H397/J397) -> 1.75 | N397: =IF(M397="","",IF(M397<Premissas!$C$8,Premissas!$E$7,IF(M397<Premissas!$C$9,Premissas!$E$8,IF(M397<Premissas!$C$10,Premissas!$E$9,IF(M397<Premissas!$C$11,Premissas!$E$10,IF(M397<Premissas!$C$12,Premissas!$E$11,Premissas!$E$12)))))) -> 500 | O397: =IF(OR(N397="",N397=0),0,N397/Premissas!$C$16) -> 19.230769
A398: 7 | B398: 1974 | C398: CARREGAMENTO | D398: 5635683 | E398: Riquelme Alves Araujo | F398: 121 | G398: 1.17 | H398: 103 | J398: 22 | K398: SIM | L398: GPA | M398: =IF(OR(J398="",J398<=0),"",H398/J398) -> 4.6818182 | N398: =IF(M398="","",IF(M398<Premissas!$C$8,Premissas!$E$7,IF(M398<Premissas!$C$9,Premissas!$E$8,IF(M398<Premissas!$C$10,Premissas!$E$9,IF(M398<Premissas!$C$11,Premissas!$E$10,IF(M398<Premissas!$C$12,Premissas!$E$11,Premissas!$E$12)))))) -> 750 | O398: =IF(OR(N398="",N398=0),0,N398/Premissas!$C$16) -> 28.846154
A399: 7 | B399: 1974 | C399: PUXADA RECEB | D399: 5635683 | E399: Riquelme Alves Araujo | F399: 217 | G399: 4.63 | H399: 47 | J399: 16 | K399: SIM | L399: GPA | M399: =IF(OR(J399="",J399<=0),"",H399/J399) -> 2.9375 | N399: =IF(M399="","",IF(M399<Premissas!$C$8,Premissas!$E$7,IF(M399<Premissas!$C$9,Premissas!$E$8,IF(M399<Premissas!$C$10,Premissas!$E$9,IF(M399<Premissas!$C$11,Premissas!$E$10,IF(M399<Premissas!$C$12,Premissas!$E$11,Premissas!$E$12)))))) -> 750 | O399: =IF(OR(N399="",N399=0),0,N399/Premissas!$C$16) -> 28.846154
A400: 7 | B400: 1974 | C400: CARREGAMENTO | D400: 5688779 | E400: Emanuel Ferreira De Vasconcelos | F400: 17 | G400: 0.52 | H400: 33 | J400: 22 | K400: SIM | L400: GPA | M400: =IF(OR(J400="",J400<=0),"",H400/J400) -> 1.5 | N400: =IF(M400="","",IF(M400<Premissas!$C$8,Premissas!$E$7,IF(M400<Premissas!$C$9,Premissas!$E$8,IF(M400<Premissas!$C$10,Premissas!$E$9,IF(M400<Premissas!$C$11,Premissas!$E$10,IF(M400<Premissas!$C$12,Premissas!$E$11,Premissas!$E$12)))))) -> 350 | O400: =IF(OR(N400="",N400=0),0,N400/Premissas!$C$16) -> 13.461538
A401: 7 | B401: 1974 | C401: PUXADA RECEB | D401: 5688779 | E401: Emanuel Ferreira De Vasconcelos | F401: 102 | G401: 5.2 | H401: 20 | J401: 16 | K401: SIM | L401: GPA | M401: =IF(OR(J401="",J401<=0),"",H401/J401) -> 1.25 | N401: =IF(M401="","",IF(M401<Premissas!$C$8,Premissas!$E$7,IF(M401<Premissas!$C$9,Premissas!$E$8,IF(M401<Premissas!$C$10,Premissas!$E$9,IF(M401<Premissas!$C$11,Premissas!$E$10,IF(M401<Premissas!$C$12,Premissas!$E$11,Premissas!$E$12)))))) -> 200 | O401: =IF(OR(N401="",N401=0),0,N401/Premissas!$C$16) -> 7.6923077
A402: 7 | B402: 1974 | C402: PUXADA RECEB | D402: 5709911 | E402: Joao Victor Mendes Da Silva | F402: 15 | G402: 0.34 | H402: 44 | J402: 16 | K402: SIM | L402: GPA | M402: =IF(OR(J402="",J402<=0),"",H402/J402) -> 2.75 | N402: =IF(M402="","",IF(M402<Premissas!$C$8,Premissas!$E$7,IF(M402<Premissas!$C$9,Premissas!$E$8,IF(M402<Premissas!$C$10,Premissas!$E$9,IF(M402<Premissas!$C$11,Premissas!$E$10,IF(M402<Premissas!$C$12,Premissas!$E$11,Premissas!$E$12)))))) -> 750 | O402: =IF(OR(N402="",N402=0),0,N402/Premissas!$C$16) -> 28.846154
A403: 7 | B403: 1974 | C403: PUXADA RECEB | D403: 5748020 | E403: Vitembergue De Paula Costa | F403: 535 | G403: 20.57 | H403: 26 | J403: 16 | K403: SIM | L403: GPA | M403: =IF(OR(J403="",J403<=0),"",H403/J403) -> 1.625 | N403: =IF(M403="","",IF(M403<Premissas!$C$8,Premissas!$E$7,IF(M403<Premissas!$C$9,Premissas!$E$8,IF(M403<Premissas!$C$10,Premissas!$E$9,IF(M403<Premissas!$C$11,Premissas!$E$10,IF(M403<Premissas!$C$12,Premissas!$E$11,Premissas!$E$12)))))) -> 500 | O403: =IF(OR(N403="",N403=0),0,N403/Premissas!$C$16) -> 19.230769
A404: 7 | B404: 1974 | C404: PUXADA RECEB | D404: 5748194 | E404: Frederico Silva De Almeida | F404: 38 | G404: 0.98 | H404: 39 | J404: 16 | K404: SIM | L404: GPA | M404: =IF(OR(J404="",J404<=0),"",H404/J404) -> 2.4375 | N404: =IF(M404="","",IF(M404<Premissas!$C$8,Premissas!$E$7,IF(M404<Premissas!$C$9,Premissas!$E$8,IF(M404<Premissas!$C$10,Premissas!$E$9,IF(M404<Premissas!$C$11,Premissas!$E$10,IF(M404<Premissas!$C$12,Premissas!$E$11,Premissas!$E$12)))))) -> 750 | O404: =IF(OR(N404="",N404=0),0,N404/Premissas!$C$16) -> 28.846154
A405: 7 | B405: 1974 | C405: PUXADA RECEB | D405: 5749140 | E405: Keven Levi Lima Rodrigues | F405: 157 | G405: 3.75 | H405: 42 | J405: 16 | K405: SIM | L405: GPA | M405: =IF(OR(J405="",J405<=0),"",H405/J405) -> 2.625 | N405: =IF(M405="","",IF(M405<Premissas!$C$8,Premissas!$E$7,IF(M405<Premissas!$C$9,Premissas!$E$8,IF(M405<Premissas!$C$10,Premissas!$E$9,IF(M405<Premissas!$C$11,Premissas!$E$10,IF(M405<Premissas!$C$12,Premissas!$E$11,Premissas!$E$12)))))) -> 750 | O405: =IF(OR(N405="",N405=0),0,N405/Premissas!$C$16) -> 28.846154
A406: 7 | B406: 1974 | C406: PUXADA RECEB | D406: 5952883 | E406: Lailson Crispim Flor Barroso | F406: 482 | G406: 14.75 | H406: 33 | J406: 16 | K406: SIM | L406: GPA | M406: =IF(OR(J406="",J406<=0),"",H406/J406) -> 2.0625 | N406: =IF(M406="","",IF(M406<Premissas!$C$8,Premissas!$E$7,IF(M406<Premissas!$C$9,Premissas!$E$8,IF(M406<Premissas!$C$10,Premissas!$E$9,IF(M406<Premissas!$C$11,Premissas!$E$10,IF(M406<Premissas!$C$12,Premissas!$E$11,Premissas!$E$12)))))) -> 750 | O406: =IF(OR(N406="",N406=0),0,N406/Premissas!$C$16) -> 28.846154
A407: 7 | B407: 1979 | C407: ATIVIDADE OP. EMP. | D407: 302691 | E407: Evandro Soares Naves | F407: 3138 | G407: 141.51 | H407: 22 | I407: 18 | J407: 18 | K407: NÃO | L407: GPA | M407: =IF(OR(J407="",J407<=0),"",H407/J407) -> 1.2222222 | N407: =IF(M407="","",IF(M407<Premissas!$C$8,Premissas!$E$7,IF(M407<Premissas!$C$9,Premissas!$E$8,IF(M407<Premissas!$C$10,Premissas!$E$9,IF(M407<Premissas!$C$11,Premissas!$E$10,IF(M407<Premissas!$C$12,Premissas!$E$11,Premissas!$E$12)))))) -> 200 | O407: =IF(OR(N407="",N407=0),0,N407/Premissas!$C$16) -> 7.6923077
A408: 7 | B408: 1979 | C408: ATIVIDADE OP. EMP. | D408: 431493 | E408: LEONARDO BARBOSA DE MOURA | F408: 906 | G408: 35.82 | H408: 25 | I408: 18 | J408: 18 | K408: NÃO | L408: GPA | M408: =IF(OR(J408="",J408<=0),"",H408/J408) -> 1.3888889 | N408: =IF(M408="","",IF(M408<Premissas!$C$8,Premissas!$E$7,IF(M408<Premissas!$C$9,Premissas!$E$8,IF(M408<Premissas!$C$10,Premissas!$E$9,IF(M408<Premissas!$C$11,Premissas!$E$10,IF(M408<Premissas!$C$12,Premissas!$E$11,Premissas!$E$12)))))) -> 200 | O408: =IF(OR(N408="",N408=0),0,N408/Premissas!$C$16) -> 7.6923077
A409: 7 | B409: 1979 | C409: RECEBIMENTO | D409: 453156 | E409: Sarah Vieira de Melo | F409: 2698 | G409: 100.89 | H409: 27 | I409: 35 | J409: 35 | K409: NÃO | L409: GPA | M409: =IF(OR(J409="",J409<=0),"",H409/J409) -> 0.77142857 | N409: =IF(M409="","",IF(M409<Premissas!$C$8,Premissas!$E$7,IF(M409<Premissas!$C$9,Premissas!$E$8,IF(M409<Premissas!$C$10,Premissas!$E$9,IF(M409<Premissas!$C$11,Premissas!$E$10,IF(M409<Premissas!$C$12,Premissas!$E$11,Premissas!$E$12)))))) -> 0 | O409: =IF(OR(N409="",N409=0),0,N409/Premissas!$C$16) -> 0
A410: 7 | B410: 1979 | C410: ATIVIDADE OP. EMP. | D410: 519447 | E410: FRANCISCO ALMEIDA SANTANA FILHO | F410: 213 | G410: 9.25 | H410: 23 | I410: 18 | J410: 18 | K410: NÃO | L410: GPA | M410: =IF(OR(J410="",J410<=0),"",H410/J410) -> 1.2777778 | N410: =IF(M410="","",IF(M410<Premissas!$C$8,Premissas!$E$7,IF(M410<Premissas!$C$9,Premissas!$E$8,IF(M410<Premissas!$C$10,Premissas!$E$9,IF(M410<Premissas!$C$11,Premissas!$E$10,IF(M410<Premissas!$C$12,Premissas!$E$11,Premissas!$E$12)))))) -> 200 | O410: =IF(OR(N410="",N410=0),0,N410/Premissas!$C$16) -> 7.6923077
A411: 7 | B411: 1979 | C411: CARREGAMENTO | D411: 519447 | E411: FRANCISCO ALMEIDA SANTANA FILHO | F411: 1419 | G411: 89.02 | H411: 16 | J411: 22 | K411: SIM | L411: GPA | M411: =IF(OR(J411="",J411<=0),"",H411/J411) -> 0.72727273 | N411: =IF(M411="","",IF(M411<Premissas!$C$8,Premissas!$E$7,IF(M411<Premissas!$C$9,Premissas!$E$8,IF(M411<Premissas!$C$10,Premissas!$E$9,IF(M411<Premissas!$C$11,Premissas!$E$10,IF(M411<Premissas!$C$12,Premissas!$E$11,Premissas!$E$12)))))) -> 0 | O411: =IF(OR(N411="",N411=0),0,N411/Premissas!$C$16) -> 0
A412: 7 | B412: 1979 | C412: CARREGAMENTO | D412: 531566 | E412: ANGELINO DA SILVA | F412: 29 | G412: 0.06 | H412: 483 | J412: 22 | K412: SIM | L412: GPA | M412: =IF(OR(J412="",J412<=0),"",H412/J412) -> 21.954545 | N412: =IF(M412="","",IF(M412<Premissas!$C$8,Premissas!$E$7,IF(M412<Premissas!$C$9,Premissas!$E$8,IF(M412<Premissas!$C$10,Premissas!$E$9,IF(M412<Premissas!$C$11,Premissas!$E$10,IF(M412<Premissas!$C$12,Premissas!$E$11,Premissas!$E$12)))))) -> 750 | O412: =IF(OR(N412="",N412=0),0,N412/Premissas!$C$16) -> 28.846154
A413: 7 | B413: 1979 | C413: PUXADA RECEB | D413: 531566 | E413: ANGELINO DA SILVA | F413: 107 | G413: 16.75 | H413: 6 | J413: 16 | K413: SIM | L413: GPA | M413: =IF(OR(J413="",J413<=0),"",H413/J413) -> 0.375 | N413: =IF(M413="","",IF(M413<Premissas!$C$8,Premissas!$E$7,IF(M413<Premissas!$C$9,Premissas!$E$8,IF(M413<Premissas!$C$10,Premissas!$E$9,IF(M413<Premissas!$C$11,Premissas!$E$10,IF(M413<Premissas!$C$12,Premissas!$E$11,Premissas!$E$12)))))) -> 0 | O413: =IF(OR(N413="",N413=0),0,N413/Premissas!$C$16) -> 0
A414: 7 | B414: 1979 | C414: RECEBIMENTO | D414: 531566 | E414: ANGELINO DA SILVA | F414: 1669 | G414: 28.44 | H414: 59 | I414: 35 | J414: 35 | K414: NÃO | L414: GPA | M414: =IF(OR(J414="",J414<=0),"",H414/J414) -> 1.6857143 | N414: =IF(M414="","",IF(M414<Premissas!$C$8,Premissas!$E$7,IF(M414<Premissas!$C$9,Premissas!$E$8,IF(M414<Premissas!$C$10,Premissas!$E$9,IF(M414<Premissas!$C$11,Premissas!$E$10,IF(M414<Premissas!$C$12,Premissas!$E$11,Premissas!$E$12)))))) -> 500 | O414: =IF(OR(N414="",N414=0),0,N414/Premissas!$C$16) -> 19.230769
A415: 7 | B415: 1979 | C415: CARREGAMENTO | D415: 5319846 | E415: Helder Rodrigues Carneiro | F415: 276 | G415: 6.98 | H415: 40 | J415: 22 | K415: SIM | L415: GPA | M415: =IF(OR(J415="",J415<=0),"",H415/J415) -> 1.8181818 | N415: =IF(M415="","",IF(M415<Premissas!$C$8,Premissas!$E$7,IF(M415<Premissas!$C$9,Premissas!$E$8,IF(M415<Premissas!$C$10,Premissas!$E$9,IF(M415<Premissas!$C$11,Premissas!$E$10,IF(M415<Premissas!$C$12,Premissas!$E$11,Premissas!$E$12)))))) -> 500 | O415: =IF(OR(N415="",N415=0),0,N415/Premissas!$C$16) -> 19.230769
A416: 7 | B416: 1979 | C416: PUXADA RECEB | D416: 5319846 | E416: Helder Rodrigues Carneiro | F416: 276 | G416: 22.3 | H416: 12 | J416: 16 | K416: SIM | L416: GPA | M416: =IF(OR(J416="",J416<=0),"",H416/J416) -> 0.75 | N416: =IF(M416="","",IF(M416<Premissas!$C$8,Premissas!$E$7,IF(M416<Premissas!$C$9,Premissas!$E$8,IF(M416<Premissas!$C$10,Premissas!$E$9,IF(M416<Premissas!$C$11,Premissas!$E$10,IF(M416<Premissas!$C$12,Premissas!$E$11,Premissas!$E$12)))))) -> 0 | O416: =IF(OR(N416="",N416=0),0,N416/Premissas!$C$16) -> 0
A417: 7 | B417: 1979 | C417: RECEBIMENTO | D417: 5319846 | E417: Helder Rodrigues Carneiro | F417: 9 | G417: 1.53 | H417: 6 | I417: 35 | J417: 35 | K417: NÃO | L417: GPA | M417: =IF(OR(J417="",J417<=0),"",H417/J417) -> 0.17142857 | N417: =IF(M417="","",IF(M417<Premissas!$C$8,Premissas!$E$7,IF(M417<Premissas!$C$9,Premissas!$E$8,IF(M417<Premissas!$C$10,Premissas!$E$9,IF(M417<Premissas!$C$11,Premissas!$E$10,IF(M417<Premissas!$C$12,Premissas!$E$11,Premissas!$E$12)))))) -> 0 | O417: =IF(OR(N417="",N417=0),0,N417/Premissas!$C$16) -> 0
A418: 7 | B418: 1979 | C418: ATIVIDADE OP. EMP. | D418: 532865 | E418: Laylson Da Silva Andrade | F418: 3224 | G418: 81.32 | H418: 40 | I418: 18 | J418: 18 | K418: NÃO | L418: GPA | M418: =IF(OR(J418="",J418<=0),"",H418/J418) -> 2.2222222 | N418: =IF(M418="","",IF(M418<Premissas!$C$8,Premissas!$E$7,IF(M418<Premissas!$C$9,Premissas!$E$8,IF(M418<Premissas!$C$10,Premissas!$E$9,IF(M418<Premissas!$C$11,Premissas!$E$10,IF(M418<Premissas!$C$12,Premissas!$E$11,Premissas!$E$12)))))) -> 750 | O418: =IF(OR(N418="",N418=0),0,N418/Premissas!$C$16) -> 28.846154
A419: 7 | B419: 1979 | C419: PUXADA RECEB | D419: 5442370 | E419: Josue Ferreira Araujo | F419: 66 | G419: 13.65 | H419: 5 | J419: 16 | K419: SIM | L419: GPA | M419: =IF(OR(J419="",J419<=0),"",H419/J419) -> 0.3125 | N419: =IF(M419="","",IF(M419<Premissas!$C$8,Premissas!$E$7,IF(M419<Premissas!$C$9,Premissas!$E$8,IF(M419<Premissas!$C$10,Premissas!$E$9,IF(M419<Premissas!$C$11,Premissas!$E$10,IF(M419<Premissas!$C$12,Premissas!$E$11,Premissas!$E$12)))))) -> 0 | O419: =IF(OR(N419="",N419=0),0,N419/Premissas!$C$16) -> 0
A420: 7 | B420: 1979 | C420: CARREGAMENTO | D420: 5443407 | E420: Ronaldo Damasceno Miranda | F420: 363 | G420: 23.1 | H420: 16 | J420: 22 | K420: SIM | L420: GPA | M420: =IF(OR(J420="",J420<=0),"",H420/J420) -> 0.72727273 | N420: =IF(M420="","",IF(M420<Premissas!$C$8,Premissas!$E$7,IF(M420<Premissas!$C$9,Premissas!$E$8,IF(M420<Premissas!$C$10,Premissas!$E$9,IF(M420<Premissas!$C$11,Premissas!$E$10,IF(M420<Premissas!$C$12,Premissas!$E$11,Premissas!$E$12)))))) -> 0 | O420: =IF(OR(N420="",N420=0),0,N420/Premissas!$C$16) -> 0
A421: 7 | B421: 1979 | C421: PUXADA RECEB | D421: 5443407 | E421: Ronaldo Damasceno Miranda | F421: 502 | G421: 51.63 | H421: 10 | J421: 16 | K421: SIM | L421: GPA | M421: =IF(OR(J421="",J421<=0),"",H421/J421) -> 0.625 | N421: =IF(M421="","",IF(M421<Premissas!$C$8,Premissas!$E$7,IF(M421<Premissas!$C$9,Premissas!$E$8,IF(M421<Premissas!$C$10,Premissas!$E$9,IF(M421<Premissas!$C$11,Premissas!$E$10,IF(M421<Premissas!$C$12,Premissas!$E$11,Premissas!$E$12)))))) -> 0 | O421: =IF(OR(N421="",N421=0),0,N421/Premissas!$C$16) -> 0
A422: 7 | B422: 1979 | C422: RECEBIMENTO | D422: 5443407 | E422: Ronaldo Damasceno Miranda | F422: 349 | G422: 14.4 | H422: 24 | I422: 35 | J422: 35 | K422: NÃO | L422: GPA | M422: =IF(OR(J422="",J422<=0),"",H422/J422) -> 0.68571429 | N422: =IF(M422="","",IF(M422<Premissas!$C$8,Premissas!$E$7,IF(M422<Premissas!$C$9,Premissas!$E$8,IF(M422<Premissas!$C$10,Premissas!$E$9,IF(M422<Premissas!$C$11,Premissas!$E$10,IF(M422<Premissas!$C$12,Premissas!$E$11,Premissas!$E$12)))))) -> 0 | O422: =IF(OR(N422="",N422=0),0,N422/Premissas!$C$16) -> 0
A423: 7 | B423: 1979 | C423: CARREGAMENTO | D423: 5449154 | E423: Fabio William Oliveira De Souza | F423: 403 | G423: 12.38 | H423: 33 | J423: 22 | K423: SIM | L423: GPA | M423: =IF(OR(J423="",J423<=0),"",H423/J423) -> 1.5 | N423: =IF(M423="","",IF(M423<Premissas!$C$8,Premissas!$E$7,IF(M423<Premissas!$C$9,Premissas!$E$8,IF(M423<Premissas!$C$10,Premissas!$E$9,IF(M423<Premissas!$C$11,Premissas!$E$10,IF(M423<Premissas!$C$12,Premissas!$E$11,Premissas!$E$12)))))) -> 350 | O423: =IF(OR(N423="",N423=0),0,N423/Premissas!$C$16) -> 13.461538
A424: 7 | B424: 1979 | C424: PUXADA RECEB | D424: 5449154 | E424: Fabio William Oliveira De Souza | F424: 486 | G424: 59.15 | H424: 8 | J424: 16 | K424: SIM | L424: GPA | M424: =IF(OR(J424="",J424<=0),"",H424/J424) -> 0.5 | N424: =IF(M424="","",IF(M424<Premissas!$C$8,Premissas!$E$7,IF(M424<Premissas!$C$9,Premissas!$E$8,IF(M424<Premissas!$C$10,Premissas!$E$9,IF(M424<Premissas!$C$11,Premissas!$E$10,IF(M424<Premissas!$C$12,Premissas!$E$11,Premissas!$E$12)))))) -> 0 | O424: =IF(OR(N424="",N424=0),0,N424/Premissas!$C$16) -> 0
A425: 7 | B425: 1979 | C425: RECEBIMENTO | D425: 5449154 | E425: Fabio William Oliveira De Souza | F425: 110 | G425: 9.92 | H425: 11 | I425: 35 | J425: 35 | K425: NÃO | L425: GPA | M425: =IF(OR(J425="",J425<=0),"",H425/J425) -> 0.31428571 | N425: =IF(M425="","",IF(M425<Premissas!$C$8,Premissas!$E$7,IF(M425<Premissas!$C$9,Premissas!$E$8,IF(M425<Premissas!$C$10,Premissas!$E$9,IF(M425<Premissas!$C$11,Premissas!$E$10,IF(M425<Premissas!$C$12,Premissas!$E$11,Premissas!$E$12)))))) -> 0 | O425: =IF(OR(N425="",N425=0),0,N425/Premissas!$C$16) -> 0
A426: 7 | B426: 1979 | C426: PUXADA RECEB | D426: 5656575 | E426: Wesley Rodrigues Dos Santos | F426: 22 | G426: 1.93 | H426: 11 | J426: 16 | K426: SIM | L426: GPA | M426: =IF(OR(J426="",J426<=0),"",H426/J426) -> 0.6875 | N426: =IF(M426="","",IF(M426<Premissas!$C$8,Premissas!$E$7,IF(M426<Premissas!$C$9,Premissas!$E$8,IF(M426<Premissas!$C$10,Premissas!$E$9,IF(M426<Premissas!$C$11,Premissas!$E$10,IF(M426<Premissas!$C$12,Premissas!$E$11,Premissas!$E$12)))))) -> 0 | O426: =IF(OR(N426="",N426=0),0,N426/Premissas!$C$16) -> 0
A427: 7 | B427: 1979 | C427: RECEBIMENTO | D427: 568002 | E427: Jefferson Rodrigues Santos | F427: 207 | G427: 33.59 | H427: 6 | I427: 35 | J427: 35 | K427: NÃO | L427: GPA | M427: =IF(OR(J427="",J427<=0),"",H427/J427) -> 0.17142857 | N427: =IF(M427="","",IF(M427<Premissas!$C$8,Premissas!$E$7,IF(M427<Premissas!$C$9,Premissas!$E$8,IF(M427<Premissas!$C$10,Premissas!$E$9,IF(M427<Premissas!$C$11,Premissas!$E$10,IF(M427<Premissas!$C$12,Premissas!$E$11,Premissas!$E$12)))))) -> 0 | O427: =IF(OR(N427="",N427=0),0,N427/Premissas!$C$16) -> 0
A428: 7 | B428: 1979 | C428: CARREGAMENTO | D428: 5692857 | E428: Lucas Dias Noronha | F428: 2038 | G428: 93.49 | H428: 22 | J428: 22 | K428: SIM | L428: GPA | M428: =IF(OR(J428="",J428<=0),"",H428/J428) -> 1 | N428: =IF(M428="","",IF(M428<Premissas!$C$8,Premissas!$E$7,IF(M428<Premissas!$C$9,Premissas!$E$8,IF(M428<Premissas!$C$10,Premissas!$E$9,IF(M428<Premissas!$C$11,Premissas!$E$10,IF(M428<Premissas!$C$12,Premissas!$E$11,Premissas!$E$12)))))) -> 100 | O428: =IF(OR(N428="",N428=0),0,N428/Premissas!$C$16) -> 3.8461538
A429: 7 | B429: 1979 | C429: CARREGAMENTO | D429: 569885 | E429: Eduardo dos Santos Rocha | F429: 296 | G429: 13.37 | H429: 22 | J429: 22 | K429: SIM | L429: GPA | M429: =IF(OR(J429="",J429<=0),"",H429/J429) -> 1 | N429: =IF(M429="","",IF(M429<Premissas!$C$8,Premissas!$E$7,IF(M429<Premissas!$C$9,Premissas!$E$8,IF(M429<Premissas!$C$10,Premissas!$E$9,IF(M429<Premissas!$C$11,Premissas!$E$10,IF(M429<Premissas!$C$12,Premissas!$E$11,Premissas!$E$12)))))) -> 100 | O429: =IF(OR(N429="",N429=0),0,N429/Premissas!$C$16) -> 3.8461538
A430: 7 | B430: 1979 | C430: PUXADA RECEB | D430: 569885 | E430: Eduardo dos Santos Rocha | F430: 95 | G430: 2.73 | H430: 35 | J430: 16 | K430: SIM | L430: GPA | M430: =IF(OR(J430="",J430<=0),"",H430/J430) -> 2.1875 | N430: =IF(M430="","",IF(M430<Premissas!$C$8,Premissas!$E$7,IF(M430<Premissas!$C$9,Premissas!$E$8,IF(M430<Premissas!$C$10,Premissas!$E$9,IF(M430<Premissas!$C$11,Premissas!$E$10,IF(M430<Premissas!$C$12,Premissas!$E$11,Premissas!$E$12)))))) -> 750 | O430: =IF(OR(N430="",N430=0),0,N430/Premissas!$C$16) -> 28.846154
A431: 7 | B431: 1979 | C431: RECEBIMENTO | D431: 569885 | E431: Eduardo dos Santos Rocha | F431: 113 | G431: 0.54 | H431: 209 | I431: 35 | J431: 35 | K431: NÃO | L431: GPA | M431: =IF(OR(J431="",J431<=0),"",H431/J431) -> 5.9714286 | N431: =IF(M431="","",IF(M431<Premissas!$C$8,Premissas!$E$7,IF(M431<Premissas!$C$9,Premissas!$E$8,IF(M431<Premissas!$C$10,Premissas!$E$9,IF(M431<Premissas!$C$11,Premissas!$E$10,IF(M431<Premissas!$C$12,Premissas!$E$11,Premissas!$E$12)))))) -> 750 | O431: =IF(OR(N431="",N431=0),0,N431/Premissas!$C$16) -> 28.846154
A432: 7 | B432: 1979 | C432: RECEBIMENTO | D432: 597537 | E432: Sabrina Vieira de Melo | F432: 1798 | G432: 78.14 | H432: 23 | I432: 35 | J432: 35 | K432: NÃO | L432: GPA | M432: =IF(OR(J432="",J432<=0),"",H432/J432) -> 0.65714286 | N432: =IF(M432="","",IF(M432<Premissas!$C$8,Premissas!$E$7,IF(M432<Premissas!$C$9,Premissas!$E$8,IF(M432<Premissas!$C$10,Premissas!$E$9,IF(M432<Premissas!$C$11,Premissas!$E$10,IF(M432<Premissas!$C$12,Premissas!$E$11,Premissas!$E$12)))))) -> 0 | O432: =IF(OR(N432="",N432=0),0,N432/Premissas!$C$16) -> 0
A433: 7 | B433: 1979 | C433: PUXADA RECEB | D433: 6002293 | E433: Alessandro Pereira Silva | F433: 5 | G433: 3.35 | H433: 1 | J433: 16 | K433: SIM | L433: GPA | M433: =IF(OR(J433="",J433<=0),"",H433/J433) -> 0.0625 | N433: =IF(M433="","",IF(M433<Premissas!$C$8,Premissas!$E$7,IF(M433<Premissas!$C$9,Premissas!$E$8,IF(M433<Premissas!$C$10,Premissas!$E$9,IF(M433<Premissas!$C$11,Premissas!$E$10,IF(M433<Premissas!$C$12,Premissas!$E$11,Premissas!$E$12)))))) -> 0 | O433: =IF(OR(N433="",N433=0),0,N433/Premissas!$C$16) -> 0
A434: 7 | B434: 1979 | C434: ATIVIDADE OP. EMP. | D434: 600573 | E434: Lucivaldo Carneiro Araujo | F434: 1882 | G434: 101.68 | H434: 19 | I434: 18 | J434: 18 | K434: NÃO | L434: GPA | M434: =IF(OR(J434="",J434<=0),"",H434/J434) -> 1.0555556 | N434: =IF(M434="","",IF(M434<Premissas!$C$8,Premissas!$E$7,IF(M434<Premissas!$C$9,Premissas!$E$8,IF(M434<Premissas!$C$10,Premissas!$E$9,IF(M434<Premissas!$C$11,Premissas!$E$10,IF(M434<Premissas!$C$12,Premissas!$E$11,Premissas!$E$12)))))) -> 100 | O434: =IF(OR(N434="",N434=0),0,N434/Premissas!$C$16) -> 3.8461538
A435: 7 | B435: 1979 | C435: CARREGAMENTO | D435: 600573 | E435: Lucivaldo Carneiro Araujo | F435: 11 | G435: 2.05 | H435: 5 | J435: 22 | K435: SIM | L435: GPA | M435: =IF(OR(J435="",J435<=0),"",H435/J435) -> 0.22727273 | N435: =IF(M435="","",IF(M435<Premissas!$C$8,Premissas!$E$7,IF(M435<Premissas!$C$9,Premissas!$E$8,IF(M435<Premissas!$C$10,Premissas!$E$9,IF(M435<Premissas!$C$11,Premissas!$E$10,IF(M435<Premissas!$C$12,Premissas!$E$11,Premissas!$E$12)))))) -> 0 | O435: =IF(OR(N435="",N435=0),0,N435/Premissas!$C$16) -> 0
A436: 7 | B436: 7801 | C436: ATIVIDADE OP. EMP. | D436: 101339 | E436: SERGIO JOSE DA SILVA | F436: 1941 | G436: 161.75 | H436: 12 | J436: 20 | K436: SIM | L436: GPA | M436: =IF(OR(J436="",J436<=0),"",H436/J436) -> 0.6 | N436: =IF(M436="","",IF(M436<Premissas!$C$8,Premissas!$E$7,IF(M436<Premissas!$C$9,Premissas!$E$8,IF(M436<Premissas!$C$10,Premissas!$E$9,IF(M436<Premissas!$C$11,Premissas!$E$10,IF(M436<Premissas!$C$12,Premissas!$E$11,Premissas!$E$12)))))) -> 0 | O436: =IF(OR(N436="",N436=0),0,N436/Premissas!$C$16) -> 0
A437: 7 | B437: 7801 | C437: ATIVIDADE OP. EMP. | D437: 10181 | E437: Raimundo Alves | F437: 1720 | G437: 188.68 | H437: 9 | J437: 20 | K437: SIM | L437: GPA | M437: =IF(OR(J437="",J437<=0),"",H437/J437) -> 0.45 | N437: =IF(M437="","",IF(M437<Premissas!$C$8,Premissas!$E$7,IF(M437<Premissas!$C$9,Premissas!$E$8,IF(M437<Premissas!$C$10,Premissas!$E$9,IF(M437<Premissas!$C$11,Premissas!$E$10,IF(M437<Premissas!$C$12,Premissas!$E$11,Premissas!$E$12)))))) -> 0 | O437: =IF(OR(N437="",N437=0),0,N437/Premissas!$C$16) -> 0
A438: 7 | B438: 7801 | C438: ATIVIDADE OP. EMP. | D438: 123922 | E438: Marciel Francisco Da Silva | F438: 1478 | G438: 81.38 | H438: 18 | J438: 20 | K438: SIM | L438: GPA | M438: =IF(OR(J438="",J438<=0),"",H438/J438) -> 0.9 | N438: =IF(M438="","",IF(M438<Premissas!$C$8,Premissas!$E$7,IF(M438<Premissas!$C$9,Premissas!$E$8,IF(M438<Premissas!$C$10,Premissas!$E$9,IF(M438<Premissas!$C$11,Premissas!$E$10,IF(M438<Premissas!$C$12,Premissas!$E$11,Premissas!$E$12)))))) -> 0 | O438: =IF(OR(N438="",N438=0),0,N438/Premissas!$C$16) -> 0
A439: 7 | B439: 7801 | C439: PUXADA RECEB | D439: 124438 | E439: JAIR DIAS DOS SANTOS | F439: 11 | G439: 1.67 | H439: 7 | J439: 16 | K439: SIM | L439: GPA | M439: =IF(OR(J439="",J439<=0),"",H439/J439) -> 0.4375 | N439: =IF(M439="","",IF(M439<Premissas!$C$8,Premissas!$E$7,IF(M439<Premissas!$C$9,Premissas!$E$8,IF(M439<Premissas!$C$10,Premissas!$E$9,IF(M439<Premissas!$C$11,Premissas!$E$10,IF(M439<Premissas!$C$12,Premissas!$E$11,Premissas!$E$12)))))) -> 0 | O439: =IF(OR(N439="",N439=0),0,N439/Premissas!$C$16) -> 0
A440: 7 | B440: 7801 | C440: RECEBIMENTO | D440: 124438 | E440: JAIR DIAS DOS SANTOS | F440: 2580 | G440: 148.11 | H440: 17 | J440: 17 | K440: SIM | L440: GPA | M440: =IF(OR(J440="",J440<=0),"",H440/J440) -> 1 | N440: =IF(M440="","",IF(M440<Premissas!$C$8,Premissas!$E$7,IF(M440<Premissas!$C$9,Premissas!$E$8,IF(M440<Premissas!$C$10,Premissas!$E$9,IF(M440<Premissas!$C$11,Premissas!$E$10,IF(M440<Premissas!$C$12,Premissas!$E$11,Premissas!$E$12)))))) -> 100 | O440: =IF(OR(N440="",N440=0),0,N440/Premissas!$C$16) -> 3.8461538
A441: 7 | B441: 7801 | C441: ATIVIDADE OP. EMP. | D441: 138654 | E441: Pedro Pereira Da Silva Neto | F441: 4042 | G441: 190.15 | H441: 21 | J441: 20 | K441: SIM | L441: GPA | M441: =IF(OR(J441="",J441<=0),"",H441/J441) -> 1.05 | N441: =IF(M441="","",IF(M441<Premissas!$C$8,Premissas!$E$7,IF(M441<Premissas!$C$9,Premissas!$E$8,IF(M441<Premissas!$C$10,Premissas!$E$9,IF(M441<Premissas!$C$11,Premissas!$E$10,IF(M441<Premissas!$C$12,Premissas!$E$11,Premissas!$E$12)))))) -> 100 | O441: =IF(OR(N441="",N441=0),0,N441/Premissas!$C$16) -> 3.8461538
A442: 7 | B442: 7801 | C442: ATIVIDADE OP. EMP. | D442: 153174 | E442: JOSE ADRIANO OLIVEIRA DOS SANTOS | F442: 1409 | G442: 192.73 | H442: 7 | J442: 20 | K442: SIM | L442: GPA | M442: =IF(OR(J442="",J442<=0),"",H442/J442) -> 0.35 | N442: =IF(M442="","",IF(M442<Premissas!$C$8,Premissas!$E$7,IF(M442<Premissas!$C$9,Premissas!$E$8,IF(M442<Premissas!$C$10,Premissas!$E$9,IF(M442<Premissas!$C$11,Premissas!$E$10,IF(M442<Premissas!$C$12,Premissas!$E$11,Premissas!$E$12)))))) -> 0 | O442: =IF(OR(N442="",N442=0),0,N442/Premissas!$C$16) -> 0
A443: 7 | B443: 7801 | C443: ATIVIDADE OP. EMP. | D443: 156823 | E443: MARCIO PAIXAO DE SOUZA | F443: 601 | G443: 96.49 | H443: 6 | J443: 20 | K443: SIM | L443: GPA | M443: =IF(OR(J443="",J443<=0),"",H443/J443) -> 0.3 | N443: =IF(M443="","",IF(M443<Premissas!$C$8,Premissas!$E$7,IF(M443<Premissas!$C$9,Premissas!$E$8,IF(M443<Premissas!$C$10,Premissas!$E$9,IF(M443<Premissas!$C$11,Premissas!$E$10,IF(M443<Premissas!$C$12,Premissas!$E$11,Premissas!$E$12)))))) -> 0 | O443: =IF(OR(N443="",N443=0),0,N443/Premissas!$C$16) -> 0
A444: 7 | B444: 7801 | C444: ATIVIDADE OP. EMP. | D444: 159790 | E444: Sergio SOARES COSTA | F444: 1854 | G444: 162.15 | H444: 11 | J444: 20 | K444: SIM | L444: GPA | M444: =IF(OR(J444="",J444<=0),"",H444/J444) -> 0.55 | N444: =IF(M444="","",IF(M444<Premissas!$C$8,Premissas!$E$7,IF(M444<Premissas!$C$9,Premissas!$E$8,IF(M444<Premissas!$C$10,Premissas!$E$9,IF(M444<Premissas!$C$11,Premissas!$E$10,IF(M444<Premissas!$C$12,Premissas!$E$11,Premissas!$E$12)))))) -> 0 | O444: =IF(OR(N444="",N444=0),0,N444/Premissas!$C$16) -> 0
A445: 7 | B445: 7801 | C445: RECEBIMENTO | D445: 162817 | E445: Ivanil Augusto De Souza | F445: 1365 | G445: 74.04 | H445: 18 | J445: 17 | K445: SIM | L445: GPA | M445: =IF(OR(J445="",J445<=0),"",H445/J445) -> 1.0588235 | N445: =IF(M445="","",IF(M445<Premissas!$C$8,Premissas!$E$7,IF(M445<Premissas!$C$9,Premissas!$E$8,IF(M445<Premissas!$C$10,Premissas!$E$9,IF(M445<Premissas!$C$11,Premissas!$E$10,IF(M445<Premissas!$C$12,Premissas!$E$11,Premissas!$E$12)))))) -> 100 | O445: =IF(OR(N445="",N445=0),0,N445/Premissas!$C$16) -> 3.8461538
A446: 7 | B446: 7801 | C446: PUXADA RECEB | D446: 162825 | E446: Antonio Tenorio Da Silva Soares | F446: 12 | G446: 20.01 | H446: 1 | J446: 16 | K446: SIM | L446: GPA | M446: =IF(OR(J446="",J446<=0),"",H446/J446) -> 0.0625 | N446: =IF(M446="","",IF(M446<Premissas!$C$8,Premissas!$E$7,IF(M446<Premissas!$C$9,Premissas!$E$8,IF(M446<Premissas!$C$10,Premissas!$E$9,IF(M446<Premissas!$C$11,Premissas!$E$10,IF(M446<Premissas!$C$12,Premissas!$E$11,Premissas!$E$12)))))) -> 0 | O446: =IF(OR(N446="",N446=0),0,N446/Premissas!$C$16) -> 0
... A985: 7 | B985: 930 | C985: ATIVIDADE OP. EMP. | D985: 98905 | E985: ALEXANDRE DE OLIVEIRA CANDIDO | F985: 3062 | G985: 106.49 | H985: 29 | J985: 20 | K985: SIM | L985: GPA | M985: =IF(OR(J985="",J985<=0),"",H985/J985) -> 1.45 | N985: =IF(M985="","",IF(M985<Premissas!$C$8,Premissas!$E$7,IF(M985<Premissas!$C$9,Premissas!$E$8,IF(M985<Premissas!$C$10,Premissas!$E$9,IF(M985<Premissas!$C$11,Premissas!$E$10,IF(M985<Premissas!$C$12,Premissas!$E$11,Premissas!$E$12)))))) -> 350 | O985: =IF(OR(N985="",N985=0),0,N985/Premissas!$C$16) -> 13.461538
A986: 8 | B986: 1942 | C986: RECEBIMENTO | D986: 144295 | E986: WAGNNO DE SOUSA VELOSO | F986: 2232 | G986: 116.94 | H986: 19 | I986: 17 | J986: 17 | K986: NÃO | L986: GPA | M986: =IF(OR(J986="",J986<=0),"",H986/J986) -> 1.1176471 | N986: =IF(M986="","",IF(M986<Premissas!$C$8,Premissas!$E$7,IF(M986<Premissas!$C$9,Premissas!$E$8,IF(M986<Premissas!$C$10,Premissas!$E$9,IF(M986<Premissas!$C$11,Premissas!$E$10,IF(M986<Premissas!$C$12,Premissas!$E$11,Premissas!$E$12)))))) -> 100 | O986: =IF(OR(N986="",N986=0),0,N986/Premissas!$C$16) -> 3.8461538
...

Sheet Consolidado_HC
A1: MES | B1: USUARIO | C1: COLABORADOR | D1: CD_PRINCIPAL | E1: ATIVIDADES | F1: N_REG | G1: MELHOR_FATOR | H1: FATOR_MEDIO | I1: QTD_TOTAL | J1: HORAS | K1: FAIXA | L1: VALOR_MENSAL | M1: VALOR_DIARIO | N1: NO_TETO
A2: 7 | B2: 5439698 | C2: GABRIEL RODRIGUES DE VASCONCELOS | D2: 1942 | E2: PUXADA RECEB | F2: =COUNTIFS(Detalhe_Registro!$A:$A,A2,Detalhe_Registro!$D:$D,B2) -> 1 | G2: 1.125 | H2: 1.125 | I2: =SUMIFS(Detalhe_Registro!$F:$F,Detalhe_Registro!$A:$A,A2,Detalhe_Registro!$D:$D,B2) -> 179 | J2: =SUMIFS(Detalhe_Registro!$G:$G,Detalhe_Registro!$A:$A,A2,Detalhe_Registro!$D:$D,B2) -> 10.14 | K2: =IF(G2="","",IF(G2<Premissas!$C$8,"< 1,00",IF(G2<Premissas!$C$9,"1,00 – 1,19",IF(G2<Premissas!$C$10,"1,20 – 1,39",IF(G2<Premissas!$C$11,"1,40 – 1,59",IF(G2<Premissas!$C$12,"1,60 – 1,99","≥ 2,00")))))) -> 1,00 – 1,19 | L2: =IF(G2="","",MIN(Premissas!$C$17,IF(G2<Premissas!$C$8,Premissas!$E$7,IF(G2<Premissas!$C$9,Premissas!$E$8,IF(G2<Premissas!$C$10,Premissas!$E$9,IF(G2<Premissas!$C$11,Premissas!$E$10,IF(G2<Premissas!$C$12,Premissas!$E$11,Premissas!$E$12))))))) -> 100 | M2: =IF(OR(L2="",L2=0),0,L2/Premissas!$C$16) -> 3.8461538 | N2: =IF(L2>=Premissas!$C$17,"SIM","NÃO") -> NÃO
A3: 7 | B3: 570046 | C3: ADRIANO PEREIRA DE SOUSA | D3: 1942 | E3: RECEBIMENTO | F3: =COUNTIFS(Detalhe_Registro!$A:$A,A3,Detalhe_Registro!$D:$D,B3) -> 1 | G3: 1.588235 | H3: 1.588235 | I3: =SUMIFS(Detalhe_Registro!$F:$F,Detalhe_Registro!$A:$A,A3,Detalhe_Registro!$D:$D,B3) -> 701 | J3: =SUMIFS(Detalhe_Registro!$G:$G,Detalhe_Registro!$A:$A,A3,Detalhe_Registro!$D:$D,B3) -> 25.59 | K3: =IF(G3="","",IF(G3<Premissas!$C$8,"< 1,00",IF(G3<Premissas!$C$9,"1,00 – 1,19",IF(G3<Premissas!$C$10,"1,20 – 1,39",IF(G3<Premissas!$C$11,"1,40 – 1,59",IF(G3<Premissas!$C$12,"1,60 – 1,99","≥ 2,00")))))) -> 1,40 – 1,59 | L3: =IF(G3="","",MIN(Premissas!$C$17,IF(G3<Premissas!$C$8,Premissas!$E$7,IF(G3<Premissas!$C$9,Premissas!$E$8,IF(G3<Premissas!$C$10,Premissas!$E$9,IF(G3<Premissas!$C$11,Premissas!$E$10,IF(G3<Premissas!$C$12,Premissas!$E$11,Premissas!$E$12))))))) -> 350 | M3: =IF(OR(L3="",L3=0),0,L3/Premissas!$C$16) -> 13.461538 | N3: =IF(L3>=Premissas!$C$17,"SIM","NÃO") -> NÃO
A4: 7 | B4: 696054 | C4: AILTON MANGUEIRA DE ARAUJO | D4: 1942 | E4: ATIVIDADE OP. EMP. | F4: =COUNTIFS(Detalhe_Registro!$A:$A,A4,Detalhe_Registro!$D:$D,B4) -> 1 | G4: 1.85 | H4: 1.85 | I4: =SUMIFS(Detalhe_Registro!$F:$F,Detalhe_Registro!$A:$A,A4,Detalhe_Registro!$D:$D,B4) -> 1948 | J4: =SUMIFS(Detalhe_Registro!$G:$G,Detalhe_Registro!$A:$A,A4,Detalhe_Registro!$D:$D,B4) -> 52.62 | K4: =IF(G4="","",IF(G4<Premissas!$C$8,"< 1,00",IF(G4<Premissas!$C$9,"1,00 – 1,19",IF(G4<Premissas!$C$10,"1,20 – 1,39",IF(G4<Premissas!$C$11,"1,40 – 1,59",IF(G4<Premissas!$C$12,"1,60 – 1,99","≥ 2,00")))))) -> 1,60 – 1,99 | L4: =IF(G4="","",MIN(Premissas!$C$17,IF(G4<Premissas!$C$8,Premissas!$E$7,IF(G4<Premissas!$C$9,Premissas!$E$8,IF(G4<Premissas!$C$10,Premissas!$E$9,IF(G4<Premissas!$C$11,Premissas!$E$10,IF(G4<Premissas!$C$12,Premissas!$E$11,Premissas!$E$12))))))) -> 500 | M4: =IF(OR(L4="",L4=0),0,L4/Premissas!$C$16) -> 19.230769 | N4: =IF(L4>=Premissas!$C$17,"SIM","NÃO") -> NÃO
A5: 7 | B5: 687013 | C5: ALESSANDRO DE SOUSA BINA | D5: 1942 | E5: CARREGAMENTO | F5: =COUNTIFS(Detalhe_Registro!$A:$A,A5,Detalhe_Registro!$D:$D,B5) -> 1 | G5: 11.863636 | H5: 11.863636 | I5: =SUMIFS(Detalhe_Registro!$F:$F,Detalhe_Registro!$A:$A,A5,Detalhe_Registro!$D:$D,B5) -> 120 | J5: =SUMIFS(Detalhe_Registro!$G:$G,Detalhe_Registro!$A:$A,A5,Detalhe_Registro!$D:$D,B5) -> 0.46 | K5: =IF(G5="","",IF(G5<Premissas!$C$8,"< 1,00",IF(G5<Premissas!$C$9,"1,00 – 1,19",IF(G5<Premissas!$C$10,"1,20 – 1,39",IF(G5<Premissas!$C$11,"1,40 – 1,59",IF(G5<Premissas!$C$12,"1,60 – 1,99","≥ 2,00")))))) -> ≥ 2,00 | L5: =IF(G5="","",MIN(Premissas!$C$17,IF(G5<Premissas!$C$8,Premissas!$E$7,IF(G5<Premissas!$C$9,Premissas!$E$8,IF(G5<Premissas!$C$10,Premissas!$E$9,IF(G5<Premissas!$C$11,Premissas!$E$10,IF(G5<Premissas!$C$12,Premissas!$E$11,Premissas!$E$12))))))) -> 750 | M5: =IF(OR(L5="",L5=0),0,L5/Premissas!$C$16) -> 28.846154 | N5: =IF(L5>=Premissas!$C$17,"SIM","NÃO") -> SIM
A6: 7 | B6: 5432979 | C6: ALEXANDRE FERREIRA | D6: 1942 | E6: PUXADA RECEB | F6: =COUNTIFS(Detalhe_Registro!$A:$A,A6,Detalhe_Registro!$D:$D,B6) -> 1 | G6: 0.5 | H6: 0.5 | I6: =SUMIFS(Detalhe_Registro!$F:$F,Detalhe_Registro!$A:$A,A6,Detalhe_Registro!$D:$D,B6) -> 188 | J6: =SUMIFS(Detalhe_Registro!$G:$G,Detalhe_Registro!$A:$A,A6,Detalhe_Registro!$D:$D,B6) -> 24.66 | K6: =IF(G6="","",IF(G6<Premissas!$C$8,"< 1,00",IF(G6<Premissas!$C$9,"1,00 – 1,19",IF(G6<Premissas!$C$10,"1,20 – 1,39",IF(G6<Premissas!$C$11,"1,40 – 1,59",IF(G6<Premissas!$C$12,"1,60 – 1,99","≥ 2,00")))))) -> < 1,00 | L6: =IF(G6="","",MIN(Premissas!$C$17,IF(G6<Premissas!$C$8,Premissas!$E$7,IF(G6<Premissas!$C$9,Premissas!$E$8,IF(G6<Premissas!$C$10,Premissas!$E$9,IF(G6<Premissas!$C$11,Premissas!$E$10,IF(G6<Premissas!$C$12,Premissas!$E$11,Premissas!$E$12))))))) -> 0 | M6: =IF(OR(L6="",L6=0),0,L6/Premissas!$C$16) -> 0 | N6: =IF(L6>=Premissas!$C$17,"SIM","NÃO") -> NÃO
A7: 7 | B7: 5227321 | C7: ANILTON APARECIDO DE CAMPOS | D7: 1942 | E7: CARREGAMENTO | F7: =COUNTIFS(Detalhe_Registro!$A:$A,A7,Detalhe_Registro!$D:$D,B7) -> 1 | G7: 1.863636 | H7: 1.863636 | I7: =SUMIFS(Detalhe_Registro!$F:$F,Detalhe_Registro!$A:$A,A7,Detalhe_Registro!$D:$D,B7) -> 1263 | J7: =SUMIFS(Detalhe_Registro!$G:$G,Detalhe_Registro!$A:$A,A7,Detalhe_Registro!$D:$D,B7) -> 30.72 | K7: =IF(G7="","",IF(G7<Premissas!$C$8,"< 1,00",IF(G7<Premissas!$C$9,"1,00 – 1,19",IF(G7<Premissas!$C$10,"1,20 – 1,39",IF(G7<Premissas!$C$11,"1,40 – 1,59",IF(G7<Premissas!$C$12,"1,60 – 1,99","≥ 2,00")))))) -> 1,60 – 1,99 | L7: =IF(G7="","",MIN(Premissas!$C$17,IF(G7<Premissas!$C$8,Premissas!$E$7,IF(G7<Premissas!$C$9,Premissas!$E$8,IF(G7<Premissas!$C$10,Premissas!$E$9,IF(G7<Premissas!$C$11,Premissas!$E$10,IF(G7<Premissas!$C$12,Premissas!$E$11,Premissas!$E$12))))))) -> 500 | M7: =IF(OR(L7="",L7=0),0,L7/Premissas!$C$16) -> 19.230769 | N7: =IF(L7>=Premissas!$C$17,"SIM","NÃO") -> NÃO
A8: 7 | B8: 587354 | C8: ARLINDO CARDOSO DA SILVA JUNIOR | D8: 1942 | E8: ATIVIDADE OP. EMP. | F8: =COUNTIFS(Detalhe_Registro!$A:$A,A8,Detalhe_Registro!$D:$D,B8) -> 1 | G8: 1.1 | H8: 1.1 | I8: =SUMIFS(Detalhe_Registro!$F:$F,Detalhe_Registro!$A:$A,A8,Detalhe_Registro!$D:$D,B8) -> 1398 | J8: =SUMIFS(Detalhe_Registro!$G:$G,Detalhe_Registro!$A:$A,A8,Detalhe_Registro!$D:$D,B8) -> 64.09 | K8: =IF(G8="","",IF(G8<Premissas!$C$8,"< 1,00",IF(G8<Premissas!$C$9,"1,00 – 1,19",IF(G8<Premissas!$C$10,"1,20 – 1,39",IF(G8<Premissas!$C$11,"1,40 – 1,59",IF(G8<Premissas!$C$12,"1,60 – 1,99","≥ 2,00")))))) -> 1,00 – 1,19 | L8: =IF(G8="","",MIN(Premissas!$C$17,IF(G8<Premissas!$C$8,Premissas!$E$7,IF(G8<Premissas!$C$9,Premissas!$E$8,IF(G8<Premissas!$C$10,Premissas!$E$9,IF(G8<Premissas!$C$11,Premissas!$E$10,IF(G8<Premissas!$C$12,Premissas!$E$11,Premissas!$E$12))))))) -> 100 | M8: =IF(OR(L8="",L8=0),0,L8/Premissas!$C$16) -> 3.8461538 | N8: =IF(L8>=Premissas!$C$17,"SIM","NÃO") -> NÃO
A9: 7 | B9: 46632 | C9: ARTHUR PEREIRA | D9: 1942 | E9: RECEBIMENTO | F9: =COUNTIFS(Detalhe_Registro!$A:$A,A9,Detalhe_Registro!$D:$D,B9) -> 1 | G9: 1.058824 | H9: 1.058824 | I9: =SUMIFS(Detalhe_Registro!$F:$F,Detalhe_Registro!$A:$A,A9,Detalhe_Registro!$D:$D,B9) -> 2235 | J9: =SUMIFS(Detalhe_Registro!$G:$G,Detalhe_Registro!$A:$A,A9,Detalhe_Registro!$D:$D,B9) -> 123.77 | K9: =IF(G9="","",IF(G9<Premissas!$C$8,"< 1,00",IF(G9<Premissas!$C$9,"1,00 – 1,19",IF(G9<Premissas!$C$10,"1,20 – 1,39",IF(G9<Premissas!$C$11,"1,40 – 1,59",IF(G9<Premissas!$C$12,"1,60 – 1,99","≥ 2,00")))))) -> 1,00 – 1,19 | L9: =IF(G9="","",MIN(Premissas!$C$17,IF(G9<Premissas!$C$8,Premissas!$E$7,IF(G9<Premissas!$C$9,Premissas!$E$8,IF(G9<Premissas!$C$10,Premissas!$E$9,IF(G9<Premissas!$C$11,Premissas!$E$10,IF(G9<Premissas!$C$12,Premissas!$E$11,Premissas!$E$12))))))) -> 100 | M9: =IF(OR(L9="",L9=0),0,L9/Premissas!$C$16) -> 3.8461538 | N9: =IF(L9>=Premissas!$C$17,"SIM","NÃO") -> NÃO
A10: 7 | B10: 5448530 | C10: Alef Paixao do Nascimento | D10: 1942 | E10: CARREGAMENTO | F10: =COUNTIFS(Detalhe_Registro!$A:$A,A10,Detalhe_Registro!$D:$D,B10) -> 1 | G10: 2.045455 | H10: 2.045455 | I10: =SUMIFS(Detalhe_Registro!$F:$F,Detalhe_Registro!$A:$A,A10,Detalhe_Registro!$D:$D,B10) -> 1299 | J10: =SUMIFS(Detalhe_Registro!$G:$G,Detalhe_Registro!$A:$A,A10,Detalhe_Registro!$D:$D,B10) -> 28.93 | K10: =IF(G10="","",IF(G10<Premissas!$C$8,"< 1,00",IF(G10<Premissas!$C$9,"1,00 – 1,19",IF(G10<Premissas!$C$10,"1,20 – 1,39",IF(G10<Premissas!$C$11,"1,40 – 1,59",IF(G10<Premissas!$C$12,"1,60 – 1,99","≥ 2,00")))))) -> ≥ 2,00 | L10: =IF(G10="","",MIN(Premissas!$C$17,IF(G10<Premissas!$C$8,Premissas!$E$7,IF(G10<Premissas!$C$9,Premissas!$E$8,IF(G10<Premissas!$C$10,Premissas!$E$9,IF(G10<Premissas!$C$11,Premissas!$E$10,IF(G10<Premissas!$C$12,Premissas!$E$11,Premissas!$E$12))))))) -> 750 | M10: =IF(OR(L10="",L10=0),0,L10/Premissas!$C$16) -> 28.846154 | N10: =IF(L10>=Premissas!$C$17,"SIM","NÃO") -> SIM
A11: 7 | B11: 690554 | C11: Andre Gomes Lima | D11: 1942 | E11: PUXADA RECEB | RECEBIMENTO | F11: =COUNTIFS(Detalhe_Registro!$A:$A,A11,Detalhe_Registro!$D:$D,B11) -> 2 | G11: 2.647059 | H11: 1.948529 | I11: =SUMIFS(Detalhe_Registro!$F:$F,Detalhe_Registro!$A:$A,A11,Detalhe_Registro!$D:$D,B11) -> 4744 | J11: =SUMIFS(Detalhe_Registro!$G:$G,Detalhe_Registro!$A:$A,A11,Detalhe_Registro!$D:$D,B11) -> 106.95 | K11: =IF(G11="","",IF(G11<Premissas!$C$8,"< 1,00",IF(G11<Premissas!$C$9,"1,00 – 1,19",IF(G11<Premissas!$C$10,"1,20 – 1,39",IF(G11<Premissas!$C$11,"1,40 – 1,59",IF(G11<Premissas!$C$12,"1,60 – 1,99","≥ 2,00")))))) -> ≥ 2,00 | L11: =IF(G11="","",MIN(Premissas!$C$17,IF(G11<Premissas!$C$8,Premissas!$E$7,IF(G11<Premissas!$C$9,Premissas!$E$8,IF(G11<Premissas!$C$10,Premissas!$E$9,IF(G11<Premissas!$C$11,Premissas!$E$10,IF(G11<Premissas!$C$12,Premissas!$E$11,Premissas!$E$12))))))) -> 750 | M11: =IF(OR(L11="",L11=0),0,L11/Premissas!$C$16) -> 28.846154 | N11: =IF(L11>=Premissas!$C$17,"SIM","NÃO") -> SIM
A12: 7 | B12: 5030994 | C12: Aron Ribeiro Pereira | D12: 1942 | E12: CARREGAMENTO | F12: =COUNTIFS(Detalhe_Registro!$A:$A,A12,Detalhe_Registro!$D:$D,B12) -> 1 | G12: 3.227273 | H12: 3.227273 | I12: =SUMIFS(Detalhe_Registro!$F:$F,Detalhe_Registro!$A:$A,A12,Detalhe_Registro!$D:$D,B12) -> 180 | J12: =SUMIFS(Detalhe_Registro!$G:$G,Detalhe_Registro!$A:$A,A12,Detalhe_Registro!$D:$D,B12) -> 2.52 | K12: =IF(G12="","",IF(G12<Premissas!$C$8,"< 1,00",IF(G12<Premissas!$C$9,"1,00 – 1,19",IF(G12<Premissas!$C$10,"1,20 – 1,39",IF(G12<Premissas!$C$11,"1,40 – 1,59",IF(G12<Premissas!$C$12,"1,60 – 1,99","≥ 2,00")))))) -> ≥ 2,00 | L12: =IF(G12="","",MIN(Premissas!$C$17,IF(G12<Premissas!$C$8,Premissas!$E$7,IF(G12<Premissas!$C$9,Premissas!$E$8,IF(G12<Premissas!$C$10,Premissas!$E$9,IF(G12<Premissas!$C$11,Premissas!$E$10,IF(G12<Premissas!$C$12,Premissas!$E$11,Premissas!$E$12))))))) -> 750 | M12: =IF(OR(L12="",L12=0),0,L12/Premissas!$C$16) -> 28.846154 | N12: =IF(L12>=Premissas!$C$17,"SIM","NÃO") -> SIM
A13: 7 | B13: 5854709 | C13: Arthur Filho Barbosa Ribeiro Junior | D13: 1942 | E13: PUXADA RECEB | F13: =COUNTIFS(Detalhe_Registro!$A:$A,A13,Detalhe_Registro!$D:$D,B13) -> 1 | G13: 1.25 | H13: 1.25 | I13: =SUMIFS(Detalhe_Registro!$F:$F,Detalhe_Registro!$A:$A,A13,Detalhe_Registro!$D:$D,B13) -> 2062 | J13: =SUMIFS(Detalhe_Registro!$G:$G,Detalhe_Registro!$A:$A,A13,Detalhe_Registro!$D:$D,B13) -> 102.15 | K13: =IF(G13="","",IF(G13<Premissas!$C$8,"< 1,00",IF(G13<Premissas!$C$9,"1,00 – 1,19",IF(G13<Premissas!$C$10,"1,20 – 1,39",IF(G13<Premissas!$C$11,"1,40 – 1,59",IF(G13<Premissas!$C$12,"1,60 – 1,99","≥ 2,00")))))) -> 1,20 – 1,39 | L13: =IF(G13="","",MIN(Premissas!$C$17,IF(G13<Premissas!$C$8,Premissas!$E$7,IF(G13<Premissas!$C$9,Premissas!$E$8,IF(G13<Premissas!$C$10,Premissas!$E$9,IF(G13<Premissas!$C$11,Premissas!$E$10,IF(G13<Premissas!$C$12,Premissas!$E$11,Premissas!$E$12))))))) -> 200 | M13: =IF(OR(L13="",L13=0),0,L13/Premissas!$C$16) -> 7.6923077 | N13: =IF(L13>=Premissas!$C$17,"SIM","NÃO") -> NÃO
... A1594: 8 | B1594: 5781639 | C1594: Yago Yuri Da Costa Silva | D1594: 930 | E1594: CARREGAMENTO | F1594: =COUNTIFS(Detalhe_Registro!$A:$A,A1594,Detalhe_Registro!$D:$D,B1594) -> 1 | G1594: 2.181818 | H1594: 2.181818 | I1594: =SUMIFS(Detalhe_Registro!$F:$F,Detalhe_Registro!$A:$A,A1594,Detalhe_Registro!$D:$D,B1594) -> 2001 | J1594: =SUMIFS(Detalhe_Registro!$G:$G,Detalhe_Registro!$A:$A,A1594,Detalhe_Registro!$D:$D,B1594) -> 41.8 | K1594: =IF(G1594="","",IF(G1594<Premissas!$C$8,"< 1,00",IF(G1594<Premissas!$C$9,"1,00 – 1,19",IF(G1594<Premissas!$C$10,"1,20 – 1,39",IF(G1594<Premissas!$C$11,"1,40 – 1,59",IF(G1594<Premissas!$C$12,"1,60 – 1,99","≥ 2,00")))))) -> ≥ 2,00 | L1594: =IF(G1594="","",MIN(Premissas!$C$17,IF(G1594<Premissas!$C$8,Premissas!$E$7,IF(G1594<Premissas!$C$9,Premissas!$E$8,IF(G1594<Premissas!$C$10,Premissas!$E$9,IF(G1594<Premissas!$C$11,Premissas!$E$10,IF(G1594<Premissas!$C$12,Premissas!$E$11,Premissas!$E$12))))))) -> 750 | M1594: =IF(OR(L1594="",L1594=0),0,L1594/Premissas!$C$16) -> 28.846154 | N1594: =IF(L1594>=Premissas!$C$17,"SIM","NÃO") -> SIM

Sheet Resumo_Mes_CD
A1: RESUMO POR MÊS E CD — CUSTO MENSAL, DIÁRIO E LINHA DE GANHO
A3: MES | B3: CD | C3: HCs REG. | D3: CUSTO_MENSAL | E3: HCs_ABAIXO | F3: HCs_TETO | G3: %_ABAIXO | H3: %_TETO | I3: GANHO_30% | J3: CENARIO_30% | K3: CUSTO_DIARIO
A4: 7 | B4: 409 | C4: =COUNTIFS(Consolidado_HC!$A:$A,A4,Consolidado_HC!$D:$D,B4) -> 147 | D4: =SUMIFS(Consolidado_HC!$L:$L,Consolidado_HC!$A:$A,A4,Consolidado_HC!$D:$D,B4) -> 56650 | E4: =COUNTIFS(Consolidado_HC!$A:$A,A4,Consolidado_HC!$D:$D,B4,Consolidado_HC!$L:$L,0) -> 29 | F4: =COUNTIFS(Consolidado_HC!$A:$A,A4,Consolidado_HC!$D:$D,B4,Consolidado_HC!$N:$N,"SIM") -> 50 | G4: =IF(C4=0,0,E4/C4) -> 0.19727891 | H4: =IF(C4=0,0,F4/C4) -> 0.34013605 | I4: =ROUND(E4*0.3*Premissas!E8,0) -> 870 | J4: =D4+I4 -> 57520 | K4: =IF(Premissas!$C$16=0,0,D4/Premissas!$C$16) -> 2178.8462
A5: 7 | B5: 930 | C5: =COUNTIFS(Consolidado_HC!$A:$A,A5,Consolidado_HC!$D:$D,B5) -> 177 | D5: =SUMIFS(Consolidado_HC!$L:$L,Consolidado_HC!$A:$A,A5,Consolidado_HC!$D:$D,B5) -> 58400 | E5: =COUNTIFS(Consolidado_HC!$A:$A,A5,Consolidado_HC!$D:$D,B5,Consolidado_HC!$L:$L,0) -> 67 | F5: =COUNTIFS(Consolidado_HC!$A:$A,A5,Consolidado_HC!$D:$D,B5,Consolidado_HC!$N:$N,"SIM") -> 53 | G5: =IF(C5=0,0,E5/C5) -> 0.37853107 | H5: =IF(C5=0,0,F5/C5) -> 0.29943503 | I5: =ROUND(E5*0.3*Premissas!E8,0) -> 2010 | J5: =D5+I5 -> 60410 | K5: =IF(Premissas!$C$16=0,0,D5/Premissas!$C$16) -> 2246.1538
A6: 7 | B6: 1942 | C6: =COUNTIFS(Consolidado_HC!$A:$A,A6,Consolidado_HC!$D:$D,B6) -> 74 | D6: =SUMIFS(Consolidado_HC!$L:$L,Consolidado_HC!$A:$A,A6,Consolidado_HC!$D:$D,B6) -> 25750 | E6: =COUNTIFS(Consolidado_HC!$A:$A,A6,Consolidado_HC!$D:$D,B6,Consolidado_HC!$L:$L,0) -> 19 | F6: =COUNTIFS(Consolidado_HC!$A:$A,A6,Consolidado_HC!$D:$D,B6,Consolidado_HC!$N:$N,"SIM") -> 24 | G6: =IF(C6=0,0,E6/C6) -> 0.25675676 | H6: =IF(C6=0,0,F6/C6) -> 0.32432432 | I6: =ROUND(E6*0.3*Premissas!E8,0) -> 570 | J6: =D6+I6 -> 26320 | K6: =IF(Premissas!$C$16=0,0,D6/Premissas!$C$16) -> 990.38462
A7: 7 | B7: 1953 | C7: =COUNTIFS(Consolidado_HC!$A:$A,A7,Consolidado_HC!$D:$D,B7) -> 51 | D7: =SUMIFS(Consolidado_HC!$L:$L,Consolidado_HC!$A:$A,A7,Consolidado_HC!$D:$D,B7) -> 30100 | E7: =COUNTIFS(Consolidado_HC!$A:$A,A7,Consolidado_HC!$D:$D,B7,Consolidado_HC!$L:$L,0) -> 5 | F7: =COUNTIFS(Consolidado_HC!$A:$A,A7,Consolidado_HC!$D:$D,B7,Consolidado_HC!$N:$N,"SIM") -> 34 | G7: =IF(C7=0,0,E7/C7) -> 0.098039216 | H7: =IF(C7=0,0,F7/C7) -> 0.66666667 | I7: =ROUND(E7*0.3*Premissas!E8,0) -> 150 | J7: =D7+I7 -> 30250 | K7: =IF(Premissas!$C$16=0,0,D7/Premissas!$C$16) -> 1157.6923
A8: 7 | B8: 1974 | C8: =COUNTIFS(Consolidado_HC!$A:$A,A8,Consolidado_HC!$D:$D,B8) -> 30 | D8: =SUMIFS(Consolidado_HC!$L:$L,Consolidado_HC!$A:$A,A8,Consolidado_HC!$D:$D,B8) -> 19050 | E8: =COUNTIFS(Consolidado_HC!$A:$A,A8,Consolidado_HC!$D:$D,B8,Consolidado_HC!$L:$L,0) -> 1 | F8: =COUNTIFS(Consolidado_HC!$A:$A,A8,Consolidado_HC!$D:$D,B8,Consolidado_HC!$N:$N,"SIM") -> 21 | G8: =IF(C8=0,0,E8/C8) -> 0.033333333 | H8: =IF(C8=0,0,F8/C8) -> 0.7 | I8: =ROUND(E8*0.3*Premissas!E8,0) -> 30 | J8: =D8+I8 -> 19080 | K8: =IF(Premissas!$C$16=0,0,D8/Premissas!$C$16) -> 732.69231
A9: 7 | B9: 1979 | C9: =COUNTIFS(Consolidado_HC!$A:$A,A9,Consolidado_HC!$D:$D,B9) -> 17 | D9: =SUMIFS(Consolidado_HC!$L:$L,Consolidado_HC!$A:$A,A9,Consolidado_HC!$D:$D,B9) -> 3900 | E9: =COUNTIFS(Consolidado_HC!$A:$A,A9,Consolidado_HC!$D:$D,B9,Consolidado_HC!$L:$L,0) -> 7 | F9: =COUNTIFS(Consolidado_HC!$A:$A,A9,Consolidado_HC!$D:$D,B9,Consolidado_HC!$N:$N,"SIM") -> 3 | G9: =IF(C9=0,0,E9/C9) -> 0.41176471 | H9: =IF(C9=0,0,F9/C9) -> 0.17647059 | I9: =ROUND(E9*0.3*Premissas!E8,0) -> 210 | J9: =D9+I9 -> 4110 | K9: =IF(Premissas!$C$16=0,0,D9/Premissas!$C$16) -> 150
A10: 7 | B10: 7801 | C10: =COUNTIFS(Consolidado_HC!$A:$A,A10,Consolidado_HC!$D:$D,B10) -> 292 | D10: =SUMIFS(Consolidado_HC!$L:$L,Consolidado_HC!$A:$A,A10,Consolidado_HC!$D:$D,B10) -> 20150 | E10: =COUNTIFS(Consolidado_HC!$A:$A,A10,Consolidado_HC!$D:$D,B10,Consolidado_HC!$L:$L,0) -> 217 | F10: =COUNTIFS(Consolidado_HC!$A:$A,A10,Consolidado_HC!$D:$D,B10,Consolidado_HC!$N:$N,"SIM") -> 7 | G10: =IF(C10=0,0,E10/C10) -> 0.74315068 | H10: =IF(C10=0,0,F10/C10) -> 0.023972603 | I10: =ROUND(E10*0.3*Premissas!E8,0) -> 6510 | J10: =D10+I10 -> 26660 | K10: =IF(Premissas!$C$16=0,0,D10/Premissas!$C$16) -> 775
A11: 8 | B11: 409 | C11: =COUNTIFS(Consolidado_HC!$A:$A,A11,Consolidado_HC!$D:$D,B11) -> 148 | D11: =SUMIFS(Consolidado_HC!$L:$L,Consolidado_HC!$A:$A,A11,Consolidado_HC!$D:$D,B11) -> 48450 | E11: =COUNTIFS(Consolidado_HC!$A:$A,A11,Consolidado_HC!$D:$D,B11,Consolidado_HC!$L:$L,0) -> 43 | F11: =COUNTIFS(Consolidado_HC!$A:$A,A11,Consolidado_HC!$D:$D,B11,Consolidado_HC!$N:$N,"SIM") -> 38 | G11: =IF(C11=0,0,E11/C11) -> 0.29054054 | H11: =IF(C11=0,0,F11/C11) -> 0.25675676 | I11: =ROUND(E11*0.3*Premissas!E8,0) -> 1290 | J11: =D11+I11 -> 49740 | K11: =IF(Premissas!$C$16=0,0,D11/Premissas!$C$16) -> 1863.4615
A12: 8 | B12: 930 | C12: =COUNTIFS(Consolidado_HC!$A:$A,A12,Consolidado_HC!$D:$D,B12) -> 170 | D12: =SUMIFS(Consolidado_HC!$L:$L,Consolidado_HC!$A:$A,A12,Consolidado_HC!$D:$D,B12) -> 51950 | E12: =COUNTIFS(Consolidado_HC!$A:$A,A12,Consolidado_HC!$D:$D,B12,Consolidado_HC!$L:$L,0) -> 68 | F12: =COUNTIFS(Consolidado_HC!$A:$A,A12,Consolidado_HC!$D:$D,B12,Consolidado_HC!$N:$N,"SIM") -> 50 | G12: =IF(C12=0,0,E12/C12) -> 0.4 | H12: =IF(C12=0,0,F12/C12) -> 0.29411765 | I12: =ROUND(E12*0.3*Premissas!E8,0) -> 2040 | J12: =D12+I12 -> 53990 | K12: =IF(Premissas!$C$16=0,0,D12/Premissas!$C$16) -> 1998.0769
A13: 8 | B13: 1942 | C13: =COUNTIFS(Consolidado_HC!$A:$A,A13,Consolidado_HC!$D:$D,B13) -> 78 | D13: =SUMIFS(Consolidado_HC!$L:$L,Consolidado_HC!$A:$A,A13,Consolidado_HC!$D:$D,B13) -> 22200 | E13: =COUNTIFS(Consolidado_HC!$A:$A,A13,Consolidado_HC!$D:$D,B13,Consolidado_HC!$L:$L,0) -> 24 | F13: =COUNTIFS(Consolidado_HC!$A:$A,A13,Consolidado_HC!$D:$D,B13,Consolidado_HC!$N:$N,"SIM") -> 19 | G13: =IF(C13=0,0,E13/C13) -> 0.30769231 | H13: =IF(C13=0,0,F13/C13) -> 0.24358974 | I13: =ROUND(E13*0.3*Premissas!E8,0) -> 720 | J13: =D13+I13 -> 22920 | K13: =IF(Premissas!$C$16=0,0,D13/Premissas!$C$16) -> 853.84615
A14: 8 | B14: 1953 | C14: =COUNTIFS(Consolidado_HC!$A:$A,A14,Consolidado_HC!$D:$D,B14) -> 50 | D14: =SUMIFS(Consolidado_HC!$L:$L,Consolidado_HC!$A:$A,A14,Consolidado_HC!$D:$D,B14) -> 26200 | E14: =COUNTIFS(Consolidado_HC!$A:$A,A14,Consolidado_HC!$D:$D,B14,Consolidado_HC!$L:$L,0) -> 10 | F14: =COUNTIFS(Consolidado_HC!$A:$A,A14,Consolidado_HC!$D:$D,B14,Consolidado_HC!$N:$N,"SIM") -> 30 | G14: =IF(C14=0,0,E14/C14) -> 0.2 | H14: =IF(C14=0,0,F14/C14) -> 0.6 | I14: =ROUND(E14*0.3*Premissas!E8,0) -> 300 | J14: =D14+I14 -> 26500 | K14: =IF(Premissas!$C$16=0,0,D14/Premissas!$C$16) -> 1007.6923
A15: 8 | B15: 1974 | C15: =COUNTIFS(Consolidado_HC!$A:$A,A15,Consolidado_HC!$D:$D,B15) -> 26 | D15: =SUMIFS(Consolidado_HC!$L:$L,Consolidado_HC!$A:$A,A15,Consolidado_HC!$D:$D,B15) -> 14500 | E15: =COUNTIFS(Consolidado_HC!$A:$A,A15,Consolidado_HC!$D:$D,B15,Consolidado_HC!$L:$L,0) -> 2 | F15: =COUNTIFS(Consolidado_HC!$A:$A,A15,Consolidado_HC!$D:$D,B15,Consolidado_HC!$N:$N,"SIM") -> 16 | G15: =IF(C15=0,0,E15/C15) -> 0.076923077 | H15: =IF(C15=0,0,F15/C15) -> 0.61538462 | I15: =ROUND(E15*0.3*Premissas!E8,0) -> 60 | J15: =D15+I15 -> 14560 | K15: =IF(Premissas!$C$16=0,0,D15/Premissas!$C$16) -> 557.69231
A16: 8 | B16: 1979 | C16: =COUNTIFS(Consolidado_HC!$A:$A,A16,Consolidado_HC!$D:$D,B16) -> 19 | D16: =SUMIFS(Consolidado_HC!$L:$L,Consolidado_HC!$A:$A,A16,Consolidado_HC!$D:$D,B16) -> 4550 | E16: =COUNTIFS(Consolidado_HC!$A:$A,A16,Consolidado_HC!$D:$D,B16,Consolidado_HC!$L:$L,0) -> 7 | F16: =COUNTIFS(Consolidado_HC!$A:$A,A16,Consolidado_HC!$D:$D,B16,Consolidado_HC!$N:$N,"SIM") -> 3 | G16: =IF(C16=0,0,E16/C16) -> 0.36842105 | H16: =IF(C16=0,0,F16/C16) -> 0.15789474 | I16: =ROUND(E16*0.3*Premissas!E8,0) -> 210 | J16: =D16+I16 -> 4760 | K16: =IF(Premissas!$C$16=0,0,D16/Premissas!$C$16) -> 175
A17: 8 | B17: 7801 | C17: =COUNTIFS(Consolidado_HC!$A:$A,A17,Consolidado_HC!$D:$D,B17) -> 45 | D17: =SUMIFS(Consolidado_HC!$L:$L,Consolidado_HC!$A:$A,A17,Consolidado_HC!$D:$D,B17) -> 4200 | E17: =COUNTIFS(Consolidado_HC!$A:$A,A17,Consolidado_HC!$D:$D,B17,Consolidado_HC!$L:$L,0) -> 33 | F17: =COUNTIFS(Consolidado_HC!$A:$A,A17,Consolidado_HC!$D:$D,B17,Consolidado_HC!$N:$N,"SIM") -> 1 | G17: =IF(C17=0,0,E17/C17) -> 0.73333333 | H17: =IF(C17=0,0,F17/C17) -> 0.022222222 | I17: =ROUND(E17*0.3*Premissas!E8,0) -> 990 | J17: =D17+I17 -> 5190 | K17: =IF(Premissas!$C$16=0,0,D17/Premissas!$C$16) -> 161.53846
A18: TOTAL | C18: =SUM(C4:C17) -> 1324 | D18: =SUM(D4:D17) -> 386050 | E18: =SUM(E4:E17) -> 532 | F18: =SUM(F4:F17) -> 349 | I18: =SUM(I4:I17) -> 15960 | J18: =SUM(J4:J17) -> 402010 | K18: =IF(Premissas!$C$16=0,0,D18/Premissas!$C$16) -> 14848.077

Sheet Comparativo_Jul_Ago
A1: COMPARATIVO JULHO × AGOSTO — POR CD
A3: CD | B3: HCs_JUL | C3: HCs_AGO | D3: Δ_HCs | E3: CUSTO_JUL | F3: CUSTO_AGO | G3: Δ_CUSTO | H3: %_ABAIXO_JUL | I3: %_ABAIXO_AGO | J3: Δ_pp_ABAIXO | K3: FATOR_MED_JUL | L3: FATOR_MED_AGO
A4: 1942 | B4: 74 | C4: 78 | D4: 4 | E4: 25250 | F4: 22200 | G4: -3050 | H4: 0.25675676 | I4: 0.30769231 | J4: 0.050935551 | K4: 1.87 | L4: 1.88
A5: 1953 | B5: 51 | C5: 50 | D5: -1 | E5: 29600 | F5: 26200 | G5: -3400 | H5: 0.098039216 | I5: 0.2 | J5: 0.10196078 | K5: 2.8 | L5: 3.36
A6: 1965 | B6: 0 | C6: 269 | D6: 269 | E6: 0 | F6: 31950 | G6: 31950 | H6: 0 | I6: 0.65427509 | J6: 0.65427509 | K6: 0 | L6: 1.01
A7: 1974 | B7: 30 | C7: 26 | D7: -4 | E7: 19050 | F7: 14250 | G7: -4800 | H7: 0.033333333 | I7: 0.076923077 | J7: 0.043589744 | K7: 2.73 | L7: 2.58
A8: 1979 | B8: 17 | C8: 19 | D8: 2 | E8: 3900 | F8: 4550 | G8: 650 | H8: 0.41176471 | I8: 0.36842105 | J8: -0.043343653 | K8: 2.52 | L8: 1.61
A9: 409 | B9: 147 | C9: 148 | D9: 1 | E9: 56400 | F9: 47450 | G9: -8950 | H9: 0.19727891 | I9: 0.29054054 | J9: 0.093261629 | K9: 1.94 | L9: 1.89
A10: 7801 | B10: 292 | C10: 45 | D10: -247 | E10: 20150 | F10: 4200 | G10: -15950 | H10: 0.74315068 | I10: 0.73333333 | J10: -0.0098173516 | K10: 0.81 | L10: 0.94
A11: 930 | B11: 177 | C11: 170 | D11: -7 | E11: 57650 | F11: 51700 | G11: -5950 | H11: 0.37853107 | I11: 0.4 | J11: 0.021468927 | K11: 1.86 | L11: 1.58
A12: TOTAL | B12: 788 | C12: 805 | D12: 17 | E12: 212000 | F12: 202500 | G12: -9500 | H12: 0.43781726 | I12: 0.45093168 | J12: 0.013114418 | K12: 1.59 | L12: 1.59
A14: Leitura: Δ_pp_ABAIXO negativo = melhora (menos gente abaixo da meta). Δ_CUSTO = variação do incentivo.

Sheet Projecao_Produtividade(const)
A1: PROJEÇÃO DE PRODUTIVIDADE E RETORNO DO INCENTIVO
A3: Simulação de redução
A4: % dos HCs abaixo da meta que sobem p/ 1ª faixa (1,00–1,19) | B4: 0.3
A5: Ganho médio de produtividade desses HCs (ex.: +15%) | B5: 0.15
A6: Custo médio mensal de 1 HC (salário+encargos) R$ | B6: 4940
A7: Elasticidade corte Separação: 1 pp a mais no ressuprimento → redução de X% no corte | B7: 0.05
A8: Custo médio mensal estimado de ruptura/corte (Separação) R$ | B8: 50000

Sheet Base_Nova
A1: CD | B1: Data | C1: ID | D1: Nome | E1: Quantidade | F1: Funções | G1: Cód. QTD Funções | H1: QTD Funções
A2: 930 | B2: 46280 | C2: T620222 | D2: JOSE RENIEL SILVA FARIAS | E2: 34 | F2: Carregamento | G2: 1 | H2: 1
A3: 930 | B3: 46280 | C3: T720420 | D3: Fabio DOS SANTOS SILVA | E3: 53 | F3: Empilhadeira | G3: 2 | H3: 1
A4: 930 | B4: 46280 | C4: 122853 | D4: ROSE KATIA DE OLIVEIRA | E4: 38 | F4: Recebimento | G4: 4 | H4: 1
A5: 930 | B5: 46280 | C5: 161429 | D5: JOAO GOMES DE ALMEIDA | E5: 8 | F5: Empilhadeira+Puxada | G5: 23 | H5: 2
A6: 930 | B6: 46280 | C6: 176631 | D6: LUCAS ANDRADE CAFE | E6: 13 | F6: Recebimento | G6: 4 | H6: 1
A7: 930 | B7: 46280 | C7: 28887 | D7: MARILZA DE MATOS GOMES | E7: 37 | F7: Recebimento | G7: 4 | H7: 1
A8: 930 | B8: 46280 | C8: 372952 | D8: MARCOS ROBERTO DE SOUZA | E8: 56 | F8: Empilhadeira+Puxada | G8: 23 | H8: 2
A9: 930 | B9: 46280 | C9: 383180 | D9: SEVERINO ANTONIO | E9: 56 | F9: Empilhadeira+Puxada | G9: 23 | H9: 2
A10: 930 | B10: 46280 | C10: 422175 | D10: MIKE HENRIQUE VINICIUS | E10: 8 | F10: Carregamento | G10: 1 | H10: 1
A11: 930 | B11: 46280 | C11: 435411 | D11: JOSE EVANGELISTA DA SILVA | E11: 79 | F11: Empilhadeira+Puxada | G11: 23 | H11: 2
A12: 930 | B12: 46280 | C12: 4394453 | D12: GEOVANE AQUINO DE LIMA | E12: 10 | F12: Carregamento | G12: 1 | H12: 1
A13: 930 | B13: 46280 | C13: 4531485 | D13: GUILHERME DE OLIVEIRA SILVA | E13: 35 | F13: Carregamento | G13: 1 | H13: 1
... A10302: 1953 | B10302: 46220 | C10302: 700842 | D10302: VITOR BERTO DIAS DA SILVA | E10302: 20 | F10302: Empilhadeira+Recebimento | G10302: 24 | H10302: 2
A10303: 1965 | B10303: 46280 | C10303: T40001283 | D10303: LUCAS PEREIRA ARAUJO | E10303: 21 | F10303: Carregamento | G10303: 1 | H10303: 1
A10304: 1965 | B10304: 46280 | C10304: T40002162 | D10304: GUSTAVO MENDES DOS ANJOS | E10304: 26 | F10304: Carregamento | G10304: 1 | H10304: 1
A10305: 1965 | B10305: 46280 | C10305: T40002384 | D10305: TIAGO RODRIGUES PIRES | E10305: 16 | F10305: Empilhadeira | G10305: 2 | H10305: 1
A10306: 1965 | B10306: 46280 | C10306: 10181 | D10306: Raimundo Alves | E10306: 53 | F10306: Empilhadeira | G10306: 2 | H10306: 1
A10307: 1965 | B10307: 46280 | C10307: 138654 | D10307: Pedro Pereira Da Silva Neto | E10307: 85 | F10307: Empilhadeira+Puxada | G10307: 23 | H10307: 2
A10308: 1965 | B10308: 46280 | C10308: 168375 | D10308: Luiz Dos Anjos Cruz | E10308: 21 | F10308: Empilhadeira | G10308: 2 | H10308: 1
A10309: 1965 | B10309: 46280 | C10309: 171600 | D10309: Wellington Inacio De Oliveira | E10309: 29 | F10309: Empilhadeira | G10309: 2 | H10309: 1
A10310: 1965 | B10310: 46280 | C10310: 207050 | D10310: Gildo Souza Da Silva | E10310: 43 | F10310: Recebimento | G10310: 4 | H10310: 1
A10311: 1965 | B10311: 46280 | C10311: 21719 | D10311: Deomilton Moreira Da Silva | E10311: 60 | F10311: Empilhadeira | G10311: 2 | H10311: 1
A10312: 1965 | B10312: 46280 | C10312: 266704 | D10312: Francisco Das Chagas Neto | E10312: 46 | F10312: Empilhadeira+Puxada | G10312: 23 | H10312: 2
A10313: 1965 | B10313: 46280 | C10313: 277107 | D10313: Natalino Vieira Machado | E10313: 27 | F10313: Empilhadeira+Puxada | G10313: 23 | H10313: 2
A10314: 1965 | B10314: 46280 | C10314: 2796422 | D10314: ROZANGELA DA SILVA MELO | E10314: 88 | F10314: Recebimento | G10314: 4 | H10314: 1
... A20706: 1965 | B20706: 46219 | C20706: 688778 | D20706: Jose Vagner Faustino | E20706: 10 | F20706: Carregamento | G20706: 1 | H20706: 1
A20707: 1974 | B20707: 46281 | C20707: 157110 | D20707: FRANCISCO JEAN MOURA | E20707: 8 | F20707: Empilhadeira | G20707: 2 | H20707: 1
A20708: 1974 | B20708: 46281 | C20708: 5425590 | D20708: Thiago Igor Soares Vieira | E20708: 6 | F20708: Empilhadeira | G20708: 2 | H20708: 1
A20709: 1974 | B20709: 46281 | C20709: 5443148 | D20709: Danilson Paulino De Sousa | E20709: 11 | F20709: Empilhadeira+Puxada | G20709: 23 | H20709: 2
A20710: 1974 | B20710: 46280 | C20710: 149952 | D20710: RONALD NUNES DOS SANTOS | E20710: 134 | F20710: Carregamento+Empilhadeira+Puxada+Recebimento | G20710: 1234 | H20710: 4
A20711: 1974 | B20711: 46280 | C20711: 157110 | D20711: FRANCISCO JEAN MOURA | E20711: 81 | F20711: Empilhadeira+Puxada | G20711: 23 | H20711: 2
A20712: 1974 | B20712: 46280 | C20712: 157789 | D20712: FRANCISCO DAS CHAGAS ALVES RODRIGUES | E20712: 89 | F20712: Empilhadeira+Puxada | G20712: 23 | H20712: 2
A20713: 1974 | B20713: 46280 | C20713: 286911 | D20713: ANTONIO CARLOS DOS SANTOS SOUZA | E20713: 20 | F20713: Empilhadeira+Puxada | G20713: 23 | H20713: 2
A20714: 1974 | B20714: 46280 | C20714: 299050 | D20714: ADRIANO PONTES GOMES | E20714: 12 | F20714: Empilhadeira+Puxada | G20714: 23 | H20714: 2
A20715: 1974 | B20715: 46280 | C20715: 316536 | D20715: JOSE HORMANDO SOARES DOS SANTOS | E20715: 132 | F20715: Empilhadeira+Puxada | G20715: 23 | H20715: 2
A20716: 1974 | B20716: 46280 | C20716: 5425590 | D20716: Thiago Igor Soares Vieira | E20716: 66 | F20716: Empilhadeira+Puxada | G20716: 23 | H20716: 2
A20717: 1974 | B20717: 46280 | C20717: 5426251 | D20717: Alisson Vitor Vieira Diniz | E20717: 125 | F20717: Carregamento+Empilhadeira+Puxada+Recebimento | G20717: 1234 | H20717: 4
A20718: 1974 | B20718: 46280 | C20718: 5440050 | D20718: Daniel Diogo Moraes | E20718: 103 | F20718: Carregamento | G20718: 1 | H20718: 1
... A22168: 1979 | B22168: 46221 | C22168: 569885 | D22168: Eduardo dos Santos Rocha | E22168: 107 | F22168: Carregamento+Puxada | G22168: 13 | H22168: 2

Sheet Chave_função_Metas
A1: CD | B1: Função | C1: Cód. Unidade de Medida | E1: CD | F1: Indicador | G1: Categoria | H1: Meta | I1: Média Geral | J1: Cód. Unidade de Medida
A2: 409 | B2: Carregamento | C2: 1 | E2: 409 | F2: ATIVIDADE OP. EMP. | G2: CARNES | H2: 26.991741 | I2: =AVERAGE(H2:H4) -> 25.96294 | J2: 2
A3: 409 | B3: Carregamento+Empilhadeira | C3: 12 | E3: 409 | F3: ATIVIDADE OP. EMP. | G3: F.L.V | H3: 26.171763 | J3: 2
A4: 409 | B4: Carregamento+Empilhadeira+Puxada | C4: 123 | E4: 409 | F4: ATIVIDADE OP. EMP. | G4: MERCEARIA | H4: 24.725317 | J4: 2
A5: 409 | B5: Carregamento+Empilhadeira+Puxada+Recebimento | C5: 1234 | E5: 409 | F5: CARREGAMENTO | G5: CARNES | H5: 15.819599 | I5: =AVERAGE(H5:H7) -> 21.764179 | J5: 1
A6: 409 | B6: Carregamento+Puxada | C6: 13 | E6: 409 | F6: CARREGAMENTO | G6: F.L.V | H6: 24.390974 | J6: 1
A7: 409 | B7: Carregamento+Recebimento | C7: 14 | E7: 409 | F7: CARREGAMENTO | G7: MERCEARIA | H7: 25.081963 | J7: 1
A8: 409 | B8: Empilhadeira | C8: 2 | E8: 409 | F8: PUXADA RECEB | G8: CARNES | H8: 20.014969 | I8: =AVERAGE(H8:H10) -> 21.914432 | J8: 34
A9: 409 | B9: Empilhadeira+Puxada | C9: 23 | E9: 409 | F9: PUXADA RECEB | G9: F.L.V | H9: 23.865604 | J9: 34
A10: 409 | B10: Empilhadeira+Puxada+Recebimento | C10: 234 | E10: 409 | F10: PUXADA RECEB | G10: MERCEARIA | H10: 21.862723 | J10: 34
A11: 409 | B11: Empilhadeira+Recebimento | C11: 24 | E11: 409 | F11: RECEBIMENTO | G11: CARNES | H11: 16.771957 | I11: =AVERAGE(H11:H13) -> 23.031803 | J11: 4
A12: 409 | B12: Puxada | C12: 3 | E12: 409 | F12: RECEBIMENTO | G12: F.L.V | H12: 20.718359 | J12: 4
A13: 409 | B13: Puxada+Recebimento | C13: 34 | E13: 409 | F13: RECEBIMENTO | G13: MERCEARIA | H13: 31.605093 | J13: 4
A14: 409 | B14: Recebimento | C14: 4

Sheet Metas__Supe
A1: Cod_Centrocusto | B1: Atividade _Primária | C1: Meta Produtividade
A2: 1942 | B2: ATIVIDADE OP. EMP. | C2: 20
A3: 1942 | B3: CARREGAMENTO | C3: 22
A4: 1942 | B4: SEPARACAO | C4: 80
A5: 1942 | B5: RECEBIMENTO | C5: 17
A6: 1953 | B6: PUXADA RECEB | C6: 15
A7: 1953 | B7: RECEBIMENTO | C7: 20
A8: 1953 | B8: ATIVIDADE OP. EMP. | C8: 19
A9: 1953 | B9: CARREGAMENTO | C9: 19
A10: 1953 | B10: SEPARACAO | C10: 111
A11: 1953 | B11: ATIVIDADE OP. EMP. | C11: 21
A12: 1953 | B12: PUXADA RECEB | C12: 25
A13: 1953 | B13: CARREGAMENTO | C13: 15
... A68: 1974 | B68: APOIO OPERAÇÃO | C68: 345

Sheet Resumo_Mes_Atividade
A1: SIMULAÇÃO POR MÊS E ATIVIDADE
A3: MES | B3: ATIVIDADE | C3: HCs | D3: REGS | E3: META_REF | F3: FATOR_MED | G3: %_ABAIXO | H3: CUSTO_REG_MENSAL | I3: CUSTO_DIARIO
A4: 7 | B4: ATIVIDADE OP. EMP. | C4: 203 | D4: 203 | E4: 20 | F4: 1.19 | G4: 0.50246305 | H4: 43550 | I4: =H4/Premissas!$C$16 -> 1675
A5: 7 | B5: CARREGAMENTO | C5: 294 | D5: 294 | E5: 22 | F5: 1.87 | G5: 0.44217687 | H5: 86950 | I5: =H5/Premissas!$C$16 -> 3344.2308
A6: 7 | B6: PUXADA RECEB | C6: 311 | D6: 311 | E6: 16 | F6: 1.16 | G6: 0.52733119 | H6: 60200 | I6: =H6/Premissas!$C$16 -> 2315.3846
A7: 7 | B7: RECEBIMENTO | C7: 176 | D7: 176 | E7: 17 | F7: 1.69 | G7: 0.375 | H7: 53000 | I7: =H7/Premissas!$C$16 -> 2038.4615
A8: 8 | B8: ATIVIDADE OP. EMP. | C8: 214 | D8: 293 | E8: 20 | F8: 0.99 | G8: 0.64846416 | H8: 40650 | I8: =H8/Premissas!$C$16 -> 1563.4615
A9: 8 | B9: CARREGAMENTO | C9: 295 | D9: 380 | E9: 22 | F9: 1.46 | G9: 0.52631579 | H9: 83900 | I9: =H9/Premissas!$C$16 -> 3226.9231
A10: 8 | B10: PUXADA RECEB | C10: 305 | D10: 400 | E10: 16 | F10: 1.18 | G10: 0.5075 | H10: 67950 | I10: =H10/Premissas!$C$16 -> 2613.4615
A11: 8 | B11: RECEBIMENTO | C11: 194 | D11: 243 | E11: 17 | F11: 1.85 | G11: 0.3909465 | H11: 74100 | I11: =H11/Premissas!$C$16 -> 2850

Sheet Resumo_Mes_CD_Atividade
A1: MÊS × CD × ATIVIDADE
A3: MES | B3: CD | C3: ATIVIDADE | D3: HCs | E3: REGS | F3: META | G3: FATOR_MED | H3: QTD | I3: CUSTO_MENSAL | J3: CUSTO_DIARIO
A4: 7 | B4: 1942 | C4: ATIVIDADE OP. EMP. | D4: 24 | E4: 24 | F4: 20 | G4: 1.28 | H4: 37765 | I4: 5600 | J4: =I4/Premissas!$C$16 -> 215.38462
A5: 7 | B5: 1942 | C5: CARREGAMENTO | D5: 33 | E5: 33 | F5: 22 | G5: 2.4 | H5: 26547 | I5: 15050 | J5: =I5/Premissas!$C$16 -> 578.84615
A6: 7 | B6: 1942 | C6: PUXADA RECEB | D6: 20 | E6: 20 | F6: 16 | G6: 1.47 | H6: 10605 | I6: 4400 | J6: =I6/Premissas!$C$16 -> 169.23077
A7: 7 | B7: 1942 | C7: RECEBIMENTO | D7: 10 | E7: 10 | F7: 17 | G7: 1.06 | H7: 15412 | I7: 2250 | J7: =I7/Premissas!$C$16 -> 86.538462
A8: 7 | B8: 1953 | C8: ATIVIDADE OP. EMP. | D8: 16 | E8: 16 | F8: 19 | G8: 2.26 | H8: 25487 | I8: 9850 | J8: =I8/Premissas!$C$16 -> 378.84615
A9: 7 | B9: 1953 | C9: CARREGAMENTO | D9: 15 | E9: 15 | F9: 18 | G9: 3.63 | H9: 9665 | I9: 8800 | J9: =I9/Premissas!$C$16 -> 338.46154
A10: 7 | B10: 1953 | C10: PUXADA RECEB | D10: 26 | E10: 26 | F10: 15 | G10: 1.66 | H10: 15689 | I10: 8050 | J10: =I10/Premissas!$C$16 -> 309.61538
A11: 7 | B11: 1953 | C11: RECEBIMENTO | D11: 20 | E11: 20 | F11: 19 | G11: 2.19 | H11: 18416 | I11: 9900 | J11: =I11/Premissas!$C$16 -> 380.76923
A12: 7 | B12: 1974 | C12: ATIVIDADE OP. EMP. | D12: 8 | E12: 8 | F12: 9 | G12: 3.38 | H12: 11457 | I12: 6000 | J12: =I12/Premissas!$C$16 -> 230.76923
A13: 7 | B13: 1974 | C13: CARREGAMENTO | D13: 9 | E13: 9 | F13: 22 | G13: 2.78 | H13: 2801 | I13: 4450 | J13: =I13/Premissas!$C$16 -> 171.15385
A14: 7 | B14: 1974 | C14: PUXADA RECEB | D14: 21 | E14: 21 | F14: 16 | G14: 1.95 | H14: 4914 | I14: 10850 | J14: =I14/Premissas!$C$16 -> 417.30769
A15: 7 | B15: 1974 | C15: RECEBIMENTO | D15: 8 | E15: 8 | F15: 41 | G15: 1.96 | H15: 10542 | I15: 3650 | J15: =I15/Premissas!$C$16 -> 140.38462
... A63: 8 | B63: 930 | C63: RECEBIMENTO | D63: 37 | E63: 37 | F63: 17 | G63: 1.83 | H63: 54126 | I63: 12850 | J63: =I63/Premissas!$C$16 -> 494.23077

Sheet Distribuicao_Mes_Faixa
A1: DISTRIBUIÇÃO POR MÊS E FAIXA (MENSAL + DIÁRIO)
A3: MES | B3: FAIXA | C3: VALOR_MENSAL | D3: VALOR_DIARIO | E3: QTD_HCs | F3: %_HCs | G3: CUSTO_MENSAL | H3: CUSTO_DIARIO
A4: 7 | B4: < 1,00 | C4: =Premissas!E7 -> 0 | D4: =Premissas!F7 -> 0 | E4: =COUNTIFS(Consolidado_HC!A:A,A4,Consolidado_HC!L:L,0) -> 345 | F4: =IFERROR(E4/SUMIFS(E:E,A:A,A4),0) -> 0.43781726 | G4: =E4*C4 -> 0 | H4: =E4*D4 -> 0
A5: 7 | B5: 1,00 – 1,19 | C5: =Premissas!E8 -> 100 | D5: =Premissas!F8 -> 3.8461538 | E5: =COUNTIFS(Consolidado_HC!A:A,A5,Consolidado_HC!L:L,100) -> 81 | F5: =IFERROR(E5/SUMIFS(E:E,A:A,A5),0) -> 0.10279188 | G5: =E5*C5 -> 8100 | H5: =E5*D5 -> 311.53846
A6: 7 | B6: 1,20 – 1,39 | C6: =Premissas!E9 -> 200 | D6: =Premissas!F9 -> 7.6923077 | E6: =COUNTIFS(Consolidado_HC!A:A,A6,Consolidado_HC!L:L,200) -> 52 | F6: =IFERROR(E6/SUMIFS(E:E,A:A,A6),0) -> 0.065989848 | G6: =E6*C6 -> 10400 | H6: =E6*D6 -> 400
A7: 7 | B7: 1,40 – 1,59 | C7: =Premissas!E10 -> 350 | D7: =Premissas!F10 -> 13.461538 | E7: =COUNTIFS(Consolidado_HC!A:A,A7,Consolidado_HC!L:L,350) -> 50 | F7: =IFERROR(E7/SUMIFS(E:E,A:A,A7),0) -> 0.063451777 | G7: =E7*C7 -> 17500 | H7: =E7*D7 -> 673.07692
A8: 7 | B8: 1,60 – 1,99 | C8: =Premissas!E11 -> 500 | D8: =Premissas!F11 -> 19.230769 | E8: =COUNTIFS(Consolidado_HC!A:A,A8,Consolidado_HC!L:L,500) -> 68 | F8: =IFERROR(E8/SUMIFS(E:E,A:A,A8),0) -> 0.086294416 | G8: =E8*C8 -> 34000 | H8: =E8*D8 -> 1307.6923
A9: 7 | B9: ≥ 2,00 | C9: =Premissas!E12 -> 750 | D9: =Premissas!F12 -> 28.846154 | E9: =COUNTIFS(Consolidado_HC!A:A,A9,Consolidado_HC!L:L,750) -> 192 | F9: =IFERROR(E9/SUMIFS(E:E,A:A,A9),0) -> 0.24365482 | G9: =E9*C9 -> 144000 | H9: =E9*D9 -> 5538.4615
A10: 8 | B10: < 1,00 | C10: =Premissas!E7 -> 0 | D10: =Premissas!F7 -> 0 | E10: =COUNTIFS(Consolidado_HC!A:A,A10,Consolidado_HC!L:L,0) -> 363 | F10: =IFERROR(E10/SUMIFS(E:E,A:A,A10),0) -> 0.45093168 | G10: =E10*C10 -> 0 | H10: =E10*D10 -> 0
A11: 8 | B11: 1,00 – 1,19 | C11: =Premissas!E8 -> 100 | D11: =Premissas!F8 -> 3.8461538 | E11: =COUNTIFS(Consolidado_HC!A:A,A11,Consolidado_HC!L:L,100) -> 78 | F11: =IFERROR(E11/SUMIFS(E:E,A:A,A11),0) -> 0.09689441 | G11: =E11*C11 -> 7800 | H11: =E11*D11 -> 300
A12: 8 | B12: 1,20 – 1,39 | C12: =Premissas!E9 -> 200 | D12: =Premissas!F9 -> 7.6923077 | E12: =COUNTIFS(Consolidado_HC!A:A,A12,Consolidado_HC!L:L,200) -> 69 | F12: =IFERROR(E12/SUMIFS(E:E,A:A,A12),0) -> 0.085714286 | G12: =E12*C12 -> 13800 | H12: =E12*D12 -> 530.76923
A13: 8 | B13: 1,40 – 1,59 | C13: =Premissas!E10 -> 350 | D13: =Premissas!F10 -> 13.461538 | E13: =COUNTIFS(Consolidado_HC!A:A,A13,Consolidado_HC!L:L,350) -> 64 | F13: =IFERROR(E13/SUMIFS(E:E,A:A,A13),0) -> 0.079503106 | G13: =E13*C13 -> 22400 | H13: =E13*D13 -> 861.53846
A14: 8 | B14: 1,60 – 1,99 | C14: =Premissas!E11 -> 500 | D14: =Premissas!F11 -> 19.230769 | E14: =COUNTIFS(Consolidado_HC!A:A,A14,Consolidado_HC!L:L,500) -> 51 | F14: =IFERROR(E14/SUMIFS(E:E,A:A,A14),0) -> 0.063354037 | G14: =E14*C14 -> 25500 | H14: =E14*D14 -> 980.76923
A15: 8 | B15: ≥ 2,00 | C15: =Premissas!E12 -> 750 | D15: =Premissas!F12 -> 28.846154 | E15: =COUNTIFS(Consolidado_HC!A:A,A15,Consolidado_HC!L:L,750) -> 180 | F15: =IFERROR(E15/SUMIFS(E:E,A:A,A15),0) -> 0.22360248 | G15: =E15*C15 -> 135000 | H15: =E15*D15 -> 5192.3077

Sheet Base
A1: MES | B1: CD | C1: ATIVIDADE | D1: USUÁRIO | E1: COLABORADOR | F1: QUANTIDADE | G1: HORAS | H1: PRODUTIVIDADE | I1: META | J1: EMPRESA | K1: EMPRESA_AJUSTADA
A2: 7 | B2: 409 | C2: ATIVIDADE OP. EMP. | D2: 182403 | E2: Reginaldo Alves Araujo | F2: 2377 | G2: 66.81 | H2: 36 | I2: 25 | J2: GPA | K2: =IF(J2<>"",IF(OR(UPPER(J2)="TERCEIRO",UPPER(J2)="TERCEIRA"),"TERCEIRA",IF(UPPER(J2)="GPA","GPA",J2)),IF(LEFT(D2,1)="T","TERCEIRA","GPA")) -> GPA
A3: 7 | B3: 409 | C3: RECEBIMENTO | D3: 250187 | E3: Marcio Da Silva Rodrigues | F3: 1518 | G3: 30.47 | H3: 50 | I3: 25 | J3: GPA | K3: =IF(J3<>"",IF(OR(UPPER(J3)="TERCEIRO",UPPER(J3)="TERCEIRA"),"TERCEIRA",IF(UPPER(J3)="GPA","GPA",J3)),IF(LEFT(D3,1)="T","TERCEIRA","GPA")) -> GPA
A4: 7 | B4: 409 | C4: CARREGAMENTO | D4: 250896 | E4: Hugo Clementino Nunes | F4: 272 | G4: 4.08 | H4: 67 | I4: 24 | J4: GPA | K4: =IF(J4<>"",IF(OR(UPPER(J4)="TERCEIRO",UPPER(J4)="TERCEIRA"),"TERCEIRA",IF(UPPER(J4)="GPA","GPA",J4)),IF(LEFT(D4,1)="T","TERCEIRA","GPA")) -> GPA
A5: 7 | B5: 409 | C5: PUXADA RECEB | D5: 250896 | E5: Hugo Clementino Nunes | F5: 318 | G5: 9.38 | H5: 34 | I5: 22 | J5: GPA | K5: =IF(J5<>"",IF(OR(UPPER(J5)="TERCEIRO",UPPER(J5)="TERCEIRA"),"TERCEIRA",IF(UPPER(J5)="GPA","GPA",J5)),IF(LEFT(D5,1)="T","TERCEIRA","GPA")) -> GPA
A6: 7 | B6: 409 | C6: RECEBIMENTO | D6: 250896 | E6: Hugo Clementino Nunes | F6: 187 | G6: 7.68 | H6: 24 | I6: 25 | J6: GPA | K6: =IF(J6<>"",IF(OR(UPPER(J6)="TERCEIRO",UPPER(J6)="TERCEIRA"),"TERCEIRA",IF(UPPER(J6)="GPA","GPA",J6)),IF(LEFT(D6,1)="T","TERCEIRA","GPA")) -> GPA
A7: 7 | B7: 409 | C7: SEPARACAO | D7: 250896 | E7: Hugo Clementino Nunes | F7: 499 | G7: 6.21 | H7: 80 | I7: 105 | J7: GPA | K7: =IF(J7<>"",IF(OR(UPPER(J7)="TERCEIRO",UPPER(J7)="TERCEIRA"),"TERCEIRA",IF(UPPER(J7)="GPA","GPA",J7)),IF(LEFT(D7,1)="T","TERCEIRA","GPA")) -> GPA
A8: 7 | B8: 409 | C8: PUXADA RECEB | D8: 251239 | E8: Mauricio Rodrigues | F8: 124 | G8: 7.08 | H8: 18 | I8: 22 | J8: GPA | K8: =IF(J8<>"",IF(OR(UPPER(J8)="TERCEIRO",UPPER(J8)="TERCEIRA"),"TERCEIRA",IF(UPPER(J8)="GPA","GPA",J8)),IF(LEFT(D8,1)="T","TERCEIRA","GPA")) -> GPA
A9: 7 | B9: 409 | C9: PUXADA RECEB | D9: 251240 | E9: Gildo Antonio Barbosa | F9: 38 | G9: 1.3 | H9: 29 | I9: 22 | J9: GPA | K9: =IF(J9<>"",IF(OR(UPPER(J9)="TERCEIRO",UPPER(J9)="TERCEIRA"),"TERCEIRA",IF(UPPER(J9)="GPA","GPA",J9)),IF(LEFT(D9,1)="T","TERCEIRA","GPA")) -> GPA
A10: 7 | B10: 409 | C10: RECEBIMENTO | D10: 251240 | E10: Gildo Antonio Barbosa | F10: 3278 | G10: 39.72 | H10: 83 | I10: 25 | J10: GPA | K10: =IF(J10<>"",IF(OR(UPPER(J10)="TERCEIRO",UPPER(J10)="TERCEIRA"),"TERCEIRA",IF(UPPER(J10)="GPA","GPA",J10)),IF(LEFT(D10,1)="T","TERCEIRA","GPA")) -> GPA
A11: 7 | B11: 409 | C11: CARREGAMENTO | D11: 255199 | E11: Gilberton Santana De Moura | F11: 344 | G11: 7.68 | H11: 45 | I11: 24 | J11: GPA | K11: =IF(J11<>"",IF(OR(UPPER(J11)="TERCEIRO",UPPER(J11)="TERCEIRA"),"TERCEIRA",IF(UPPER(J11)="GPA","GPA",J11)),IF(LEFT(D11,1)="T","TERCEIRA","GPA")) -> GPA
A12: 7 | B12: 409 | C12: ATIVIDADE OP. EMP. | D12: 264318 | E12: Flavio Soares Da Silva | F12: 2828 | G12: 66.5 | H12: 43 | I12: 25 | J12: GPA | K12: =IF(J12<>"",IF(OR(UPPER(J12)="TERCEIRO",UPPER(J12)="TERCEIRA"),"TERCEIRA",IF(UPPER(J12)="GPA","GPA",J12)),IF(LEFT(D12,1)="T","TERCEIRA","GPA")) -> GPA
A13: 7 | B13: 409 | C13: SEPARACAO | D13: 264318 | E13: Flavio Soares Da Silva | F13: 714 | G13: 3.65 | H13: 196 | I13: 105 | J13: GPA | K13: =IF(J13<>"",IF(OR(UPPER(J13)="TERCEIRO",UPPER(J13)="TERCEIRA"),"TERCEIRA",IF(UPPER(J13)="GPA","GPA",J13)),IF(LEFT(D13,1)="T","TERCEIRA","GPA")) -> GPA
... A3816: 8 | B3816: 1965 | C3816: CARREGAMENTO | D3816: 2958732 | E3816: Gilvana Oliveira De Araujo | F3816: 192 | G3816: 9.96 | H3816: 19 | I3816: 0 | J3816: GPA | K3816: =IF(J3816<>"",IF(OR(UPPER(J3816)="TERCEIRO",UPPER(J3816)="TERCEIRA"),"TERCEIRA",IF(UPPER(J3816)="GPA","GPA",J3816)),IF(LEFT(D3816,1)="T","TERCEIRA","GPA")) -> GPA
A3817: 8 | B3817: 1965 | C3817: SEPARACAO | D3817: 2991799 | E3817: Gustavo De Mello Dos Santos | F3817: 297 | G3817: 8.07 | H3817: 37 | J3817: GPA | K3817: =IF(J3817<>"",IF(OR(UPPER(J3817)="TERCEIRO",UPPER(J3817)="TERCEIRA"),"TERCEIRA",IF(UPPER(J3817)="GPA","GPA",J3817)),IF(LEFT(D3817,1)="T","TERCEIRA","GPA")) -> GPA
A3818: 8 | B3818: 1965 | C3818: RECEBIMENTO | D3818: 30307 | E3818: MARIA VANDA DOS ANJOS CRUZ | F3818: 153 | G3818: 20.01 | H3818: 8 | I3818: 0 | J3818: GPA | K3818: =IF(J3818<>"",IF(OR(UPPER(J3818)="TERCEIRO",UPPER(J3818)="TERCEIRA"),"TERCEIRA",IF(UPPER(J3818)="GPA","GPA",J3818)),IF(LEFT(D3818,1)="T","TERCEIRA","GPA")) -> GPA
A3819: 8 | B3819: 1965 | C3819: ATIVIDADE OP. EMP. | D3819: 308129 | E3819: Silvio Rodrigues Da Macena | F3819: 57 | G3819: 9.52 | H3819: 6 | I3819: 0 | J3819: GPA | K3819: =IF(J3819<>"",IF(OR(UPPER(J3819)="TERCEIRO",UPPER(J3819)="TERCEIRA"),"TERCEIRA",IF(UPPER(J3819)="GPA","GPA",J3819)),IF(LEFT(D3819,1)="T","TERCEIRA","GPA")) -> GPA
A3820: 8 | B3820: 1965 | C3820: RECEBIMENTO | D3820: 308129 | E3820: Silvio Rodrigues Da Macena | F3820: 1 | G3820: 0.46 | H3820: 2 | I3820: 0 | J3820: GPA | K3820: =IF(J3820<>"",IF(OR(UPPER(J3820)="TERCEIRO",UPPER(J3820)="TERCEIRA"),"TERCEIRA",IF(UPPER(J3820)="GPA","GPA",J3820)),IF(LEFT(D3820,1)="T","TERCEIRA","GPA")) -> GPA
A3821: 8 | B3821: 1965 | C3821: ATIVIDADE OP. EMP. | D3821: 308965 | E3821: ANDRE FERREIRA APOLINARIO | F3821: 961 | G3821: 104.26 | H3821: 9 | I3821: 0 | J3821: GPA | K3821: =IF(J3821<>"",IF(OR(UPPER(J3821)="TERCEIRO",UPPER(J3821)="TERCEIRA"),"TERCEIRA",IF(UPPER(J3821)="GPA","GPA",J3821)),IF(LEFT(D3821,1)="T","TERCEIRA","GPA")) -> GPA
A3822: 8 | B3822: 1965 | C3822: RECEBIMENTO | D3822: 3155196 | E3822: CLAUDIO ROBERTO OTAVIO | F3822: 785 | G3822: 89.69 | H3822: 9 | I3822: 0 | J3822: GPA | K3822: =IF(J3822<>"",IF(OR(UPPER(J3822)="TERCEIRO",UPPER(J3822)="TERCEIRA"),"TERCEIRA",IF(UPPER(J3822)="GPA","GPA",J3822)),IF(LEFT(D3822,1)="T","TERCEIRA","GPA")) -> GPA
A3823: 8 | B3823: 1965 | C3823: ATIVIDADE OP. EMP. | D3823: 316516 | E3823: EDMAR AGUIAR VIANA | F3823: 1909 | G3823: 177.75 | H3823: 11 | I3823: 0 | J3823: GPA | K3823: =IF(J3823<>"",IF(OR(UPPER(J3823)="TERCEIRO",UPPER(J3823)="TERCEIRA"),"TERCEIRA",IF(UPPER(J3823)="GPA","GPA",J3823)),IF(LEFT(D3823,1)="T","TERCEIRA","GPA")) -> GPA
A3824: 8 | B3824: 1965 | C3824: ATIVIDADE OP. EMP. | D3824: 322452 | E3824: Givaldo Moreira Silva | F3824: 2709 | G3824: 159.88 | H3824: 17 | I3824: 0 | J3824: GPA | K3824: =IF(J3824<>"",IF(OR(UPPER(J3824)="TERCEIRO",UPPER(J3824)="TERCEIRA"),"TERCEIRA",IF(UPPER(J3824)="GPA","GPA",J3824)),IF(LEFT(D3824,1)="T","TERCEIRA","GPA")) -> GPA
A3825: 8 | B3825: 1965 | C3825: CARREGAMENTO | D3825: 322452 | E3825: Givaldo Moreira Silva | F3825: 63 | G3825: 4.38 | H3825: 14 | I3825: 0 | J3825: GPA | K3825: =IF(J3825<>"",IF(OR(UPPER(J3825)="TERCEIRO",UPPER(J3825)="TERCEIRA"),"TERCEIRA",IF(UPPER(J3825)="GPA","GPA",J3825)),IF(LEFT(D3825,1)="T","TERCEIRA","GPA")) -> GPA
A3826: 8 | B3826: 1965 | C3826: ATIVIDADE OP. EMP. | D3826: 324132 | E3826: ARIEL SOUZA OLIVEIRA | F3826: 1430 | G3826: 160.38 | H3826: 9 | I3826: 0 | J3826: GPA | K3826: =IF(J3826<>"",IF(OR(UPPER(J3826)="TERCEIRO",UPPER(J3826)="TERCEIRA"),"TERCEIRA",IF(UPPER(J3826)="GPA","GPA",J3826)),IF(LEFT(D3826,1)="T","TERCEIRA","GPA")) -> GPA
A3827: 8 | B3827: 1965 | C3827: RECEBIMENTO | D3827: 3353583 | E3827: GILBERTO NOVAES DOS SANTOS | F3827: 1095 | G3827: 113.3 | H3827: 10 | I3827: 0 | J3827: GPA | K3827: =IF(J3827<>"",IF(OR(UPPER(J3827)="TERCEIRO",UPPER(J3827)="TERCEIRA"),"TERCEIRA",IF(UPPER(J3827)="GPA","GPA",J3827)),IF(LEFT(D3827,1)="T","TERCEIRA","GPA")) -> GPA
A3828: 8 | B3828: 1965 | C3828: SEPARACAO | D3828: 3353583 | E3828: GILBERTO NOVAES DOS SANTOS | F3828: 61 | G3828: 0.84 | H3828: 73 | J3828: GPA | K3828: =IF(J3828<>"",IF(OR(UPPER(J3828)="TERCEIRO",UPPER(J3828)="TERCEIRA"),"TERCEIRA",IF(UPPER(J3828)="GPA","GPA",J3828)),IF(LEFT(D3828,1)="T","TERCEIRA","GPA")) -> GPA
A3829: 8 | B3829: 1965 | C3829: CARREGAMENTO | D3829: 335416 | E3829: Dourivaldo Dias De Oliveira | F3829: 103 | G3829: 32.15 | H3829: 3 | I3829: 0 | J3829: GPA | K3829: =IF(J3829<>"",IF(OR(UPPER(J3829)="TERCEIRO",UPPER(J3829)="TERCEIRA"),"TERCEIRA",IF(UPPER(J3829)="GPA","GPA",J3829)),IF(LEFT(D3829,1)="T","TERCEIRA","GPA")) -> GPA
A3830: 8 | B3830: 1965 | C3830: ATIVIDADE OP. EMP. | D3830: 33664 | E3830: Genivar Da Silva Muniz | F3830: 2656 | G3830: 180.94 | H3830: 15 | I3830: 0 | J3830: GPA | K3830: =IF(J3830<>"",IF(OR(UPPER(J3830)="TERCEIRO",UPPER(J3830)="TERCEIRA"),"TERCEIRA",IF(UPPER(J3830)="GPA","GPA",J3830)),IF(LEFT(D3830,1)="T","TERCEIRA","GPA")) -> GPA
A3831: 8 | B3831: 1965 | C3831: ATIVIDADE OP. EMP. | D3831: 339769 | E3831: CRISTIANO ANDRADE QUIRINO | F3831: 1536 | G3831: 168.16 | H3831: 9 | I3831: 0 | J3831: GPA | K3831: =IF(J3831<>"",IF(OR(UPPER(J3831)="TERCEIRO",UPPER(J3831)="TERCEIRA"),"TERCEIRA",IF(UPPER(J3831)="GPA","GPA",J3831)),IF(LEFT(D3831,1)="T","TERCEIRA","GPA")) -> GPA
A3832: 8 | B3832: 1965 | C3832: ATIVIDADE OP. EMP. | D3832: 344003 | E3832: ELIOMAR BARBOSA DA SILVA | F3832: 2869 | G3832: 163.9 | H3832: 18 | I3832: 0 | J3832: GPA | K3832: =IF(J3832<>"",IF(OR(UPPER(J3832)="TERCEIRO",UPPER(J3832)="TERCEIRA"),"TERCEIRA",IF(UPPER(J3832)="GPA","GPA",J3832)),IF(LEFT(D3832,1)="T","TERCEIRA","GPA")) -> GPA
A3833: 8 | B3833: 1965 | C3833: RECEBIMENTO | D3833: 346537 | E3833: MARISA APARECIDA DE MEIRA BARRETO | F3833: 1097 | G3833: 160.08 | H3833: 7 | I3833: 0 | J3833: GPA | K3833: =IF(J3833<>"",IF(OR(UPPER(J3833)="TERCEIRO",UPPER(J3833)="TERCEIRA"),"TERCEIRA",IF(UPPER(J3833)="GPA","GPA",J3833)),IF(LEFT(D3833,1)="T","TERCEIRA","GPA")) -> GPA
A3834: 8 | B3834: 1965 | C3834: PUXADA RECEB | D3834: 346641 | E3834: Edson Jose Do Nascimento | F3834: 266 | G3834: 11.77 | H3834: 23 | I3834: 0 | J3834: GPA | K3834: =IF(J3834<>"",IF(OR(UPPER(J3834)="TERCEIRO",UPPER(J3834)="TERCEIRA"),"TERCEIRA",IF(UPPER(J3834)="GPA","GPA",J3834)),IF(LEFT(D3834,1)="T","TERCEIRA","GPA")) -> GPA
A3835: 8 | B3835: 1965 | C3835: RECEBIMENTO | D3835: 346641 | E3835: Edson Jose Do Nascimento | F3835: 4347 | G3835: 132.01 | H3835: 33 | I3835: 0 | J3835: GPA | K3835: =IF(J3835<>"",IF(OR(UPPER(J3835)="TERCEIRO",UPPER(J3835)="TERCEIRA"),"TERCEIRA",IF(UPPER(J3835)="GPA","GPA",J3835)),IF(LEFT(D3835,1)="T","TERCEIRA","GPA")) -> GPA
A3836: 8 | B3836: 1965 | C3836: ATIVIDADE OP. EMP. | D3836: 352220 | E3836: MONICA FERNANDES ARAUJO CARNEIRO DE BARROS | F3836: 1364 | G3836: 161.78 | H3836: 8 | I3836: 0 | J3836: GPA | K3836: =IF(J3836<>"",IF(OR(UPPER(J3836)="TERCEIRO",UPPER(J3836)="TERCEIRA"),"TERCEIRA",IF(UPPER(J3836)="GPA","GPA",J3836)),IF(LEFT(D3836,1)="T","TERCEIRA","GPA")) -> GPA
A3837: 8 | B3837: 1965 | C3837: ATIVIDADE OP. EMP. | D3837: 352458 | E3837: Jose Antonio Mendes | F3837: 1487 | G3837: 118.83 | H3837: 13 | I3837: 0 | J3837: GPA | K3837: =IF(J3837<>"",IF(OR(UPPER(J3837)="TERCEIRO",UPPER(J3837)="TERCEIRA"),"TERCEIRA",IF(UPPER(J3837)="GPA","GPA",J3837)),IF(LEFT(D3837,1)="T","TERCEIRA","GPA")) -> GPA
A3838: 8 | B3838: 1965 | C3838: ATIVIDADE OP. EMP. | D3838: 3534685 | E3838: CEZAR AMORIM SOUSA | F3838: 2073 | G3838: 127.53 | H3838: 16 | I3838: 0 | J3838: GPA | K3838: =IF(J3838<>"",IF(OR(UPPER(J3838)="TERCEIRO",UPPER(J3838)="TERCEIRA"),"TERCEIRA",IF(UPPER(J3838)="GPA","GPA",J3838)),IF(LEFT(D3838,1)="T","TERCEIRA","GPA")) -> GPA
A3839: 8 | B3839: 1965 | C3839: PUXADA RECEB | D3839: 3536254 | E3839: Lucas Cruz Caldas | F3839: 270 | G3839: 50.53 | H3839: 5 | I3839: 0 | J3839: GPA | K3839: =IF(J3839<>"",IF(OR(UPPER(J3839)="TERCEIRO",UPPER(J3839)="TERCEIRA"),"TERCEIRA",IF(UPPER(J3839)="GPA","GPA",J3839)),IF(LEFT(D3839,1)="T","TERCEIRA","GPA")) -> GPA
A3840: 8 | B3840: 1965 | C3840: RECEBIMENTO | D3840: 3536254 | E3840: Lucas Cruz Caldas | F3840: 42 | G3840: 0.65 | H3840: 65 | I3840: 0 | J3840: GPA | K3840: =IF(J3840<>"",IF(OR(UPPER(J3840)="TERCEIRO",UPPER(J3840)="TERCEIRA"),"TERCEIRA",IF(UPPER(J3840)="GPA","GPA",J3840)),IF(LEFT(D3840,1)="T","TERCEIRA","GPA")) -> GPA
... A3873: 8 | B3873: 1965 | C3873: PUXADA RECEB | D3873: 4257901 | E3873: Jefferson Luiz Araujo Da Silva | F3873: 2405 | G3873: 121.91 | H3873: 20 | I3873: 0 | J3873: GPA | K3873: =IF(J3873<>"",IF(OR(UPPER(J3873)="TERCEIRO",UPPER(J3873)="TERCEIRA"),"TERCEIRA",IF(UPPER(J3873)="GPA","GPA",J3873)),IF(LEFT(D3873,1)="T","TERCEIRA","GPA")) -> GPA
A3874: 8 | B3874: 1965 | C3874: SEPARACAO | D3874: 4257901 | E3874: Jefferson Luiz Araujo Da Silva | F3874: 192 | G3874: 5.35 | H3874: 36 | J3874: GPA | K3874: =IF(J3874<>"",IF(OR(UPPER(J3874)="TERCEIRO",UPPER(J3874)="TERCEIRA"),"TERCEIRA",IF(UPPER(J3874)="GPA","GPA",J3874)),IF(LEFT(D3874,1)="T","TERCEIRA","GPA")) -> GPA
A3875: 8 | B3875: 1965 | C3875: CARREGAMENTO | D3875: 4261062 | E3875: ANTONIO BRUNO DOS SANTOS VIEIRA | F3875: 69 | G3875: 12.84 | H3875: 5 | I3875: 0 | J3875: GPA | K3875: =IF(J3875<>"",IF(OR(UPPER(J3875)="TERCEIRO",UPPER(J3875)="TERCEIRA"),"TERCEIRA",IF(UPPER(J3875)="GPA","GPA",J3875)),IF(LEFT(D3875,1)="T","TERCEIRA","GPA")) -> GPA
A3876: 8 | B3876: 1965 | C3876: ATIVIDADE OP. EMP. | D3876: 427308 | E3876: Jilson Stankievicz | F3876: 1775 | G3876: 153.31 | H3876: 12 | I3876: 0 | J3876: GPA | K3876: =IF(J3876<>"",IF(OR(UPPER(J3876)="TERCEIRO",UPPER(J3876)="TERCEIRA"),"TERCEIRA",IF(UPPER(J3876)="GPA","GPA",J3876)),IF(LEFT(D3876,1)="T","TERCEIRA","GPA")) -> GPA
A3877: 8 | B3877: 1965 | C3877: ATIVIDADE OP. EMP. | D3877: 442548 | E3877: FRANCILENE RODRIGUES DE SOUSA | F3877: 1772 | G3877: 197.07 | H3877: 9 | I3877: 0 | J3877: GPA | K3877: =IF(J3877<>"",IF(OR(UPPER(J3877)="TERCEIRO",UPPER(J3877)="TERCEIRA"),"TERCEIRA",IF(UPPER(J3877)="GPA","GPA",J3877)),IF(LEFT(D3877,1)="T","TERCEIRA","GPA")) -> GPA
A3878: 8 | B3878: 1965 | C3878: ATIVIDADE OP. EMP. | D3878: 4456297 | E3878: Claudinei Luna Diniz | F3878: 1306 | G3878: 104.83 | H3878: 12 | I3878: 0 | J3878: GPA | K3878: =IF(J3878<>"",IF(OR(UPPER(J3878)="TERCEIRO",UPPER(J3878)="TERCEIRA"),"TERCEIRA",IF(UPPER(J3878)="GPA","GPA",J3878)),IF(LEFT(D3878,1)="T","TERCEIRA","GPA")) -> GPA
A3879: 8 | B3879: 1965 | C3879: PUXADA RECEB | D3879: 4463714 | E3879: GILBERTO GIL SOARES CLEMENTE | F3879: 2 | G3879: 0.6 | H3879: 3 | I3879: 0 | J3879: GPA | K3879: =IF(J3879<>"",IF(OR(UPPER(J3879)="TERCEIRO",UPPER(J3879)="TERCEIRA"),"TERCEIRA",IF(UPPER(J3879)="GPA","GPA",J3879)),IF(LEFT(D3879,1)="T","TERCEIRA","GPA")) -> GPA
A3880: 8 | B3880: 1965 | C3880: RECEBIMENTO | D3880: 4463714 | E3880: GILBERTO GIL SOARES CLEMENTE | F3880: 3600 | G3880: 159.26 | H3880: 23 | I3880: 0 | J3880: GPA | K3880: =IF(J3880<>"",IF(OR(UPPER(J3880)="TERCEIRO",UPPER(J3880)="TERCEIRA"),"TERCEIRA",IF(UPPER(J3880)="GPA","GPA",J3880)),IF(LEFT(D3880,1)="T","TERCEIRA","GPA")) -> GPA
A3881: 8 | B3881: 1965 | C3881: PUXADA RECEB | D3881: 4467400 | E3881: Andrea Martins Da Silva | F3881: 2 | G3881: 9.36 | H3881: 0 | I3881: 0 | J3881: GPA | K3881: =IF(J3881<>"",IF(OR(UPPER(J3881)="TERCEIRO",UPPER(J3881)="TERCEIRA"),"TERCEIRA",IF(UPPER(J3881)="GPA","GPA",J3881)),IF(LEFT(D3881,1)="T","TERCEIRA","GPA")) -> GPA
A3882: 8 | B3882: 1965 | C3882: ATIVIDADE OP. EMP. | D3882: 4478452 | E3882: FERNANDO ANTONIO DA SILVA | F3882: 71 | G3882: 14.95 | H3882: 5 | I3882: 0 | J3882: GPA | K3882: =IF(J3882<>"",IF(OR(UPPER(J3882)="TERCEIRO",UPPER(J3882)="TERCEIRA"),"TERCEIRA",IF(UPPER(J3882)="GPA","GPA",J3882)),IF(LEFT(D3882,1)="T","TERCEIRA","GPA")) -> GPA
A3883: 8 | B3883: 1965 | C3883: PUXADA RECEB | D3883: 4478940 | E3883: Francisco Silva de Araujo | F3883: 170 | G3883: 28.43 | H3883: 6 | I3883: 0 | J3883: GPA | K3883: =IF(J3883<>"",IF(OR(UPPER(J3883)="TERCEIRO",UPPER(J3883)="TERCEIRA"),"TERCEIRA",IF(UPPER(J3883)="GPA","GPA",J3883)),IF(LEFT(D3883,1)="T","TERCEIRA","GPA")) -> GPA
A3884: 8 | B3884: 1965 | C3884: RECEBIMENTO | D3884: 4478940 | E3884: Francisco Silva de Araujo | F3884: 4 | G3884: 3.72 | H3884: 1 | I3884: 0 | J3884: GPA | K3884: =IF(J3884<>"",IF(OR(UPPER(J3884)="TERCEIRO",UPPER(J3884)="TERCEIRA"),"TERCEIRA",IF(UPPER(J3884)="GPA","GPA",J3884)),IF(LEFT(D3884,1)="T","TERCEIRA","GPA")) -> GPA
A3885: 8 | B3885: 1965 | C3885: PUXADA RECEB | D3885: 449713 | E3885: Osmar Francisco Da Cunha | F3885: 2168 | G3885: 114.39 | H3885: 19 | I3885: 0 | J3885: GPA | K3885: =IF(J3885<>"",IF(OR(UPPER(J3885)="TERCEIRO",UPPER(J3885)="TERCEIRA"),"TERCEIRA",IF(UPPER(J3885)="GPA","GPA",J3885)),IF(LEFT(D3885,1)="T","TERCEIRA","GPA")) -> GPA
A3886: 8 | B3886: 1965 | C3886: SEPARACAO | D3886: 449713 | E3886: Osmar Francisco Da Cunha | F3886: 66 | G3886: 1.72 | H3886: 38 | J3886: GPA | K3886: =IF(J3886<>"",IF(OR(UPPER(J3886)="TERCEIRO",UPPER(J3886)="TERCEIRA"),"TERCEIRA",IF(UPPER(J3886)="GPA","GPA",J3886)),IF(LEFT(D3886,1)="T","TERCEIRA","GPA")) -> GPA
A3887: 8 | B3887: 1965 | C3887: SEPARACAO | D3887: 4527739 | E3887: ELANE CRISTINA DA SILVA MELO | F3887: 523 | G3887: 10.94 | H3887: 48 | J3887: GPA | K3887: =IF(J3887<>"",IF(OR(UPPER(J3887)="TERCEIRO",UPPER(J3887)="TERCEIRA"),"TERCEIRA",IF(UPPER(J3887)="GPA","GPA",J3887)),IF(LEFT(D3887,1)="T","TERCEIRA","GPA")) -> GPA
A3888: 8 | B3888: 1965 | C3888: ATIVIDADE OP. EMP. | D3888: 454854 | E3888: Valquiria Da Silva Ribeiro | F3888: 583 | G3888: 86.04 | H3888: 7 | I3888: 0 | J3888: GPA | K3888: =IF(J3888<>"",IF(OR(UPPER(J3888)="TERCEIRO",UPPER(J3888)="TERCEIRA"),"TERCEIRA",IF(UPPER(J3888)="GPA","GPA",J3888)),IF(LEFT(D3888,1)="T","TERCEIRA","GPA")) -> GPA
A3889: 8 | B3889: 1965 | C3889: ATIVIDADE OP. EMP. | D3889: 456332 | E3889: DAMIAO RUFINO | F3889: 37 | G3889: 21.8 | H3889: 2 | I3889: 0 | J3889: GPA | K3889: =IF(J3889<>"",IF(OR(UPPER(J3889)="TERCEIRO",UPPER(J3889)="TERCEIRA"),"TERCEIRA",IF(UPPER(J3889)="GPA","GPA",J3889)),IF(LEFT(D3889,1)="T","TERCEIRA","GPA")) -> GPA
A3890: 8 | B3890: 1965 | C3890: CARREGAMENTO | D3890: 4575156 | E3890: Homero Anilis | F3890: 358 | G3890: 15.62 | H3890: 23 | I3890: 0 | J3890: GPA | K3890: =IF(J3890<>"",IF(OR(UPPER(J3890)="TERCEIRO",UPPER(J3890)="TERCEIRA"),"TERCEIRA",IF(UPPER(J3890)="GPA","GPA",J3890)),IF(LEFT(D3890,1)="T","TERCEIRA","GPA")) -> GPA
A3891: 8 | B3891: 1965 | C3891: CARREGAMENTO | D3891: 4576837 | E3891: Elias Jose De Araujo | F3891: 1115 | G3891: 52.95 | H3891: 21 | I3891: 0 | J3891: GPA | K3891: =IF(J3891<>"",IF(OR(UPPER(J3891)="TERCEIRO",UPPER(J3891)="TERCEIRA"),"TERCEIRA",IF(UPPER(J3891)="GPA","GPA",J3891)),IF(LEFT(D3891,1)="T","TERCEIRA","GPA")) -> GPA
A3892: 8 | B3892: 1965 | C3892: ATIVIDADE OP. EMP. | D3892: 4577418 | E3892: Edgar Veras Santos | F3892: 1941 | G3892: 143.41 | H3892: 14 | I3892: 0 | J3892: GPA | K3892: =IF(J3892<>"",IF(OR(UPPER(J3892)="TERCEIRO",UPPER(J3892)="TERCEIRA"),"TERCEIRA",IF(UPPER(J3892)="GPA","GPA",J3892)),IF(LEFT(D3892,1)="T","TERCEIRA","GPA")) -> GPA
A3893: 8 | B3893: 1965 | C3893: ATIVIDADE OP. EMP. | D3893: 4578775 | E3893: JOSE INACIO SANTOS DE OLIVEIRA | F3893: 1790 | G3893: 212.91 | H3893: 8 | I3893: 0 | J3893: GPA | K3893: =IF(J3893<>"",IF(OR(UPPER(J3893)="TERCEIRO",UPPER(J3893)="TERCEIRA"),"TERCEIRA",IF(UPPER(J3893)="GPA","GPA",J3893)),IF(LEFT(D3893,1)="T","TERCEIRA","GPA")) -> GPA
A3894: 8 | B3894: 1965 | C3894: CARREGAMENTO | D3894: 4596943 | E3894: Bruno Alves Dos Santos | F3894: 600 | G3894: 34.24 | H3894: 18 | I3894: 0 | J3894: GPA | K3894: =IF(J3894<>"",IF(OR(UPPER(J3894)="TERCEIRO",UPPER(J3894)="TERCEIRA"),"TERCEIRA",IF(UPPER(J3894)="GPA","GPA",J3894)),IF(LEFT(D3894,1)="T","TERCEIRA","GPA")) -> GPA
A3895: 8 | B3895: 1965 | C3895: SEPARACAO | D3895: 4864824 | E3895: Carlos Vinicius Carmo | F3895: 576 | G3895: 20.76 | H3895: 28 | J3895: GPA | K3895: =IF(J3895<>"",IF(OR(UPPER(J3895)="TERCEIRO",UPPER(J3895)="TERCEIRA"),"TERCEIRA",IF(UPPER(J3895)="GPA","GPA",J3895)),IF(LEFT(D3895,1)="T","TERCEIRA","GPA")) -> GPA
A3896: 8 | B3896: 1965 | C3896: CARREGAMENTO | D3896: 4864905 | E3896: EDIMAR DE OLIVEIRA DA SILVA | F3896: 1069 | G3896: 62.85 | H3896: 17 | I3896: 0 | J3896: GPA | K3896: =IF(J3896<>"",IF(OR(UPPER(J3896)="TERCEIRO",UPPER(J3896)="TERCEIRA"),"TERCEIRA",IF(UPPER(J3896)="GPA","GPA",J3896)),IF(LEFT(D3896,1)="T","TERCEIRA","GPA")) -> GPA
A3897: 8 | B3897: 1965 | C3897: ATIVIDADE OP. EMP. | D3897: 495124 | E3897: Maria Ionete Martins | F3897: 1265 | G3897: 178.73 | H3897: 7 | I3897: 0 | J3897: GPA | K3897: =IF(J3897<>"",IF(OR(UPPER(J3897)="TERCEIRO",UPPER(J3897)="TERCEIRA"),"TERCEIRA",IF(UPPER(J3897)="GPA","GPA",J3897)),IF(LEFT(D3897,1)="T","TERCEIRA","GPA")) -> GPA
A3898: 8 | B3898: 1965 | C3898: CARREGAMENTO | D3898: 4979559 | E3898: WILLIAM DOS SANTOS CAETANO | F3898: 196 | G3898: 16.43 | H3898: 12 | I3898: 0 | J3898: GPA | K3898: =IF(J3898<>"",IF(OR(UPPER(J3898)="TERCEIRO",UPPER(J3898)="TERCEIRA"),"TERCEIRA",IF(UPPER(J3898)="GPA","GPA",J3898)),IF(LEFT(D3898,1)="T","TERCEIRA","GPA")) -> GPA
A3899: 8 | B3899: 1965 | C3899: RECEBIMENTO | D3899: 4979559 | E3899: WILLIAM DOS SANTOS CAETANO | F3899: 1 | G3899: 0.68 | H3899: 1 | I3899: 0 | J3899: GPA | K3899: =IF(J3899<>"",IF(OR(UPPER(J3899)="TERCEIRO",UPPER(J3899)="TERCEIRA"),"TERCEIRA",IF(UPPER(J3899)="GPA","GPA",J3899)),IF(LEFT(D3899,1)="T","TERCEIRA","GPA")) -> GPA
A3900: 8 | B3900: 1965 | C3900: SEPARACAO | D3900: 4979559 | E3900: WILLIAM DOS SANTOS CAETANO | F3900: 757 | G3900: 18.14 | H3900: 42 | J3900: GPA | K3900: =IF(J3900<>"",IF(OR(UPPER(J3900)="TERCEIRO",UPPER(J3900)="TERCEIRA"),"TERCEIRA",IF(UPPER(J3900)="GPA","GPA",J3900)),IF(LEFT(D3900,1)="T","TERCEIRA","GPA")) -> GPA
A3901: 8 | B3901: 1965 | C3901: SEPARACAO | D3901: 4989040 | E3901: RAFAEL DE CASTRO PEREIRA | F3901: 3420 | G3901: 90.45 | H3901: 38 | J3901: GPA | K3901: =IF(J3901<>"",IF(OR(UPPER(J3901)="TERCEIRO",UPPER(J3901)="TERCEIRA"),"TERCEIRA",IF(UPPER(J3901)="GPA","GPA",J3901)),IF(LEFT(D3901,1)="T","TERCEIRA","GPA")) -> GPA
A3902: 8 | B3902: 1965 | C3902: ATIVIDADE OP. EMP. | D3902: 4990137 | E3902: Erivaldo Oliveira Da Silva | F3902: 1942 | G3902: 152.94 | H3902: 13 | I3902: 0 | J3902: GPA | K3902: =IF(J3902<>"",IF(OR(UPPER(J3902)="TERCEIRO",UPPER(J3902)="TERCEIRA"),"TERCEIRA",IF(UPPER(J3902)="GPA","GPA",J3902)),IF(LEFT(D3902,1)="T","TERCEIRA","GPA")) -> GPA
A3903: 8 | B3903: 1965 | C3903: SEPARACAO | D3903: 5001838 | E3903: Debora Vieira Ferreira | F3903: 1384 | G3903: 13.56 | H3903: 102 | J3903: GPA | K3903: =IF(J3903<>"",IF(OR(UPPER(J3903)="TERCEIRO",UPPER(J3903)="TERCEIRA"),"TERCEIRA",IF(UPPER(J3903)="GPA","GPA",J3903)),IF(LEFT(D3903,1)="T","TERCEIRA","GPA")) -> GPA
A3904: 8 | B3904: 1965 | C3904: CARREGAMENTO | D3904: 500233 | E3904: Sidenilton Santos Da Conceicao | F3904: 149 | G3904: 19.14 | H3904: 8 | I3904: 0 | J3904: GPA | K3904: =IF(J3904<>"",IF(OR(UPPER(J3904)="TERCEIRO",UPPER(J3904)="TERCEIRA"),"TERCEIRA",IF(UPPER(J3904)="GPA","GPA",J3904)),IF(LEFT(D3904,1)="T","TERCEIRA","GPA")) -> GPA
A3905: 8 | B3905: 1965 | C3905: SEPARACAO | D3905: 500233 | E3905: Sidenilton Santos Da Conceicao | F3905: 561 | G3905: 15.8 | H3905: 36 | J3905: GPA | K3905: =IF(J3905<>"",IF(OR(UPPER(J3905)="TERCEIRO",UPPER(J3905)="TERCEIRA"),"TERCEIRA",IF(UPPER(J3905)="GPA","GPA",J3905)),IF(LEFT(D3905,1)="T","TERCEIRA","GPA")) -> GPA
A3906: 8 | B3906: 1965 | C3906: SEPARACAO | D3906: 5011175 | E3906: Clevisson Santos Do Nascimento | F3906: 5363 | G3906: 113.05 | H3906: 47 | J3906: GPA | K3906: =IF(J3906<>"",IF(OR(UPPER(J3906)="TERCEIRO",UPPER(J3906)="TERCEIRA"),"TERCEIRA",IF(UPPER(J3906)="GPA","GPA",J3906)),IF(LEFT(D3906,1)="T","TERCEIRA","GPA")) -> GPA
A3907: 8 | B3907: 1965 | C3907: ATIVIDADE OP. EMP. | D3907: 5061148 | E3907: EDUARDO HENRIQUE BORGES | F3907: 3754 | G3907: 199.57 | H3907: 19 | I3907: 0 | J3907: GPA | K3907: =IF(J3907<>"",IF(OR(UPPER(J3907)="TERCEIRO",UPPER(J3907)="TERCEIRA"),"TERCEIRA",IF(UPPER(J3907)="GPA","GPA",J3907)),IF(LEFT(D3907,1)="T","TERCEIRA","GPA")) -> GPA
A3908: 8 | B3908: 1965 | C3908: CARREGAMENTO | D3908: 5066190 | E3908: Iderval Dias Feitosa | F3908: 2791 | G3908: 56.42 | H3908: 49 | I3908: 0 | J3908: GPA | K3908: =IF(J3908<>"",IF(OR(UPPER(J3908)="TERCEIRO",UPPER(J3908)="TERCEIRA"),"TERCEIRA",IF(UPPER(J3908)="GPA","GPA",J3908)),IF(LEFT(D3908,1)="T","TERCEIRA","GPA")) -> GPA
A3909: 8 | B3909: 1965 | C3909: PUXADA RECEB | D3909: 5066190 | E3909: Iderval Dias Feitosa | F3909: 3 | G3909: 0.22 | H3909: 14 | I3909: 0 | J3909: GPA | K3909: =IF(J3909<>"",IF(OR(UPPER(J3909)="TERCEIRO",UPPER(J3909)="TERCEIRA"),"TERCEIRA",IF(UPPER(J3909)="GPA","GPA",J3909)),IF(LEFT(D3909,1)="T","TERCEIRA","GPA")) -> GPA
A3910: 8 | B3910: 1965 | C3910: ATIVIDADE OP. EMP. | D3910: 5081696 | E3910: CELIO JOSE DOS SANTOS | F3910: 1933 | G3910: 206.02 | H3910: 9 | I3910: 0 | J3910: GPA | K3910: =IF(J3910<>"",IF(OR(UPPER(J3910)="TERCEIRO",UPPER(J3910)="TERCEIRA"),"TERCEIRA",IF(UPPER(J3910)="GPA","GPA",J3910)),IF(LEFT(D3910,1)="T","TERCEIRA","GPA")) -> GPA
A3911: 8 | B3911: 1965 | C3911: RECEBIMENTO | D3911: 5113687 | E3911: Kawan Dickson Jesus Dos Santos | F3911: 10 | G3911: 0.19 | H3911: 53 | I3911: 0 | J3911: GPA | K3911: =IF(J3911<>"",IF(OR(UPPER(J3911)="TERCEIRO",UPPER(J3911)="TERCEIRA"),"TERCEIRA",IF(UPPER(J3911)="GPA","GPA",J3911)),IF(LEFT(D3911,1)="T","TERCEIRA","GPA")) -> GPA
A3912: 8 | B3912: 1965 | C3912: ATIVIDADE OP. EMP. | D3912: 5115418 | E3912: Diego Rodrigues Hidalgo | F3912: 5159 | G3912: 168.47 | H3912: 31 | I3912: 0 | J3912: GPA | K3912: =IF(J3912<>"",IF(OR(UPPER(J3912)="TERCEIRO",UPPER(J3912)="TERCEIRA"),"TERCEIRA",IF(UPPER(J3912)="GPA","GPA",J3912)),IF(LEFT(D3912,1)="T","TERCEIRA","GPA")) -> GPA
A3913: 8 | B3913: 1965 | C3913: CARREGAMENTO | D3913: 5122490 | E3913: Luciano Silva Lopes | F3913: 1980 | G3913: 55.45 | H3913: 36 | I3913: 0 | J3913: GPA | K3913: =IF(J3913<>"",IF(OR(UPPER(J3913)="TERCEIRO",UPPER(J3913)="TERCEIRA"),"TERCEIRA",IF(UPPER(J3913)="GPA","GPA",J3913)),IF(LEFT(D3913,1)="T","TERCEIRA","GPA")) -> GPA
A3914: 8 | B3914: 1965 | C3914: PUXADA RECEB | D3914: 5122490 | E3914: Luciano Silva Lopes | F3914: 2 | G3914: 0.58 | H3914: 3 | I3914: 0 | J3914: GPA | K3914: =IF(J3914<>"",IF(OR(UPPER(J3914)="TERCEIRO",UPPER(J3914)="TERCEIRA"),"TERCEIRA",IF(UPPER(J3914)="GPA","GPA",J3914)),IF(LEFT(D3914,1)="T","TERCEIRA","GPA")) -> GPA
A3915: 8 | B3915: 1965 | C3915: PUXADA RECEB | D3915: 5128552 | E3915: Vinicius Azevedo Do Carmo | F3915: 100 | G3915: 103.74 | H3915: 1 | I3915: 0 | J3915: GPA | K3915: =IF(J3915<>"",IF(OR(UPPER(J3915)="TERCEIRO",UPPER(J3915)="TERCEIRA"),"TERCEIRA",IF(UPPER(J3915)="GPA","GPA",J3915)),IF(LEFT(D3915,1)="T","TERCEIRA","GPA")) -> GPA
A3916: 8 | B3916: 1965 | C3916: ATIVIDADE OP. EMP. | D3916: 513395 | E3916: Uberlandia De Lima E Silva | F3916: 1053 | G3916: 176.92 | H3916: 6 | I3916: 0 | J3916: GPA | K3916: =IF(J3916<>"",IF(OR(UPPER(J3916)="TERCEIRO",UPPER(J3916)="TERCEIRA"),"TERCEIRA",IF(UPPER(J3916)="GPA","GPA",J3916)),IF(LEFT(D3916,1)="T","TERCEIRA","GPA")) -> GPA
A3917: 8 | B3917: 1965 | C3917: CARREGAMENTO | D3917: 5144280 | E3917: Tiago Farias Da Costa | F3917: 206 | G3917: 34.29 | H3917: 6 | I3917: 0 | J3917: GPA | K3917: =IF(J3917<>"",IF(OR(UPPER(J3917)="TERCEIRO",UPPER(J3917)="TERCEIRA"),"TERCEIRA",IF(UPPER(J3917)="GPA","GPA",J3917)),IF(LEFT(D3917,1)="T","TERCEIRA","GPA")) -> GPA
A3918: 8 | B3918: 1965 | C3918: SEPARACAO | D3918: 5144280 | E3918: Tiago Farias Da Costa | F3918: 75 | G3918: 4.62 | H3918: 16 | J3918: GPA | K3918: =IF(J3918<>"",IF(OR(UPPER(J3918)="TERCEIRO",UPPER(J3918)="TERCEIRA"),"TERCEIRA",IF(UPPER(J3918)="GPA","GPA",J3918)),IF(LEFT(D3918,1)="T","TERCEIRA","GPA")) -> GPA
A3919: 8 | B3919: 1965 | C3919: PUXADA RECEB | D3919: 5144485 | E3919: Ezequiel Teodoro Batista | F3919: 480 | G3919: 24.47 | H3919: 20 | I3919: 0 | J3919: GPA | K3919: =IF(J3919<>"",IF(OR(UPPER(J3919)="TERCEIRO",UPPER(J3919)="TERCEIRA"),"TERCEIRA",IF(UPPER(J3919)="GPA","GPA",J3919)),IF(LEFT(D3919,1)="T","TERCEIRA","GPA")) -> GPA
A3920: 8 | B3920: 1965 | C3920: PUXADA RECEB | D3920: 5209323 | E3920: ROBENILDO FRANCISCO DA SILVA | F3920: 7 | G3920: 8.23 | H3920: 1 | I3920: 0 | J3920: GPA | K3920: =IF(J3920<>"",IF(OR(UPPER(J3920)="TERCEIRO",UPPER(J3920)="TERCEIRA"),"TERCEIRA",IF(UPPER(J3920)="GPA","GPA",J3920)),IF(LEFT(D3920,1)="T","TERCEIRA","GPA")) -> GPA
A3921: 8 | B3921: 1965 | C3921: RECEBIMENTO | D3921: 5209323 | E3921: ROBENILDO FRANCISCO DA SILVA | F3921: 7 | G3921: 8.71 | H3921: 1 | I3921: 0 | J3921: GPA | K3921: =IF(J3921<>"",IF(OR(UPPER(J3921)="TERCEIRO",UPPER(J3921)="TERCEIRA"),"TERCEIRA",IF(UPPER(J3921)="GPA","GPA",J3921)),IF(LEFT(D3921,1)="T","TERCEIRA","GPA")) -> GPA
A3922: 8 | B3922: 1965 | C3922: SEPARACAO | D3922: 5223350 | E3922: Salvandir Jose Pereira | F3922: 323 | G3922: 4.2 | H3922: 77 | J3922: GPA | K3922: =IF(J3922<>"",IF(OR(UPPER(J3922)="TERCEIRO",UPPER(J3922)="TERCEIRA"),"TERCEIRA",IF(UPPER(J3922)="GPA","GPA",J3922)),IF(LEFT(D3922,1)="T","TERCEIRA","GPA")) -> GPA
A3923: 8 | B3923: 1965 | C3923: CARREGAMENTO | D3923: 5224349 | E3923: ALISSON SELES DA SILVA | F3923: 99 | G3923: 11.03 | H3923: 9 | I3923: 0 | J3923: GPA | K3923: =IF(J3923<>"",IF(OR(UPPER(J3923)="TERCEIRO",UPPER(J3923)="TERCEIRA"),"TERCEIRA",IF(UPPER(J3923)="GPA","GPA",J3923)),IF(LEFT(D3923,1)="T","TERCEIRA","GPA")) -> GPA
A3924: 8 | B3924: 1965 | C3924: PUXADA RECEB | D3924: 5235588 | E3924: WELLINGTON LUIZ DE OLIVEIRA | F3924: 211 | G3924: 23.41 | H3924: 9 | I3924: 0 | J3924: GPA | K3924: =IF(J3924<>"",IF(OR(UPPER(J3924)="TERCEIRO",UPPER(J3924)="TERCEIRA"),"TERCEIRA",IF(UPPER(J3924)="GPA","GPA",J3924)),IF(LEFT(D3924,1)="T","TERCEIRA","GPA")) -> GPA
A3925: 8 | B3925: 1965 | C3925: CARREGAMENTO | D3925: 5262496 | E3925: Daniel De Santana | F3925: 21 | G3925: 2.18 | H3925: 10 | I3925: 0 | J3925: GPA | K3925: =IF(J3925<>"",IF(OR(UPPER(J3925)="TERCEIRO",UPPER(J3925)="TERCEIRA"),"TERCEIRA",IF(UPPER(J3925)="GPA","GPA",J3925)),IF(LEFT(D3925,1)="T","TERCEIRA","GPA")) -> GPA
A3926: 8 | B3926: 1965 | C3926: CARREGAMENTO | D3926: 5273862 | E3926: Reinilson Santos Conceicao | F3926: 100 | G3926: 5.41 | H3926: 18 | I3926: 0 | J3926: GPA | K3926: =IF(J3926<>"",IF(OR(UPPER(J3926)="TERCEIRO",UPPER(J3926)="TERCEIRA"),"TERCEIRA",IF(UPPER(J3926)="GPA","GPA",J3926)),IF(LEFT(D3926,1)="T","TERCEIRA","GPA")) -> GPA
A3927: 8 | B3927: 1965 | C3927: SEPARACAO | D3927: 5285941 | E3927: Marcos Vinicius Ferreira Dourado | F3927: 79 | G3927: 2.03 | H3927: 39 | J3927: GPA | K3927: =IF(J3927<>"",IF(OR(UPPER(J3927)="TERCEIRO",UPPER(J3927)="TERCEIRA"),"TERCEIRA",IF(UPPER(J3927)="GPA","GPA",J3927)),IF(LEFT(D3927,1)="T","TERCEIRA","GPA")) -> GPA
A3928: 8 | B3928: 1965 | C3928: ATIVIDADE OP. EMP. | D3928: 5314739 | E3928: Jeferson Ferreira Idalino | F3928: 1861 | G3928: 179.63 | H3928: 10 | I3928: 0 | J3928: GPA | K3928: =IF(J3928<>"",IF(OR(UPPER(J3928)="TERCEIRO",UPPER(J3928)="TERCEIRA"),"TERCEIRA",IF(UPPER(J3928)="GPA","GPA",J3928)),IF(LEFT(D3928,1)="T","TERCEIRA","GPA")) -> GPA
A3929: 8 | B3929: 1965 | C3929: ATIVIDADE OP. EMP. | D3929: 5321450 | E3929: FELIPE COPE CAMPOS | F3929: 1723 | G3929: 160.74 | H3929: 11 | I3929: 0 | J3929: GPA | K3929: =IF(J3929<>"",IF(OR(UPPER(J3929)="TERCEIRO",UPPER(J3929)="TERCEIRA"),"TERCEIRA",IF(UPPER(J3929)="GPA","GPA",J3929)),IF(LEFT(D3929,1)="T","TERCEIRA","GPA")) -> GPA
A3930: 8 | B3930: 1965 | C3930: CARREGAMENTO | D3930: 5332095 | E3930: Lucas Da Silva Gaspar Lopes | F3930: 197 | G3930: 18.43 | H3930: 11 | I3930: 0 | J3930: GPA | K3930: =IF(J3930<>"",IF(OR(UPPER(J3930)="TERCEIRO",UPPER(J3930)="TERCEIRA"),"TERCEIRA",IF(UPPER(J3930)="GPA","GPA",J3930)),IF(LEFT(D3930,1)="T","TERCEIRA","GPA")) -> GPA
A3931: 8 | B3931: 1965 | C3931: ATIVIDADE OP. EMP. | D3931: 5342112 | E3931: Marcio Francisco De Souza | F3931: 2098 | G3931: 145.57 | H3931: 14 | I3931: 0 | J3931: GPA | K3931: =IF(J3931<>"",IF(OR(UPPER(J3931)="TERCEIRO",UPPER(J3931)="TERCEIRA"),"TERCEIRA",IF(UPPER(J3931)="GPA","GPA",J3931)),IF(LEFT(D3931,1)="T","TERCEIRA","GPA")) -> GPA
A3932: 8 | B3932: 1965 | C3932: CARREGAMENTO | D3932: 5351545 | E3932: GUSTAVO GUSTAVO MONTEIRO ARRUDAS | F3932: 393 | G3932: 49.77 | H3932: 8 | I3932: 0 | J3932: GPA | K3932: =IF(J3932<>"",IF(OR(UPPER(J3932)="TERCEIRO",UPPER(J3932)="TERCEIRA"),"TERCEIRA",IF(UPPER(J3932)="GPA","GPA",J3932)),IF(LEFT(D3932,1)="T","TERCEIRA","GPA")) -> GPA
A3933: 8 | B3933: 1965 | C3933: SEPARACAO | D3933: 5356768 | E3933: Daniel Santos Soares | F3933: 2813 | G3933: 103.78 | H3933: 27 | J3933: GPA | K3933: =IF(J3933<>"",IF(OR(UPPER(J3933)="TERCEIRO",UPPER(J3933)="TERCEIRA"),"TERCEIRA",IF(UPPER(J3933)="GPA","GPA",J3933)),IF(LEFT(D3933,1)="T","TERCEIRA","GPA")) -> GPA
A3934: 8 | B3934: 1965 | C3934: SEPARACAO | D3934: 5358450 | E3934: Willians Xavier Da Silva | F3934: 915 | G3934: 35.81 | H3934: 26 | J3934: GPA | K3934: =IF(J3934<>"",IF(OR(UPPER(J3934)="TERCEIRO",UPPER(J3934)="TERCEIRA"),"TERCEIRA",IF(UPPER(J3934)="GPA","GPA",J3934)),IF(LEFT(D3934,1)="T","TERCEIRA","GPA")) -> GPA
...

Sheet Din
A3: MES | B3: CD_PRINCIPAL | C3: Contagem Distinta de USUARIO
A4: 7 | B4: 409 | C4: 147
A5: 7 | B5: 930 | C5: 177
A6: 7 | B6: 1942 | C6: 74
A7: 7 | B7: 1953 | C7: 51
A8: 7 | B8: 1974 | C8: 30
A9: 7 | B9: 1979 | C9: 17
A10: 7 | B10: 7801 | C10: 292
A11: 7 Total | C11: 788
A12: 8 | B12: 409 | C12: 148
A13: 8 | B13: 930 | C13: 170
A14: 8 | B14: 1942 | C14: 78
A15: 8 | B15: 1953 | C15: 50
A16: 8 | B16: 1965 | C16: 269
A17: 8 | B17: 1974 | C17: 26
A18: 8 | B18: 1979 | C18: 19
A19: 8 | B19: 7801 | C19: 45
A20: 8 Total | C20: 805
A21: Total Geral | C21: 901
